Workbook
Name Categorias: controle!#REF!

Sheet Pesquisa Global
A1: PESQUISA DE EQUIPAMENTOS | X1: Tipos | Y1: Marcas | Z1: Departamentos | AA1: Status | AB1: Modos
X2: Todos | Y2: Todas | Z2: Todos | AA2: Todos | AB2: Contém
X3: Adaptador de rede | Y3: Apple | Z3: Administração | AA3: BOM | AB3: Começa com
A4: PESQUISAR | X4: Celular | Y4: BROTHER | Z4: Administrativo | AA4: Não informado | AB4: Exata
X5: Componente | Y5: C3 Tech (Distribuído por Coletek) | Z5: Almoxarifado | AA5: OK
A6: TIPO DE EQUIPAMENTO | D6: MARCA | G6: DEPARTAMENTO | J6: STATUS | M6: CORRESPONDÊNCIA | X6: Desktop | Y6: CISCO | Z6: Áudio | AA6: RUIM
A7: Todos | D7: Todas | G7: Todos | J7: Todos | M7: Contém | X7: Equipamento de rede | Y7: Dell | Z7: AUDIO HIBRIDA
X8: Fonte/Conector | Y8: DELL | Z8: Cabine OFF
A9: EQUIPAMENTOS ENCONTRADOS | D9: DESKTOPS / MICROS | G9: MONITORES | J9: OUTROS EQUIPAMENTOS | M9: RESPONSÁVEIS | X9: Impressora | Y9: EPSON | Z9: Camarim
A10: {=_xlfn.LET(_xlpm.q,TRIM($B$4),_xlpm.tp,$A$7,_xlpm.mk,$D$7,_xlpm.dp,$G$7,_xlpm.st,$J$7,_xlpm.md,$M$7,_xlpm.b,'Índice Equipamentos'!$A$2:$T$563,_xlpm.txt,INDEX(_xlpm.b,,20)&"",_xlpm.oq,IF(_xlpm.q="",1,_xlfn.SWITCH(_xlpm.md,"Exata",LOWER(_xlpm.txt)=LOWER(_xlpm.q),"Começa com",LEFT(LOWER(_xlpm.txt),LEN(_xlpm.q))=LOWER(_xlpm.q),ISNUMBER(SEARCH(_xlpm.q,_xlpm.txt)))),_xlpm.ot,IF(_xlpm.tp="Todos",1,--(INDEX(_xlpm.b,,1)=_xlpm.tp)),_xlpm.om,IF(_xlpm.mk="Todas",1,--(INDEX(_xlpm.b,,7)=_xlpm.mk)),_xlpm.od,IF(_xlpm.dp="Todos",1,--(INDEX(_xlpm.b,,4)=_xlpm.dp)),_xlpm.os,IF(_xlpm.st="Todos",1,--(INDEX(_xlpm.b,,10)=_xlpm.st)),_xlpm.ok,_xlpm.oq*_xlpm.ot*_xlpm.om*_xlpm.od*_xlpm.os,SUM(--_xlpm.ok))} -> 1 | D10: {=_xlfn.LET(_xlpm.q,TRIM($B$4),_xlpm.tp,$A$7,_xlpm.mk,$D$7,_xlpm.dp,$G$7,_xlpm.st,$J$7,_xlpm.md,$M$7,_xlpm.b,'Índice Equipamentos'!$A$2:$T$563,_xlpm.txt,INDEX(_xlpm.b,,20)&"",_xlpm.oq,IF(_xlpm.q="",1,_xlfn.SWITCH(_xlpm.md,"Exata",LOWER(_xlpm.txt)=LOWER(_xlpm.q),"Começa com",LEFT(LOWER(_xlpm.txt),LEN(_xlpm.q))=LOWER(_xlpm.q),ISNUMBER(SEARCH(_xlpm.q,_xlpm.txt)))),_xlpm.ot,IF(_xlpm.tp="Todos",1,--(INDEX(_xlpm.b,,1)=_xlpm.tp)),_xlpm.om,IF(_xlpm.mk="Todas",1,--(INDEX(_xlpm.b,,7)=_xlpm.mk)),_xlpm.od,IF(_xlpm.dp="Todos",1,--(INDEX(_xlpm.b,,4)=_xlpm.dp)),_xlpm.os,IF(_xlpm.st="Todos",1,--(INDEX(_xlpm.b,,10)=_xlpm.st)),_xlpm.ok,_xlpm.oq*_xlpm.ot*_xlpm.om*_xlpm.od*_xlpm.os,SUM(--_xlpm.ok*--(INDEX(_xlpm.b,,1)="Desktop")))} -> 196 | G10: {=_xlfn.LET(_xlpm.q,TRIM($B$4),_xlpm.tp,$A$7,_xlpm.mk,$D$7,_xlpm.dp,$G$7,_xlpm.st,$J$7,_xlpm.md,$M$7,_xlpm.b,'Índice Equipamentos'!$A$2:$T$563,_xlpm.txt,INDEX(_xlpm.b,,20)&"",_xlpm.oq,IF(_xlpm.q="",1,_xlfn.SWITCH(_xlpm.md,"Exata",LOWER(_xlpm.txt)=LOWER(_xlpm.q),"Começa com",LEFT(LOWER(_xlpm.txt),LEN(_xlpm.q))=LOWER(_xlpm.q),ISNUMBER(SEARCH(_xlpm.q,_xlpm.txt)))),_xlpm.ot,IF(_xlpm.tp="Todos",1,--(INDEX(_xlpm.b,,1)=_xlpm.tp)),_xlpm.om,IF(_xlpm.mk="Todas",1,--(INDEX(_xlpm.b,,7)=_xlpm.mk)),_xlpm.od,IF(_xlpm.dp="Todos",1,--(INDEX(_xlpm.b,,4)=_xlpm.dp)),_xlpm.os,IF(_xlpm.st="Todos",1,--(INDEX(_xlpm.b,,10)=_xlpm.st)),_xlpm.ok,_xlpm.oq*_xlpm.ot*_xlpm.om*_xlpm.od*_xlpm.os,SUM(--_xlpm.ok*--(INDEX(_xlpm.b,,1)="Monitor")))} -> 235 | J10: {=_xlfn.LET(_xlpm.q,TRIM($B$4),_xlpm.tp,$A$7,_xlpm.mk,$D$7,_xlpm.dp,$G$7,_xlpm.st,$J$7,_xlpm.md,$M$7,_xlpm.b,'Índice Equipamentos'!$A$2:$T$563,_xlpm.txt,INDEX(_xlpm.b,,20)&"",_xlpm.oq,IF(_xlpm.q="",1,_xlfn.SWITCH(_xlpm.md,"Exata",LOWER(_xlpm.txt)=LOWER(_xlpm.q),"Começa com",LEFT(LOWER(_xlpm.txt),LEN(_xlpm.q))=LOWER(_xlpm.q),ISNUMBER(SEARCH(_xlpm.q,_xlpm.txt)))),_xlpm.ot,IF(_xlpm.tp="Todos",1,--(INDEX(_xlpm.b,,1)=_xlpm.tp)),_xlpm.om,IF(_xlpm.mk="Todas",1,--(INDEX(_xlpm.b,,7)=_xlpm.mk)),_xlpm.od,IF(_xlpm.dp="Todos",1,--(INDEX(_xlpm.b,,4)=_xlpm.dp)),_xlpm.os,IF(_xlpm.st="Todos",1,--(INDEX(_xlpm.b,,10)=_xlpm.st)),_xlpm.ok,_xlpm.oq*_xlpm.ot*_xlpm.om*_xlpm.od*_xlpm.os,SUM(--_xlpm.ok)-SUM(--_xlpm.ok*--(INDEX(_xlpm.b,,1)="Desktop"))-SUM(--_xlpm.ok*--(INDEX(_xlpm.b,,1)="Monitor")))} -> -430 | M10: {=_xlfn.LET(_xlpm.q,TRIM($B$4),_xlpm.tp,$A$7,_xlpm.mk,$D$7,_xlpm.dp,$G$7,_xlpm.st,$J$7,_xlpm.md,$M$7,_xlpm.b,'Índice Equipamentos'!$A$2:$T$563,_xlpm.txt,INDEX(_xlpm.b,,20)&"",_xlpm.oq,IF(_xlpm.q="",1,_xlfn.SWITCH(_xlpm.md,"Exata",LOWER(_xlpm.txt)=LOWER(_xlpm.q),"Começa com",LEFT(LOWER(_xlpm.txt),LEN(_xlpm.q))=LOWER(_xlpm.q),ISNUMBER(SEARCH(_xlpm.q,_xlpm.txt)))),_xlpm.ot,IF(_xlpm.tp="Todos",1,--(INDEX(_xlpm.b,,1)=_xlpm.tp)),_xlpm.om,IF(_xlpm.mk="Todas",1,--(INDEX(_xlpm.b,,7)=_xlpm.mk)),_xlpm.od,IF(_xlpm.dp="Todos",1,--(INDEX(_xlpm.b,,4)=_xlpm.dp)),_xlpm.os,IF(_xlpm.st="Todos",1,--(INDEX(_xlpm.b,,10)=_xlpm.st)),_xlpm.ok,_xlpm.oq*_xlpm.ot*_xlpm.om*_xlpm.od*_xlpm.os,IFERROR(ROWS(_xlfn.UNIQUE(_xlfn._xlws.FILTER(INDEX(_xlpm.b,,3),_xlpm.ok*(INDEX(_xlpm.b,,3)<>"Sem responsável")))),0))} -> 118 | X10: Mesa digitalizadora | Y10: FG | Z10: Cartucheira
X11: Monitor | Y11: Genérico | Z11: Comercial
X12: Notebook | Y12: Grandstream | Z12: Contabilidade
A13: RESULTADO DETALHADO — TODOS OS DADOS DISPONÍVEIS DO EQUIPAMENTO | X13: Telefonia | Y13: HP | Z13: Controladoria
A14: EQUIPAMENTO | B14: RESPONSÁVEL | C14: DEPARTAMENTO | D14: CLASSIFICAÇÃO | E14: MODELO | F14: MARCA | G14: PATRIMÔNIO | H14: HOSTNAME / Nº | I14: STATUS | J14: CONDIÇÃO | K14: CPU / PROCESSADOR | L14: ARMAZENAMENTO | M14: RAM | N14: DETALHES TÉCNICOS | O14: LOCALIZAÇÃO | Y14: Iphone 7 | Z14: Copa
A15: {=_xlfn.LET(_xlpm.q,TRIM($B$4),_xlpm.tp,$A$7,_xlpm.mk,$D$7,_xlpm.dp,$G$7,_xlpm.st,$J$7,_xlpm.md,$M$7,_xlpm.b,'Índice Equipamentos'!$A$2:$T$563,_xlpm.txt,INDEX(_xlpm.b,,20)&"",_xlpm.oq,IF(_xlpm.q="",1,_xlfn.SWITCH(_xlpm.md,"Exata",LOWER(_xlpm.txt)=LOWER(_xlpm.q),"Começa com",LEFT(LOWER(_xlpm.txt),LEN(_xlpm.q))=LOWER(_xlpm.q),ISNUMBER(SEARCH(_xlpm.q,_xlpm.txt)))),_xlpm.ot,IF(_xlpm.tp="Todos",1,--(INDEX(_xlpm.b,,1)=_xlpm.tp)),_xlpm.om,IF(_xlpm.mk="Todas",1,--(INDEX(_xlpm.b,,7)=_xlpm.mk)),_xlpm.od,IF(_xlpm.dp="Todos",1,--(INDEX(_xlpm.b,,4)=_xlpm.dp)),_xlpm.os,IF(_xlpm.st="Todos",1,--(INDEX(_xlpm.b,,10)=_xlpm.st)),_xlpm.ok,_xlpm.oq*_xlpm.ot*_xlpm.om*_xlpm.od*_xlpm.os,_xlpm.v,_xlfn.CHOOSECOLS(_xlpm.b,1,3,4,5,6,7,8,9,10,11,12,13,14,17,19),_xlfn._xlws.FILTER(IF(_xlpm.v="","",_xlpm.v),_xlpm.ok,"Nenhum equipamento encontrado com os filtros selecionados."))} -> #VALUE! | Y15: Leader Electronics | Z15: Dallet
Y16: LG | Z16: Depósito do RH
Y17: LG K10 (2016) | Z17: Depósito RH
Y18: LG K10 (2017) | Z18: Diretoria Administrativa
Y19: Mass Power | Z19: Diretoria Comercial
Y20: Motorol G8 | Z20: Diretoria Exec
Y21: NOC | Z21: Diretoria Executiva
Y22: Nokia | Z22: DIRETORIA EXECUTIVA
Y23: Samsung | Z23: Diretoria Ins
Y24: SWITCHING ADAPTOR | Z24: Diretoria Institucional
Y25: Vasata | Z25: Financeiro
Y26: Wacom | Z26: frente do swicher
Y27: XEROX | Z27: Frente Switcher
Z28: FTP
Z29: Geração
Z30: Gerencia Op/Eg
Z31: Gerencia Op/Eng
Z32: ILHA 1
Z33: ILHA 2
Z34: ILHA 3
Z35: ILHA 4
Z36: Jornalismo
Z37: Marketing
Z38: Master
Z39: Meet
... Z65: TI

Sheet CENTRAL
A1: INVENTARIO DO T.I
A4: TOTAL DE ATIVOS | D4: DEPARTAMENTOS | G4: COM RESPONSÁVEL | J4: COM HOSTNAME
A5: =ROWS(ListaInventario[Categoria]) -> 513 | D5: {=_xlfn.LET(_xlpm.d,TRIM(ListaInventario[Departamento]),COUNTA(_xlfn.UNIQUE(_xlfn._xlws.FILTER(_xlpm.d,_xlpm.d<>""))))} -> 56 | G5: =COUNTIF(ListaInventario[Responsável],"<>") -> 505 | J5: =COUNTIF(ListaInventario[Hostname],"<>") -> 343

Sheet controle
A1: Categoria | B1: Modelo | C1: Hostname | D1: Patrimônio | E1: Departamento | F1: Responsável | G1: Marca | H1: Serial | I1: Ramal | J1: IP | K1: Observação | L1: CPU | M1: Disco | N1: RAM | O1: ISO | P1: Status | Q1: Chave de auditoria | R1: VERIFICAÇÃO | S1: Departamento
A2: Desktop Antigo | B2: Optiplex 7020 | C2: FFF2GN2 | E2: Depósito RH | F2: T.I | G2: Dell | K2: Status: inativo | L2: Intel i7 7ª | M2: NVMe 256 GB | N2: 8 GB | O2: w10 | P2: OK | Q2: =A2&"¦"&B2&"¦"&C2&"¦"&D2&"¦"&E2&"¦"&F2&"¦"&G2&"¦"&#REF!&"¦"&L2&"¦"&M2&"¦"&N2&"¦"&O2&"¦"&#REF! -> #REF! | R2: 46266
A3: Desktop Antigo | B3: Optiplex 7020 | C3: FFLTDN2 | E3: Depósito RH | F3: T.I | G3: Dell | K3: Status: Bom | L3: Intel i7 7ª | M3: NVMe 256 GB | N3: 8 GB | O3: w10 | P3: OK | Q3: =A3&"¦"&B3&"¦"&C3&"¦"&D3&"¦"&E3&"¦"&F3&"¦"&G3&"¦"&K3&"¦"&L3&"¦"&M3&"¦"&N3&"¦"&O3&"¦"&#REF! -> #REF! | R3: 46266
A4: Desktop Antigo | B4: Optiplex 7020 | C4: FFNZDN2 | E4: Depósito RH | F4: T.I | G4: Dell | K4: Status : OK | L4: Intel i7 7ª | M4: NVMe 256 GB | N4: 8 GB | O4: w10 | P4: OK | Q4: =A4&"¦"&B4&"¦"&C4&"¦"&D4&"¦"&E4&"¦"&F4&"¦"&G4&"¦"&K4&"¦"&L4&"¦"&M4&"¦"&N4&"¦"&O4&"¦"&#REF! -> #REF! | R4: 46266
A5: Desktop Antigo | B5: Optiplex 7020 | C5: FFQYDN2 | E5: Depósito RH | F5: T.I | G5: Dell | K5: Status : OK | L5: Intel i7 7ª | M5: NVMe 256 GB | N5: 8 GB | O5: w10 | P5: OK | Q5: =A5&"¦"&B5&"¦"&C5&"¦"&D5&"¦"&E5&"¦"&F5&"¦"&G5&"¦"&K5&"¦"&L5&"¦"&M5&"¦"&N5&"¦"&O5&"¦"&#REF! -> #REF! | R5: 46266
A6: Desktop Antigo | B6: Optiplex 7020 | C6: FFVZDN2 | E6: Depósito RH | F6: T.I | G6: Dell | K6: Status : OK | L6: Intel i7 7ª | M6: NVMe 256 GB | N6: 8 GB | O6: w10 | P6: OK | Q6: =A6&"¦"&B6&"¦"&C6&"¦"&D6&"¦"&E6&"¦"&F6&"¦"&G6&"¦"&K6&"¦"&L6&"¦"&M6&"¦"&N6&"¦"&O6&"¦"&#REF! -> #REF! | R6: 46266
A7: Desktop Antigo | B7: Optiplex 7020 | C7: FFXYDN2 | E7: Depósito RH | F7: T.I | G7: Dell | K7: Status : OK | L7: Intel i7 7ª | M7: NVMe 256 GB | N7: 8 GB | O7: w10 | P7: OK | Q7: =A7&"¦"&B7&"¦"&C7&"¦"&D7&"¦"&E7&"¦"&F7&"¦"&G7&"¦"&K7&"¦"&L7&"¦"&M7&"¦"&N7&"¦"&O7&"¦"&#REF! -> #REF! | R7: 46266
A8: Desktop Antigo | B8: Optiplex 7020 | C8: FFZYDN2 | E8: Depósito RH | F8: T.I | G8: Dell | K8: Status : OK | L8: Intel i7 7ª | M8: NVMe 256 GB | N8: 8 GB | O8: w10 | P8: OK | Q8: =A8&"¦"&B8&"¦"&C8&"¦"&D8&"¦"&E8&"¦"&F8&"¦"&G8&"¦"&K8&"¦"&L8&"¦"&M8&"¦"&N8&"¦"&O8&"¦"&#REF! -> #REF! | R8: 46266
A9: Desktop Antigo | B9: Optiplex 7020 | C9: FG30FN2 | E9: Depósito RH | F9: T.I | G9: Dell | K9: Status : OK | L9: Intel i7 7ª | M9: NVMe 256 GB | N9: 8 GB | O9: w10 | P9: OK | Q9: =A9&"¦"&B9&"¦"&C9&"¦"&D9&"¦"&E9&"¦"&F9&"¦"&G9&"¦"&K9&"¦"&L9&"¦"&M9&"¦"&N9&"¦"&O9&"¦"&#REF! -> #REF! | R9: 46266
A10: Desktop Antigo | B10: Optiplex 7020 | C10: FG5ZDN2 | E10: Depósito RH | F10: T.I | G10: Dell | K10: Status : OK | L10: Intel i7 7ª | M10: NVMe 256 GB | N10: 8 GB | O10: w10 | P10: OK | Q10: =A10&"¦"&B10&"¦"&C10&"¦"&D10&"¦"&E10&"¦"&F10&"¦"&G10&"¦"&K10&"¦"&L10&"¦"&M10&"¦"&N10&"¦"&O10&"¦"&#REF! -> #REF! | R10: 46266
A11: Desktop Antigo | B11: Optiplex 7020 | C11: FG7YDN2 | E11: Depósito RH | F11: T.I | G11: Dell | K11: Status : OK | L11: Intel i7 7ª | M11: SSD SATA 256 GB | N11: 8 GB | O11: w10 | P11: OK | Q11: =A11&"¦"&B11&"¦"&C11&"¦"&D11&"¦"&E11&"¦"&F11&"¦"&G11&"¦"&K11&"¦"&L11&"¦"&M11&"¦"&N11&"¦"&O11&"¦"&#REF! -> #REF! | R11: 46266
A12: Desktop Antigo | B12: Optiplex 7020 | C12: FGDTDN2 | E12: Depósito RH | F12: T.I | G12: Dell | K12: Status : OK | L12: Intel i7 7ª | M12: NVMe 256 GB | N12: 8 GB | O12: w10 | P12: OK | Q12: =A12&"¦"&B12&"¦"&C12&"¦"&D12&"¦"&E12&"¦"&F12&"¦"&G12&"¦"&K12&"¦"&L12&"¦"&M12&"¦"&N12&"¦"&O12&"¦"&#REF! -> #REF! | R12: 46266
A13: Desktop Antigo | B13: 7050 | C13: FGGYDN2 | E13: Depósito RH | F13: T.I | G13: Dell | K13: Status : OK | P13: OK | Q13: =A13&"¦"&B13&"¦"&C13&"¦"&D13&"¦"&E13&"¦"&F13&"¦"&G13&"¦"&K13&"¦"&L13&"¦"&M13&"¦"&N13&"¦"&O13&"¦"&#REF! -> #REF! | R13: 46266
A14: Desktop Antigo | B14: Optiplex 7020 | C14: FGJ1FN2 | E14: Depósito RH | F14: T.I | G14: Dell | K14: Status : OK | L14: Intel i7 7ª | M14: NVMe 256 GB | N14: 8 GB | O14: w10 | P14: OK | Q14: =A14&"¦"&B14&"¦"&C14&"¦"&D14&"¦"&E14&"¦"&F14&"¦"&G14&"¦"&K14&"¦"&L14&"¦"&M14&"¦"&N14&"¦"&O14&"¦"&#REF! -> #REF! | R14: 46266
A15: Desktop Antigo | B15: Optiplex 7020 | C15: FGK2FN2 | E15: Depósito RH | F15: T.I | G15: Dell | K15: Status : OK | L15: Intel i7 7ª | M15: NVMe 256 GB | N15: 8 GB | O15: w10 | P15: OK | Q15: =A15&"¦"&B15&"¦"&C15&"¦"&D15&"¦"&E15&"¦"&F15&"¦"&G15&"¦"&K15&"¦"&L15&"¦"&M15&"¦"&N15&"¦"&O15&"¦"&#REF! -> #REF! | R15: 46266
A16: Desktop Antigo | B16: Optiplex 7020 | C16: FGLZDN2 | E16: Depósito RH | F16: T.I | G16: Dell | K16: Status : OK | L16: Intel i7 7ª | M16: NVMe 256 GB | N16: 8 GB | O16: w10 | P16: OK | Q16: =A16&"¦"&B16&"¦"&C16&"¦"&D16&"¦"&E16&"¦"&F16&"¦"&G16&"¦"&K16&"¦"&L16&"¦"&M16&"¦"&N16&"¦"&O16&"¦"&#REF! -> #REF! | R16: 46266
A17: Desktop Antigo | B17: Optiplex 7020 | C17: FGNTDN2 | E17: Depósito RH | F17: T.I | G17: Dell | K17: Status : INATIVO | L17: Intel i7 7ª | M17: NVMe 256 GB | N17: 8 GB | O17: w10 | P17: OK | Q17: =A17&"¦"&B17&"¦"&C17&"¦"&D17&"¦"&E17&"¦"&F17&"¦"&G17&"¦"&#REF!&"¦"&L17&"¦"&M17&"¦"&N17&"¦"&O17&"¦"&#REF! -> #REF! | R17: 46266
A18: Desktop Antigo | B18: Optiplex 7020 | C18: FGQ2FN2 | E18: Depósito RH | F18: T.I | G18: Dell | K18: Status : OK | L18: Intel i7 7ª | M18: NVMe 256 GB | N18: 8 GB | O18: w10 | P18: OK | Q18: =A18&"¦"&B18&"¦"&C18&"¦"&D18&"¦"&E18&"¦"&F18&"¦"&G18&"¦"&K18&"¦"&L18&"¦"&M18&"¦"&N18&"¦"&O18&"¦"&#REF! -> #REF! | R18: 46266
A19: Desktop Antigo | B19: Optiplex 7020 | C19: FGRZDN2 | E19: Depósito RH | F19: T.I | G19: Dell | K19: Status : OK | L19: Intel i7 7ª | M19: NVMe 256 GB | N19: 8 GB | O19: w10 | P19: OK | Q19: =A19&"¦"&B19&"¦"&C19&"¦"&D19&"¦"&E19&"¦"&F19&"¦"&G19&"¦"&K19&"¦"&L19&"¦"&M19&"¦"&N19&"¦"&O19&"¦"&#REF! -> #REF! | R19: 46266
A20: Desktop Antigo | B20: Optiplex 7020 | C20: FGT1FN2 | E20: Depósito RH | F20: T.I | G20: Dell | K20: Status : OK | L20: Intel i7 7ª | M20: NVMe 256 GB | N20: 8 GB | O20: w10 | P20: OK | Q20: =A20&"¦"&B20&"¦"&C20&"¦"&D20&"¦"&E20&"¦"&F20&"¦"&G20&"¦"&K20&"¦"&L20&"¦"&M20&"¦"&N20&"¦"&O20&"¦"&#REF! -> #REF! | R20: 46266
A21: Desktop Antigo | B21: Optiplex 7020 | C21: FGV2FN2 | E21: Depósito RH | F21: T.I | G21: Dell | K21: Status : OK | L21: Intel i7 7ª | M21: NVMe 256 GB | N21: 8 GB | O21: w10 | P21: OK | Q21: =A21&"¦"&B21&"¦"&C21&"¦"&D21&"¦"&E21&"¦"&F21&"¦"&G21&"¦"&#REF!&"¦"&L21&"¦"&M21&"¦"&N21&"¦"&O21&"¦"&#REF! -> #REF! | R21: 46266
A22: Desktop Antigo | B22: Optiplex 7020 | C22: FGX0FN2 | E22: Depósito RH | F22: T.I | G22: Dell | K22: Status : OK | L22: Intel i7 7ª | M22: NVMe 256 GB | N22: 8 GB | O22: w10 | P22: OK | Q22: =A22&"¦"&B22&"¦"&C22&"¦"&D22&"¦"&E22&"¦"&F22&"¦"&G22&"¦"&K22&"¦"&L22&"¦"&M22&"¦"&N22&"¦"&O22&"¦"&#REF! -> #REF! | R22: 46266
A23: Desktop Antigo | B23: Optiplex 7020 | C23: FGZ0FN2 | E23: Depósito RH | F23: T.I | G23: Dell | K23: Status : OK | L23: Intel i7 7ª | M23: NVMe 256 GB | N23: 8 GB | O23: w10 | P23: OK | Q23: =A23&"¦"&B23&"¦"&C23&"¦"&D23&"¦"&E23&"¦"&F23&"¦"&G23&"¦"&K23&"¦"&L23&"¦"&M23&"¦"&N23&"¦"&O23&"¦"&#REF! -> #REF! | R23: 46266
A24: Desktop Antigo | B24: Optiplex 7020 | C24: FH3ZDN2 | E24: Depósito RH | F24: T.I | G24: Dell | K24: Status : OK | L24: Intel i7 7ª | M24: NVMe 256 GB | N24: 8 GB | O24: w10 | P24: OK | Q24: =A24&"¦"&B24&"¦"&C24&"¦"&D24&"¦"&E24&"¦"&F24&"¦"&G24&"¦"&K24&"¦"&L24&"¦"&M24&"¦"&N24&"¦"&O24&"¦"&#REF! -> #REF! | R24: 46266
A25: Desktop Antigo | B25: Optiplex 7020 | C25: FH90FN2 | E25: Depósito RH | F25: T.I | G25: Dell | K25: Status : OK | P25: OK | Q25: =A25&"¦"&B25&"¦"&C25&"¦"&D25&"¦"&E25&"¦"&F25&"¦"&G25&"¦"&K25&"¦"&L25&"¦"&M25&"¦"&N25&"¦"&O25&"¦"&#REF! -> #REF! | R25: 46266
A26: Desktop Antigo | B26: Optiplex 7020 | C26: FHC0FN2 | E26: Depósito RH | F26: T.I | G26: Dell | K26: Status : OK | L26: Intel i7 7ª | M26: SSD SATA 256 GB | N26: 8 GB | O26: w10 | P26: OK | Q26: =A26&"¦"&B26&"¦"&C26&"¦"&D26&"¦"&E26&"¦"&F26&"¦"&G26&"¦"&K26&"¦"&L26&"¦"&M26&"¦"&N26&"¦"&O26&"¦"&#REF! -> #REF! | R26: 46266
A27: Desktop Antigo | B27: Optiplex 7020 | C27: FHD0FN2 | E27: Depósito RH | F27: T.I | G27: Dell | K27: Status : OK | L27: Intel i7 7ª | M27: NVMe 256 GB | N27: 8 GB | O27: w10 | P27: OK | Q27: =A27&"¦"&B27&"¦"&C27&"¦"&D27&"¦"&E27&"¦"&F27&"¦"&G27&"¦"&K27&"¦"&L27&"¦"&M27&"¦"&N27&"¦"&O27&"¦"&#REF! -> #REF! | R27: 46266
A28: Desktop Antigo | B28: Optiplex 7020 | C28: FHDYFN2 | E28: Depósito RH | F28: T.I | G28: Dell | K28: Status : OK | L28: Intel i7 7ª | M28: NVMe 256 GB | N28: 8 GB | O28: w10 | P28: OK | Q28: =A28&"¦"&B28&"¦"&C28&"¦"&D28&"¦"&E28&"¦"&F28&"¦"&G28&"¦"&K28&"¦"&L28&"¦"&M28&"¦"&N28&"¦"&O28&"¦"&#REF! -> #REF! | R28: 46266
A29: Desktop Antigo | B29: Optiplex 7020 | C29: FHFZDN2 | E29: Depósito RH | F29: T.I | G29: Dell | K29: Status : OK | L29: Intel i7 7ª | M29: NVMe 256 GB | N29: 8 GB | O29: w10 | P29: OK | Q29: =A29&"¦"&B29&"¦"&C29&"¦"&D29&"¦"&E29&"¦"&F29&"¦"&G29&"¦"&K29&"¦"&L29&"¦"&M29&"¦"&N29&"¦"&O29&"¦"&#REF! -> #REF! | R29: 46266
A30: Desktop Antigo | B30: Optiplex 7020 | C30: FHH2FN2 | E30: Depósito RH | F30: T.I | G30: Dell | K30: Status : OK | P30: OK | Q30: =A30&"¦"&B30&"¦"&C30&"¦"&D30&"¦"&E30&"¦"&F30&"¦"&G30&"¦"&K30&"¦"&L30&"¦"&M30&"¦"&N30&"¦"&O30&"¦"&#REF! -> #REF! | R30: 46266
A31: Desktop Antigo | B31: Optiplex 7020 | C31: FHJTDN2 | E31: Depósito RH | F31: T.I | G31: Dell | K31: Status : OK | L31: Intel i7 7ª | M31: SSD SATA 256 GB | N31: 8 GB | O31: w10 | P31: OK | Q31: =A31&"¦"&B31&"¦"&C31&"¦"&D31&"¦"&E31&"¦"&F31&"¦"&G31&"¦"&K31&"¦"&L31&"¦"&M31&"¦"&N31&"¦"&O31&"¦"&#REF! -> #REF! | R31: 46266
A32: Desktop Antigo | B32: Optiplex 7020 | C32: FHKYDN2 | E32: Depósito RH | F32: T.I | G32: Dell | K32: Status : OK | L32: Intel i7 7ª | M32: SSD SATA 256 GB | N32: 8 GB | O32: w10 | P32: OK | Q32: =A32&"¦"&B32&"¦"&C32&"¦"&D32&"¦"&E32&"¦"&F32&"¦"&G32&"¦"&K32&"¦"&L32&"¦"&M32&"¦"&N32&"¦"&O32&"¦"&#REF! -> #REF! | R32: 46266
A33: Desktop Antigo | B33: Optiplex 7020 | C33: FHM0FN2 | E33: Depósito RH | F33: T.I | G33: Dell | K33: Status : OK | L33: Intel i7 7ª | M33: NVMe 256 GB | N33: 8 GB | O33: w10 | P33: OK | Q33: =A33&"¦"&B33&"¦"&C33&"¦"&D33&"¦"&E33&"¦"&F33&"¦"&G33&"¦"&K33&"¦"&L33&"¦"&M33&"¦"&N33&"¦"&O33&"¦"&#REF! -> #REF! | R33: 46266
A34: Desktop Antigo | B34: Optiplex 7020 | C34: FHNZDN2 | E34: Depósito RH | F34: T.I | G34: Dell | K34: Status : OK | L34: Intel i7 7ª | M34: NVMe 256 GB | N34: 8 GB | O34: w10 | P34: OK | Q34: =A34&"¦"&B34&"¦"&C34&"¦"&D34&"¦"&E34&"¦"&F34&"¦"&G34&"¦"&K34&"¦"&L34&"¦"&M34&"¦"&N34&"¦"&O34&"¦"&#REF! -> #REF! | R34: 46266
A35: Desktop Antigo | B35: Optiplex 7020 | C35: FHQTDN2 | E35: Depósito RH | F35: T.I | G35: Dell | K35: Status : OK | L35: Intel i7 7ª | M35: NVMe 256 GB | N35: 8 GB | O35: w10 | P35: OK | Q35: =A35&"¦"&B35&"¦"&C35&"¦"&D35&"¦"&E35&"¦"&F35&"¦"&G35&"¦"&K35&"¦"&L35&"¦"&M35&"¦"&N35&"¦"&O35&"¦"&#REF! -> #REF! | R35: 46266
A36: Desktop Antigo | B36: Optiplex 7020 | C36: FHSYDN2 | E36: Depósito RH | F36: T.I | G36: Dell | K36: Status : OK | P36: OK | Q36: =A36&"¦"&B36&"¦"&C36&"¦"&D36&"¦"&E36&"¦"&F36&"¦"&G36&"¦"&K36&"¦"&L36&"¦"&M36&"¦"&N36&"¦"&O36&"¦"&#REF! -> #REF! | R36: 46266
A37: Desktop Antigo | B37: Optiplex 7020 | C37: FHZYDN2 | E37: Depósito RH | F37: T.I | G37: Dell | K37: Status : inativo | L37: Intel i7 7ª | M37: NVMe 256 GB | N37: 8 GB | O37: w10 | P37: OK | Q37: =A37&"¦"&B37&"¦"&C37&"¦"&D37&"¦"&E37&"¦"&F37&"¦"&G37&"¦"&#REF!&"¦"&L37&"¦"&M37&"¦"&N37&"¦"&O37&"¦"&#REF! -> #REF! | R37: 46266
A38: Desktop Antigo | B38: Optiplex 7020 | C38: FKG0FN2 | E38: Depósito RH | F38: T.I | G38: Dell | K38: Status : OK | L38: Intel i7 7ª | M38: NVMe 256 GB | N38: 8 GB | O38: w10 | P38: OK | Q38: =A38&"¦"&B38&"¦"&C38&"¦"&D38&"¦"&E38&"¦"&F38&"¦"&G38&"¦"&K38&"¦"&L38&"¦"&M38&"¦"&N38&"¦"&O38&"¦"&#REF! -> #REF! | R38: 46266
A39: Desktop Antigo | B39: Optiplex 7020 | C39: FKHZDN2 | E39: Depósito RH | F39: T.I | G39: Dell | K39: Status : OK | L39: Intel i7 7ª | M39: NVMe 256 GB | N39: 8 GB | O39: w10 | P39: OK | Q39: =A39&"¦"&B39&"¦"&C39&"¦"&D39&"¦"&E39&"¦"&F39&"¦"&G39&"¦"&K39&"¦"&L39&"¦"&M39&"¦"&N39&"¦"&O39&"¦"&#REF! -> #REF! | R39: 46266
A40: Desktop Antigo | B40: Optiplex 7020 | C40: FKJ0FN2 | E40: Depósito RH | F40: T.I | G40: Dell | K40: Status : OK | L40: Intel i7 7ª | M40: NVMe 256 GB | N40: 8 GB | O40: w10 | P40: OK | Q40: =A40&"¦"&B40&"¦"&C40&"¦"&D40&"¦"&E40&"¦"&F40&"¦"&G40&"¦"&K40&"¦"&L40&"¦"&M40&"¦"&N40&"¦"&O40&"¦"&#REF! -> #REF! | R40: 46266
A41: Desktop Antigo | B41: Optiplex 7020 | C41: FKL2FN2 | E41: Depósito RH | F41: T.I | G41: Dell | K41: Status : OK | L41: Intel i7 7ª | M41: NVMe 256 GB | N41: 8 GB | O41: w10 | P41: OK | Q41: =A41&"¦"&B41&"¦"&C41&"¦"&D41&"¦"&E41&"¦"&F41&"¦"&G41&"¦"&K41&"¦"&L41&"¦"&M41&"¦"&N41&"¦"&O41&"¦"&#REF! -> #REF! | R41: 46266
A42: Desktop Antigo | B42: Optiplex 7020 | C42: FKLYDN2 | E42: Depósito RH | F42: T.I | G42: Dell | K42: Status : OK | L42: Intel i7 7ª | M42: SSD SATA 256 GB | N42: 8 GB | O42: w10 | P42: OK | Q42: =A42&"¦"&B42&"¦"&C42&"¦"&D42&"¦"&E42&"¦"&F42&"¦"&G42&"¦"&K42&"¦"&L42&"¦"&M42&"¦"&N42&"¦"&O42&"¦"&#REF! -> #REF! | R42: 46266
A43: Desktop Antigo | B43: Optiplex 7020 | C43: FKM2FN2 | E43: Depósito RH | F43: T.I | G43: Dell | K43: Status : OK | L43: Intel i7 7ª | M43: SSD SATA 256 GB | N43: 8 GB | O43: w10 | P43: OK | Q43: =A43&"¦"&B43&"¦"&C43&"¦"&D43&"¦"&E43&"¦"&F43&"¦"&G43&"¦"&K43&"¦"&L43&"¦"&M43&"¦"&N43&"¦"&O43&"¦"&#REF! -> #REF! | R43: 46266
A44: Desktop Antigo | B44: Optiplex 7020 | C44: FKN2FN2 | E44: Depósito RH | F44: T.I | G44: Dell | K44: Status : OK | L44: Intel i7 7ª | M44: SSD SATA 256 GB | N44: 8 GB | O44: w10 | P44: OK | Q44: =A44&"¦"&B44&"¦"&C44&"¦"&D44&"¦"&E44&"¦"&F44&"¦"&G44&"¦"&K44&"¦"&L44&"¦"&M44&"¦"&N44&"¦"&O44&"¦"&#REF! -> #REF! | R44: 46266
A45: Desktop Antigo | B45: Optiplex 7020 | C45: FKP1FN2 | E45: Depósito RH | F45: T.I | G45: Dell | K45: Status : OK | L45: Intel i7 7ª | M45: NVMe 256 GB | N45: 8 GB | O45: w10 | P45: OK | Q45: =A45&"¦"&B45&"¦"&C45&"¦"&D45&"¦"&E45&"¦"&F45&"¦"&G45&"¦"&K45&"¦"&L45&"¦"&M45&"¦"&N45&"¦"&O45&"¦"&#REF! -> #REF! | R45: 46266
A46: Desktop Antigo | B46: Optiplex 7020 | C46: FKQZDN2 | E46: Depósito RH | F46: T.I | G46: Dell | K46: Status : OK | L46: Intel i7 7ª | M46: NVMe 256 GB | N46: 8 GB | O46: w10 | P46: OK | Q46: =A46&"¦"&B46&"¦"&C46&"¦"&D46&"¦"&E46&"¦"&F46&"¦"&G46&"¦"&K46&"¦"&L46&"¦"&M46&"¦"&N46&"¦"&O46&"¦"&#REF! -> #REF! | R46: 46266
A47: Desktop Antigo | B47: Optiplex 7020 | C47: FKS2FN2 | E47: Depósito RH | F47: T.I | G47: Dell | K47: Status : Inativo | L47: Intel i7 7ª | M47: NVMe 256 GB | N47: 8 GB | O47: w10 | P47: OK | Q47: =A47&"¦"&B47&"¦"&C47&"¦"&D47&"¦"&E47&"¦"&F47&"¦"&G47&"¦"&#REF!&"¦"&L47&"¦"&M47&"¦"&N47&"¦"&O47&"¦"&#REF! -> #REF! | R47: 46266
A48: Desktop Antigo | B48: Optiplex 7020 | C48: FKVZDN2 | E48: Depósito RH | F48: T.I | G48: Dell | K48: Status : OK | L48: Intel i7 7ª | M48: SSD SATA 256 GB | N48: 8 GB | O48: w10 | P48: OK | Q48: =A48&"¦"&B48&"¦"&C48&"¦"&D48&"¦"&E48&"¦"&F48&"¦"&G48&"¦"&K48&"¦"&L48&"¦"&M48&"¦"&N48&"¦"&O48&"¦"&#REF! -> #REF! | R48: 46266
A49: Desktop Antigo | B49: Optiplex 7020 | C49: FKX0FN2 | E49: Depósito RH | F49: T.I | G49: Dell | K49: Status : OK | L49: Intel i7 7ª | M49: NVMe 256 GB | N49: 8 GB | O49: w10 | P49: OK | Q49: =A49&"¦"&B49&"¦"&C49&"¦"&D49&"¦"&E49&"¦"&F49&"¦"&G49&"¦"&K49&"¦"&L49&"¦"&M49&"¦"&N49&"¦"&O49&"¦"&#REF! -> #REF! | R49: 46266
A50: Desktop Antigo | B50: Optiplex 7020 | C50: FKXZDN2 | E50: Depósito RH | F50: T.I | G50: Dell | K50: Status : OK | L50: Intel i7 7ª | M50: NVMe 256 GB | N50: 8 GB | O50: w10 | P50: OK | Q50: =A50&"¦"&B50&"¦"&C50&"¦"&D50&"¦"&E50&"¦"&F50&"¦"&G50&"¦"&K50&"¦"&L50&"¦"&M50&"¦"&N50&"¦"&O50&"¦"&#REF! -> #REF! | R50: 46266
A51: Desktop Antigo | B51: Optiplex 7020 | C51: FKYZDN2 | E51: Depósito RH | F51: T.I | G51: Dell | K51: Status : OK | L51: Intel i7 7ª | M51: NVMe 256 GB | N51: 8 GB | O51: w10 | P51: OK | Q51: =A51&"¦"&B51&"¦"&C51&"¦"&D51&"¦"&E51&"¦"&F51&"¦"&G51&"¦"&K51&"¦"&L51&"¦"&M51&"¦"&N51&"¦"&O51&"¦"&#REF! -> #REF! | R51: 46266
A52: Desktop Antigo | B52: Optiplex 7020 | C52: FKZYDN2 | E52: Depósito RH | F52: T.I | G52: Dell | K52: Status : OK | L52: Intel i7 7ª | M52: SSD SATA 256 GB | N52: 8 GB | O52: w10 | P52: OK | Q52: =A52&"¦"&B52&"¦"&C52&"¦"&D52&"¦"&E52&"¦"&F52&"¦"&G52&"¦"&K52&"¦"&L52&"¦"&M52&"¦"&N52&"¦"&O52&"¦"&#REF! -> #REF! | R52: 46266
A53: Desktop Antigo | B53: Optiplex 7020 | C53: FL0VDN2 | E53: Depósito RH | F53: T.I | G53: Dell | K53: Status : OK | L53: Intel i7 7ª | M53: NVMe 256 GB | N53: 8 GB | O53: w10 | P53: OK | Q53: =A53&"¦"&B53&"¦"&C53&"¦"&D53&"¦"&E53&"¦"&F53&"¦"&G53&"¦"&K53&"¦"&L53&"¦"&M53&"¦"&N53&"¦"&O53&"¦"&#REF! -> #REF! | R53: 46266
A54: Desktop Antigo | B54: Optiplex 7020 | C54: FL31FN2 | E54: Depósito RH | F54: T.I | G54: Dell | K54: Status : OK | L54: Intel i7 7ª | M54: NVMe 256 GB | N54: 8 GB | O54: w10 | P54: OK | Q54: =A54&"¦"&B54&"¦"&C54&"¦"&D54&"¦"&E54&"¦"&F54&"¦"&G54&"¦"&K54&"¦"&L54&"¦"&M54&"¦"&N54&"¦"&O54&"¦"&#REF! -> #REF! | R54: 46266
A55: Desktop Antigo | B55: Optiplex 7020 | C55: FL41FN2 | E55: Depósito RH | F55: T.I | G55: Dell | K55: Status : OK | L55: Intel i7 7ª | M55: NVMe 256 GB | N55: 8 GB | O55: w10 | P55: OK | Q55: =A55&"¦"&B55&"¦"&C55&"¦"&D55&"¦"&E55&"¦"&F55&"¦"&G55&"¦"&K55&"¦"&L55&"¦"&M55&"¦"&N55&"¦"&O55&"¦"&#REF! -> #REF! | R55: 46266
A56: Desktop Antigo | B56: Optiplex 7020 | C56: FL4ZDN2 | E56: Depósito RH | F56: T.I | G56: Dell | K56: Status : OK | L56: Intel i7 7ª | M56: NVMe 256 GB | N56: 8 GB | O56: w10 | P56: OK | Q56: =A56&"¦"&B56&"¦"&C56&"¦"&D56&"¦"&E56&"¦"&F56&"¦"&G56&"¦"&K56&"¦"&L56&"¦"&M56&"¦"&N56&"¦"&O56&"¦"&#REF! -> #REF! | R56: 46266
A57: Desktop Antigo | B57: Optiplex 7020 | C57: FL5VDN2 | E57: Depósito RH | F57: T.I | G57: Dell | K57: Status : OK | L57: Intel i7 7ª | M57: SSD SATA 256 GB | N57: 8 GB | O57: w10 | P57: OK | Q57: =A57&"¦"&B57&"¦"&C57&"¦"&D57&"¦"&E57&"¦"&F57&"¦"&G57&"¦"&K57&"¦"&L57&"¦"&M57&"¦"&N57&"¦"&O57&"¦"&#REF! -> #REF! | R57: 46266
A58: Desktop Antigo | B58: Optiplex 7020 | C58: FL62FN2 | E58: Depósito RH | F58: T.I | G58: Dell | K58: Status : OK | L58: Intel i7 7ª | M58: NVMe 256 GB | N58: 8 GB | O58: w10 | P58: OK | Q58: =A58&"¦"&B58&"¦"&C58&"¦"&D58&"¦"&E58&"¦"&F58&"¦"&G58&"¦"&K58&"¦"&L58&"¦"&M58&"¦"&N58&"¦"&O58&"¦"&#REF! -> #REF! | R58: 46266
A59: Desktop Antigo | B59: Optiplex 7020 | C59: FL71FN2 | E59: Depósito RH | F59: T.I | G59: Dell | K59: Status : OK | L59: Intel i7 7ª | M59: NVMe 256 GB | N59: 8 GB | O59: w10 | P59: OK | Q59: =A59&"¦"&B59&"¦"&C59&"¦"&D59&"¦"&E59&"¦"&F59&"¦"&G59&"¦"&K59&"¦"&L59&"¦"&M59&"¦"&N59&"¦"&O59&"¦"&#REF! -> #REF! | R59: 46266
... A74: Desktop Antigo | B74: Optiplex 7020 | C74: FLKTDN2 | E74: Depósito RH | F74: T.I | G74: Dell | K74: Status : OK | L74: Intel i7 7ª | M74: SSD SATA 256 GB | N74: 8 GB | O74: w10 | P74: OK | Q74: =A74&"¦"&B74&"¦"&C74&"¦"&D74&"¦"&E74&"¦"&F74&"¦"&G74&"¦"&K74&"¦"&L74&"¦"&M74&"¦"&N74&"¦"&O74&"¦"&#REF! -> #REF! | R74: 46266
A75: Desktop Antigo | B75: Optiplex 7020 | C75: FLL0FN2 | E75: Depósito RH | F75: T.I | G75: Dell | K75: Status : ina/DEF | L75: Intel i7 7ª | M75: SSD SATA 256 GB | N75: 8 GB | O75: w10 | P75: OK | Q75: =A75&"¦"&B75&"¦"&C75&"¦"&D75&"¦"&E75&"¦"&F75&"¦"&G75&"¦"&#REF!&"¦"&L75&"¦"&M75&"¦"&N75&"¦"&O75&"¦"&#REF! -> #REF! | R75: 46266
A76: Desktop Antigo | B76: Optiplex 7020 | C76: FLM0FN2 | E76: Depósito RH | F76: T.I | G76: Dell | K76: Status : OK | L76: Intel i7 7ª | M76: NVMe 256 GB | N76: 8 GB | O76: w10 | P76: OK | Q76: =A76&"¦"&B76&"¦"&C76&"¦"&D76&"¦"&E76&"¦"&F76&"¦"&G76&"¦"&K76&"¦"&L76&"¦"&M76&"¦"&N76&"¦"&O76&"¦"&#REF! -> #REF! | R76: 46266
A77: Desktop Antigo | B77: Optiplex 7020 | C77: FLMTDN2 | E77: Depósito RH | F77: T.I | G77: Dell | K77: Status : OK | L77: Intel i7 7ª | M77: NVMe 256 GB | N77: 8 GB | O77: w10 | P77: OK | Q77: =A77&"¦"&B77&"¦"&C77&"¦"&D77&"¦"&E77&"¦"&F77&"¦"&G77&"¦"&K77&"¦"&L77&"¦"&M77&"¦"&N77&"¦"&O77&"¦"&#REF! -> #REF! | R77: 46266
A78: Desktop Antigo | B78: Optiplex 7020 | C78: FL1VDN2 | E78: Diretoria Exec | F78: GUSTAVO FRAGA BRANDAO PAULUS | G78: Dell | K78: Status : OK | L78: Intel i7 7ª | N78: 8 GB | O78: w10 | P78: OK | Q78: =A78&"¦"&B78&"¦"&C78&"¦"&D78&"¦"&E78&"¦"&F78&"¦"&G78&"¦"&K78&"¦"&L78&"¦"&M78&"¦"&N78&"¦"&O78&"¦"&#REF! -> #REF! | R78: 46266
A79: Desktop Antigo | B79: 7050 | C79: FH0ZDN2 | E79: Frente do swicher | F79: USUÁRIO FRENTE SWICHER | G79: Dell | K79: Status: Bom | P79: OK | Q79: =A79&"¦"&B79&"¦"&C79&"¦"&D79&"¦"&E79&"¦"&F79&"¦"&G79&"¦"&K79&"¦"&L79&"¦"&M79&"¦"&N79&"¦"&O79&"¦"&#REF! -> #REF! | R79: 46266
A80: Desktop Antigo | B80: Optiplex 7020 | C80: FLBTDN2 | E80: Frente do swicher | F80: USUÁRIO FRENTE SWICHER | G80: Dell | K80: Status : OK | L80: Intel i7 7ª | M80: NVMe 256 GB | N80: 8 GB | O80: w10 | P80: OK | Q80: =A80&"¦"&B80&"¦"&C80&"¦"&D80&"¦"&E80&"¦"&F80&"¦"&G80&"¦"&K80&"¦"&L80&"¦"&M80&"¦"&N80&"¦"&O80&"¦"&#REF! -> #REF! | R80: 46266
A81: Desktop Antigo | B81: QCM1250 | C81: FGTZDN2 | E81: ILHA 1 | F81: USUÁRIO ILHA 1 | G81: Dell | K81: Status: Bom | P81: OK | Q81: =A81&"¦"&B81&"¦"&C81&"¦"&D81&"¦"&E81&"¦"&F81&"¦"&G81&"¦"&K81&"¦"&L81&"¦"&M81&"¦"&N81&"¦"&O81&"¦"&#REF! -> #REF! | R81: 46266
A82: Desktop Antigo | B82: QCM1250 | C82: FGMTDN2 | E82: ILHA 2 | F82: USUÁRIO ILHA 2 | G82: Dell | K82: Status: Bom | P82: OK | Q82: =A82&"¦"&B82&"¦"&C82&"¦"&D82&"¦"&E82&"¦"&F82&"¦"&G82&"¦"&K82&"¦"&L82&"¦"&M82&"¦"&N82&"¦"&O82&"¦"&#REF! -> #REF! | R82: 46266
A83: Desktop Antigo | B83: QCM1250 | C83: FGS1FN2 | E83: ILHA 3 | F83: USUÁRIO ILHA 3 | G83: Dell | K83: Status: Bom | P83: OK | Q83: =A83&"¦"&B83&"¦"&C83&"¦"&D83&"¦"&E83&"¦"&F83&"¦"&G83&"¦"&K83&"¦"&L83&"¦"&M83&"¦"&N83&"¦"&O83&"¦"&#REF! -> #REF! | R83: 46266
A84: Desktop Antigo | B84: QCM1250 | C84: FGPYDN2 | E84: ILHA 4 | F84: USUÁRIO ILHA 4 | G84: Dell | K84: Status: Bom | P84: OK | Q84: =A84&"¦"&B84&"¦"&C84&"¦"&D84&"¦"&E84&"¦"&F84&"¦"&G84&"¦"&K84&"¦"&L84&"¦"&M84&"¦"&N84&"¦"&O84&"¦"&#REF! -> #REF! | R84: 46266
A85: Desktop Antigo | B85: Optiplex 7020 | C85: FFHYDN2 | E85: Switcher | F85: USUÁRIO SWITCHER | G85: Dell | K85: Status : OK | P85: OK | Q85: =A85&"¦"&B85&"¦"&C85&"¦"&D85&"¦"&E85&"¦"&F85&"¦"&G85&"¦"&K85&"¦"&L85&"¦"&M85&"¦"&N85&"¦"&O85&"¦"&#REF! -> #REF! | R85: 46266
A86: Desktop Antigo | B86: Optiplex 7020 | C86: FG92FN2 | E86: Switcher | F86: USUÁRIO SWITCHER | G86: Dell | K86: Status : OK | L86: Intel i7 7ª | M86: NVMe 256 GB | N86: 8 GB | O86: w10 | P86: OK | Q86: =A86&"¦"&B86&"¦"&C86&"¦"&D86&"¦"&E86&"¦"&F86&"¦"&G86&"¦"&K86&"¦"&L86&"¦"&M86&"¦"&N86&"¦"&O86&"¦"&#REF! -> #REF! | R86: 46266
A87: Desktop Antigo | B87: Optiplex 7020 | C87: FKTZDN2 | E87: Switcher | F87: USUÁRIO SWITCHER | G87: Dell | K87: Status : OK | P87: OK | Q87: =A87&"¦"&B87&"¦"&C87&"¦"&D87&"¦"&E87&"¦"&F87&"¦"&G87&"¦"&K87&"¦"&L87&"¦"&M87&"¦"&N87&"¦"&O87&"¦"&#REF! -> #REF! | R87: 46266
A88: Desktop Antigo | B88: Optiplex 7020 | C88: FLFZDN2 | E88: Switcher | F88: USUÁRIO SWITCHER | G88: Dell | K88: Status : OK | P88: OK | Q88: =A88&"¦"&B88&"¦"&C88&"¦"&D88&"¦"&E88&"¦"&F88&"¦"&G88&"¦"&K88&"¦"&L88&"¦"&M88&"¦"&N88&"¦"&O88&"¦"&#REF! -> #REF! | R88: 46266
A89: Impressora | B89: WorkCentre 3345 | D89: 8234 | E89: Administrativo | G89: XEROX | H89: 3BT806127 | J89: 10.28.70.21 | K89: Status: Bom | P89: OK | Q89: =A89&"¦"&B89&"¦"&C89&"¦"&D89&"¦"&E89&"¦"&F89&"¦"&G89&"¦"&#REF!&"¦"&L89&"¦"&M89&"¦"&N89&"¦"&O89&"¦"&#REF! -> #REF! | R89: 46266
A90: Impressora | B90: COLOR ECOTANK | D90: 15104 | E90: Diretoria Administrativa | F90: MAURICIO GODINHO DOS SANTOS | G90: EPSON | H90: X952016786 | J90: 10.28.70.14 | K90: Status: Bom | P90: OK | Q90: =A90&"¦"&B90&"¦"&C90&"¦"&D90&"¦"&E90&"¦"&F90&"¦"&G90&"¦"&#REF!&"¦"&L90&"¦"&M90&"¦"&N90&"¦"&O90&"¦"&#REF! -> #REF! | R90: 46266
A91: Impressora | B91: DCP-T830DW | D91: 16549 | E91: DIRETORIA EXECUTIVA | F91: GUSTAVO PAULOS | G91: BROTHER | H91: U67681G5H187183 | J91: 10.28.70.23 | K91: Status: Bom | P91: OK | Q91: =A91&"¦"&B91&"¦"&C91&"¦"&D91&"¦"&E91&"¦"&F91&"¦"&G91&"¦"&#REF!&"¦"&L91&"¦"&M91&"¦"&N91&"¦"&O91&"¦"&#REF! -> #REF! | R91: 46266
A92: Impressora | B92: WorkCentre 3345 | D92: 8220 | E92: Jornalismo | G92: XEROX | H92: 3BT805947 | J92: 10.28.70.19 | K92: Status: Bom | P92: OK | Q92: =A92&"¦"&B92&"¦"&C92&"¦"&D92&"¦"&E92&"¦"&F92&"¦"&G92&"¦"&#REF!&"¦"&L92&"¦"&M92&"¦"&N92&"¦"&O92&"¦"&#REF! -> #REF! | R92: 46266
A93: Impressora | B93: Color LaserJet MFP E57540 | D93: 16335 | E93: Marketing | G93: HP | H93: BRBSN7NJD9 | J93: 10.28.70.18 | K93: Status: Bom | P93: OK | Q93: =A93&"¦"&B93&"¦"&C93&"¦"&D93&"¦"&E93&"¦"&F93&"¦"&G93&"¦"&#REF!&"¦"&L93&"¦"&M93&"¦"&N93&"¦"&O93&"¦"&#REF! -> #REF! | R93: 46266
A94: Impressora | B94: WorkCentre 3345 | D94: 7663 | E94: OPEC | G94: XEROX | H94: 3BT806183 | J94: 10.28.70.20 | K94: Status: Bom | P94: OK | Q94: =A94&"¦"&B94&"¦"&C94&"¦"&D94&"¦"&E94&"¦"&F94&"¦"&G94&"¦"&#REF!&"¦"&L94&"¦"&M94&"¦"&N94&"¦"&O94&"¦"&#REF! -> #REF! | R94: 46266
A95: Impressora | B95: WorkCentre 3345 | D95: 8533 | E95: RH | G95: XEROX | H95: 3BT805711 | J95: 10.28.70.22 | K95: Status: Bom | P95: OK | Q95: =A95&"¦"&B95&"¦"&C95&"¦"&D95&"¦"&E95&"¦"&F95&"¦"&G95&"¦"&#REF!&"¦"&L95&"¦"&M95&"¦"&N95&"¦"&O95&"¦"&#REF! -> #REF! | R95: 46266
A96: Micro | B96: DELL PRO MICRO QCM1250 | C96: JTH31H4 | D96: 830 | E96: Administração | F96: AMANDA GOMES PACHECO SEVERO | G96: Dell | K96: Status: Bom | L96: Intel Core i5-14500T | M96: 512GB SSD NVME | N96: 16GB DDR5 | P96: OK | Q96: =A96&"¦"&B96&"¦"&C96&"¦"&D96&"¦"&E96&"¦"&F96&"¦"&G96&"¦"&K96&"¦"&L96&"¦"&M96&"¦"&N96&"¦"&O96&"¦"&#REF! -> #REF! | R96: 46266
A97: Micro | B97: DELL PRO MICRO QCM1250 | C97: GZJ31H4 | D97: 838 | E97: Administração | F97: DAISY DA SILVA RUSSO | G97: Dell | K97: Status: Bom | L97: Intel Core i5-14500T | M97: 512GB SSD NVME | N97: 16GB DDR5 | P97: OK | Q97: =A97&"¦"&B97&"¦"&C97&"¦"&D97&"¦"&E97&"¦"&F97&"¦"&G97&"¦"&K97&"¦"&L97&"¦"&M97&"¦"&N97&"¦"&O97&"¦"&#REF! -> #REF! | R97: 46266
A98: Micro | B98: DELL PRO MICRO QCM1250 | C98: 4TH31H4 | D98: 889 | E98: Administração | F98: SABRINA CARVALHO DA SILVA | G98: Dell | K98: Status: Bom | L98: Intel Core i5-14500T | M98: 512GB SSD NVME | N98: 16GB DDR5 | P98: OK | Q98: =A98&"¦"&B98&"¦"&C98&"¦"&D98&"¦"&E98&"¦"&F98&"¦"&G98&"¦"&#REF!&"¦"&L98&"¦"&M98&"¦"&N98&"¦"&O98&"¦"&#REF! -> #REF! | R98: 46266
A99: Micro | B99: DELL PRO MICRO QCM1250 | C99: F2K31H4 | D99: 807 | E99: Administrativo | F99: ADRIANO BARBOSA RESTA | G99: Dell | K99: Status: Bom | L99: Intel Core i5-14500T | M99: 512GB SSD NVME | N99: 16GB DDR5 | P99: OK | Q99: =A99&"¦"&B99&"¦"&C99&"¦"&D99&"¦"&E99&"¦"&F99&"¦"&G99&"¦"&K99&"¦"&L99&"¦"&M99&"¦"&N99&"¦"&O99&"¦"&#REF! -> #REF! | R99: 46266
A100: Micro | B100: DELL PRO MICRO QCM1250 | C100: DTH31H4 | D100: 827 | E100: Almoxarifado | F100: USUÁRIO ALMOXARIFADO | G100: Dell | K100: Status: Bom | L100: Intel Core i5-14500T | M100: 512GB SSD NVME | N100: 16GB DDR5 | P100: OK | Q100: =A100&"¦"&B100&"¦"&C100&"¦"&D100&"¦"&E100&"¦"&F100&"¦"&G100&"¦"&K100&"¦"&L100&"¦"&M100&"¦"&N100&"¦"&O100&"¦"&#REF! -> #REF! | R100: 46266
A101: Micro | B101: DELL PRO MICRO QCM1250 | C101: HRH31H4 | D101: 817 | E101: Áudio | F101: USUÁRIO ÁUDIO | G101: Dell | K101: Status: Bom | L101: Intel Core i5-14500T | M101: 512GB SSD NVME | N101: 16GB DDR5 | P101: OK | Q101: =A101&"¦"&B101&"¦"&C101&"¦"&D101&"¦"&E101&"¦"&F101&"¦"&G101&"¦"&K101&"¦"&L101&"¦"&M101&"¦"&N101&"¦"&O101&"¦"&#REF! -> #REF! | R101: 46266
A102: Micro | B102: DELL PRO MICRO QCM1250 | C102: 80K31H4 | D102: 809 | E102: Cabine OFF | F102: USUÁRIO CABINE OFF | G102: Dell | K102: Status: Bom | L102: Intel Core i5-14500T | M102: 512GB SSD NVME | N102: 16GB DDR5 | P102: OK | Q102: =A102&"¦"&B102&"¦"&C102&"¦"&D102&"¦"&E102&"¦"&F102&"¦"&G102&"¦"&K102&"¦"&L102&"¦"&M102&"¦"&N102&"¦"&O102&"¦"&#REF! -> #REF! | R102: 46266
A103: Micro | B103: DELL PRO MICRO QCM1250 | C103: 6SH31H4 | D103: 816 | E103: Camarim | F103: USUÁRIO CAMARIM | G103: Dell | K103: Status: Bom | L103: Intel Core i5-14500T | M103: 512GB SSD NVME | N103: 16GB DDR5 | P103: OK | Q103: =A103&"¦"&B103&"¦"&C103&"¦"&D103&"¦"&E103&"¦"&F103&"¦"&G103&"¦"&K103&"¦"&L103&"¦"&M103&"¦"&N103&"¦"&O103&"¦"&#REF! -> #REF! | R103: 46266
A104: Micro | B104: DELL PRO MICRO QCM1250 | C104: CSH31H4 | D104: 881 | E104: Cartucheira | F104: USUÁRIO ÁUDIO | G104: Dell | K104: Status: Bom | L104: Intel Core i5-14500T | M104: 512GB SSD NVME | N104: 16GB DDR5 | P104: OK | Q104: =A104&"¦"&B104&"¦"&C104&"¦"&D104&"¦"&E104&"¦"&F104&"¦"&G104&"¦"&K104&"¦"&L104&"¦"&M104&"¦"&N104&"¦"&O104&"¦"&#REF! -> #REF! | R104: 46266
A105: Micro | B105: DELL PRO MICRO QCM1250 | C105: 92K31H4 | D105: 815 | E105: Comercial | F105: AMANDA DE OLIVEIRA MOREIRA | G105: Dell | K105: Status: Bom | L105: Intel Core i5-14500T | M105: 512GB SSD NVME | N105: 16GB DDR5 | P105: OK | Q105: =A105&"¦"&B105&"¦"&C105&"¦"&D105&"¦"&E105&"¦"&F105&"¦"&G105&"¦"&K105&"¦"&L105&"¦"&M105&"¦"&N105&"¦"&O105&"¦"&#REF! -> #REF! | R105: 46266
A106: Micro | B106: DELL PRO MICRO QCM1250 | C106: G3K31H4 | D106: 824 | E106: Comercial | F106: ISABEL CRISTINA GIUSTI DA SILVA | G106: Dell | K106: Status: Bom | L106: Intel Core i5-14500T | M106: 512GB SSD NVME | N106: 16GB DDR5 | P106: OK | Q106: =A106&"¦"&B106&"¦"&C106&"¦"&D106&"¦"&E106&"¦"&F106&"¦"&G106&"¦"&K106&"¦"&L106&"¦"&M106&"¦"&N106&"¦"&O106&"¦"&#REF! -> #REF! | R106: 46266
A107: Micro | B107: DELL PRO MICRO QCM1250 | C107: 6TH31H4 | D107: 835 | E107: Comercial | F107: FABIANA ALMINHANA | G107: Dell | K107: Status: Bom | L107: Intel Core i5-14500T | M107: 512GB SSD NVME | N107: 16GB DDR5 | P107: OK | Q107: =A107&"¦"&B107&"¦"&C107&"¦"&D107&"¦"&E107&"¦"&F107&"¦"&G107&"¦"&K107&"¦"&L107&"¦"&M107&"¦"&N107&"¦"&O107&"¦"&#REF! -> #REF! | R107: 46266
A108: Micro | B108: DELL PRO MICRO QCM1250 | C108: 1RH31H4 | D108: 822 | E108: Contabilidade | F108: VALDIR STANZIONE | G108: Dell | K108: Status: Bom | L108: Intel Core i5-14500T | M108: 512GB SSD NVME | N108: 16GB DDR5 | P108: OK | Q108: =A108&"¦"&B108&"¦"&C108&"¦"&D108&"¦"&E108&"¦"&F108&"¦"&G108&"¦"&K108&"¦"&L108&"¦"&M108&"¦"&N108&"¦"&O108&"¦"&#REF! -> #REF! | R108: 46266
A109: Micro | B109: DELL PRO MICRO QCM1250 | C109: G2K31H4 | D109: 886 | E109: Contabilidade | F109: SUSI SILVETE DA SILVA | G109: Dell | K109: Status: Bom | L109: Intel Core i5-14500T | M109: 512GB SSD NVME | N109: 16GB DDR5 | P109: OK | Q109: =A109&"¦"&B109&"¦"&C109&"¦"&D109&"¦"&E109&"¦"&F109&"¦"&G109&"¦"&K109&"¦"&L109&"¦"&M109&"¦"&N109&"¦"&O109&"¦"&#REF! -> #REF! | R109: 46266
A110: Micro | B110: DELL PRO MICRO QCM1250 | C110: D1K31H4 | D110: 866 | E110: Controladoria | F110: LUIZA CLAUDIA GONCALVES | G110: Dell | K110: Status: Bom | L110: Intel Core i5-14500T | M110: 512GB SSD NVME | N110: 16GB DDR5 | P110: OK | Q110: =A110&"¦"&B110&"¦"&C110&"¦"&D110&"¦"&E110&"¦"&F110&"¦"&G110&"¦"&K110&"¦"&L110&"¦"&M110&"¦"&N110&"¦"&O110&"¦"&#REF! -> #REF! | R110: 46266
A111: Micro | B111: DELL PRO MICRO QCM1250 | C111: 23K31H4 | D111: 871 | E111: Dallet | F111: THIAGO COSTA NARDON | G111: Dell | K111: Status: Bom | L111: Intel Core i5-14500T | M111: 512GB SSD NVME | N111: 16GB DDR5 | P111: OK | Q111: =A111&"¦"&B111&"¦"&C111&"¦"&D111&"¦"&E111&"¦"&F111&"¦"&G111&"¦"&K111&"¦"&L111&"¦"&M111&"¦"&N111&"¦"&O111&"¦"&#REF! -> #REF! | R111: 46266
A112: Micro | B112: DELL PRO MICRO QCM1250 | C112: 8SH31H4 | D112: 805 | E112: Depósito RH | F112: CENTRAL TECNICA | G112: Dell | K112: Status: Bom | L112: Intel Core i5-14500T | M112: 512GB SSD NVME | N112: 16GB DDR5 | P112: OK | Q112: =A112&"¦"&B112&"¦"&C112&"¦"&D112&"¦"&E112&"¦"&F112&"¦"&G112&"¦"&K112&"¦"&L112&"¦"&M112&"¦"&N112&"¦"&O112&"¦"&#REF! -> #REF! | R112: 46266
A113: Micro | B113: DELL PRO MICRO QCM1250 | C113: 12K31H4 | D113: 812 | E113: Depósito RH | F113: T.I | G113: Dell | K113: Status: Bom | L113: Intel Core i5-14500T | M113: 512GB SSD NVME | N113: 16GB DDR5 | P113: OK | Q113: =A113&"¦"&B113&"¦"&C113&"¦"&D113&"¦"&E113&"¦"&F113&"¦"&G113&"¦"&K113&"¦"&L113&"¦"&M113&"¦"&N113&"¦"&O113&"¦"&#REF! -> #REF! | R113: 46266
A114: Micro | B114: DELL PRO MICRO QCM1250 | C114: 8RH31H4 | D114: 860 | E114: Depósito RH | F114: T.I | G114: Dell | K114: Status: Bom | L114: Intel Core i5-14500T | M114: 512GB SSD NVME | N114: 16GB DDR5 | P114: OK | Q114: =A114&"¦"&B114&"¦"&C114&"¦"&D114&"¦"&E114&"¦"&F114&"¦"&G114&"¦"&K114&"¦"&L114&"¦"&M114&"¦"&N114&"¦"&O114&"¦"&#REF! -> #REF! | R114: 46266
...

Sheet Monitores
A1: Configurações | B1: Modelo | C1: Numero | D1: Patrimonio | E1: Departamento | F1: Nomes | G1: MARCA
A2: Monitor 18.5”, HD , 60Hz | B2: 9P1E | C2: 001 | D2: 439 | F2: JOÃO OTÁVIO | G2: Dell
A3: Monitor 18.5”, HD , 60Hz | B3: 9P1E | C3: 002 | D3: 455 | F3: JOÃO OTÁVIO | G3: Dell
A4: Monitor 18.5”, HD , 60Hz | B4: 9P1E | C4: 003 | D4: 668 | E4: Administrativo | F4: AMANDA PACHECO | G4: Dell
A5: Monitor 18.5”, HD , 60Hz | B5: 9P1E | C5: 004 | D5: 677 | E5: Administrativo | F5: AMANDA PACHECO | G5: Dell
A6: Monitor 18.5”, HD , 60Hz | B6: 9P1E | C6: 005 | D6: 663 | E6: Administrativo | F6: SABRINA | G6: Dell
A7: Monitor 18.5”, HD , 60Hz | B7: 9P1E | C7: 006 | D7: 664 | E7: Administrativo | F7: SABRINA | G7: Dell
A8: Monitor 18.5”, HD , 60Hz | B8: 9P1E | C8: 007 | D8: 683 | E8: Administrativo | F8: DAISY | G8: Dell
A9: Monitor 18.5”, HD , 60Hz | B9: 9P1E | C9: 008 | D9: 681 | E9: Administrativo | F9: DAISY | G9: Dell
A10: Monitor 18.5”, HD , 60Hz | B10: 9P1E | C10: 009 | D10: 667 | E10: Administrativo | F10: ADRIANO RESTA | G10: Dell
A11: Monitor 18.5”, HD , 60Hz | B11: 9P1E | C11: 010 | D11: 676 | E11: Administrativo | F11: ADRIANO RESTA | G11: Dell
A12: Monitor 21.5'', FHD , 75Hz | B12: 22B3HMF | C12: 011 | D12: 720 | E12: T.I | F12: BRUNO | G12: Dell
A13: Monitor 21.5'', FHD , 75Hz | B13: 22B3HMF | C13: 012 | D13: 726 | E13: T.I | F13: BRUNO | G13: Dell
A14: Monitor 18.5”, HD , 60Hz | B14: 9P1E | C14: 013 | D14: 424 | E14: T.I | F14: AMAILSON GAWLINSKI | G14: Dell
A15: Monitor 18.5”, HD , 60Hz | B15: 9P1E | C15: 014 | D15: 413 | E15: T.I | F15: AMAILSON GAWLINSKI | G15: Dell
A16: Monitor 18.5”, HD , 60Hz | B16: 9P1E | C16: 015 | D16: 691 | E16: T.I | F16: LIVRE | G16: Dell
A17: Monitor 18.5”, HD , 60Hz | B17: 9P1E | C17: 016 | D17: 426 | E17: T.I | F17: LIVRE | G17: Dell
A18: Monitor 18.5”, HD , 60Hz | B18: 9P1E | C18: 017 | D18: 666 | E18: Controladoria | F18: CLAUDIA | G18: Dell
A19: Monitor 18.5”, HD , 60Hz | B19: 9P1E | C19: 018 | D19: 669 | E19: Controladoria | F19: CLAUDIA | G19: Dell
A20: Monitor 23" , FHD , 60Hz | B20: P2317H | C20: 019 | D20: 88P5GL2 | E20: Dallet | F20: TIAGO NARDON | G20: Dell
A21: Monitor 23" , FHD , 60Hz | B21: P2317H | C21: 020 | D21: 50G5GL2 | E21: Dallet | F21: TIAGO NARDON | G21: Dell
A22: Monitor 18.5”, HD , 60Hz | B22: 9P1E | C22: 021 | D22: 420 | E22: Contabilidade | F22: SUSI | G22: Dell
A23: Monitor 18.5”, HD , 60Hz | B23: 9P1E | C23: 022 | D23: 438 | E23: Contabilidade | F23: SUSI | G23: Dell
A24: Monitor 18.5”, HD , 60Hz | B24: 9P1E | C24: 023 | D24: 440 | E24: Contabilidade | F24: VALDIR | G24: Dell
A25: Monitor 18.5”, HD , 60Hz | B25: 9P1E | C25: 024 | D25: 442 | E25: Contabilidade | F25: VALDIR | G25: Dell
A26: Monitor 18.5”, HD , 60Hz | B26: 9P1E | C26: 025 | D26: 415 | E26: Financeiro | F26: DEBORA | G26: Dell
A27: Monitor 18.5”, HD , 60Hz | B27: 9P1E | C27: 026 | D27: 427 | E27: Financeiro | F27: DEBORA | G27: Dell
A28: Monitor 18.5”, HD , 60Hz | B28: 9P1E | C28: 027 | D28: 447 | E28: Financeiro | F28: GUILHERME | G28: Dell
A29: Monitor 18.5”, HD , 60Hz | B29: 9P1E | C29: 028 | D29: 432 | E29: Financeiro | F29: GUILHERME | G29: Dell
A30: Monitor 18.5”, HD , 60Hz | B30: 9P1E | C30: 029 | D30: 429 | E30: Financeiro | F30: DEBORA | G30: Dell
A31: Monitor 18.5”, HD , 60Hz | B31: 9P1E | C31: 030 | D31: 450 | E31: Financeiro | F31: DEBORA | G31: Dell
A32: Monitor 18.5”, HD , 60Hz | B32: 9P1E | C32: 031 | D32: 684 | E32: Opec | F32: DUDA | G32: Dell
A33: Monitor 18.5”, HD , 60Hz | B33: 9P1E | C33: 032 | D33: 675 | E33: Opec | F33: DUDA | G33: Dell
A34: Monitor 18.5”, HD , 60Hz | B34: 9P1E | C34: 033 | D34: 678 | E34: Opec | F34: VITOR | G34: Dell
A35: Monitor 18.5”, HD , 60Hz | B35: 9P1E | C35: 034 | D35: 673 | E35: Opec | F35: VITOR | G35: Dell
A36: Monitor 21.5'', FHD, 75HZ | B36: 22B3HMF | C36: 035 | D36: 724 | E36: Marketing | F36: TIAGO PERONI | G36: Dell
A37: Monitor 21.5'', FHD, 75HZ | B37: 22B3HMF | C37: 036 | D37: 717 | E37: Marketing | F37: TIAGO PERONI | G37: Dell
A38: Monitor 23" , FHD , 60Hz | B38: Dell P2317H | C38: 037 | D38: 51K5GL2 | E38: Marketing | F38: RODRIGO CHAGAS | G38: Dell
A39: Monitor 23" , FHD , 60Hz | B39: Dell P2317H | C39: 038 | D39: 6K05GL2 | E39: Marketing | F39: RODRIGO CHAGAS | G39: Dell
A40: Monitor 21.5'', FHD, 75HZ | B40: 22B3HMF | C40: 039 | D40: 711 | E40: Marketing | F40: TIAGO FERREIRA | G40: Dell
A41: Monitor 21.5'', FHD, 75HZ | B41: 22B3HMF | C41: 040 | D41: 719 | E41: Marketing | F41: TIAGO FERREIRA | G41: Dell
A42: Monitor 21.5'', FHD, 75HZ | B42: 22B3HMF | C42: 041 | D42: 713 | E42: Marketing | F42: ESTER | G42: Dell
A43: Monitor 21.5'', FHD, 75HZ | B43: 22B3HMF | C43: 042 | D43: 721 | E43: Marketing | F43: ESTER | G43: Dell
A44: Monitor 21.5'', FHD, 75HZ | B44: 22B3HMF | C44: 043 | D44: 727 | E44: Marketing | F44: PAOLA RODRIGUES | G44: Dell
A45: Monitor 21.5'', FHD, 75HZ | B45: 22B3HMF | C45: 044 | D45: 714 | E45: Marketing | F45: PAOLA RODRIGUES | G45: Dell
A46: Monitor 21.5'', FHD, 75HZ | B46: 22B3HMF | C46: 045 | D46: 722 | E46: Marketing | F46: GABRIEL CAMPOS | G46: Dell
A47: Monitor 21.5'', FHD, 75HZ | B47: 22B3HMF | C47: 046 | D47: 710 | E47: Marketing | F47: GABRIEL CAMPOS | G47: Dell
A48: Monitor 18.5”, HD , 60Hz | B48: 9P1E | C48: 047 | D48: 448 | E48: Comercial | F48: ISABEL CRISTINA | G48: Dell
A49: Monitor 18.5”, HD , 60Hz | B49: 9P1E | C49: 048 | D49: 416 | E49: Comercial | F49: ISABEL CRISTINA | G49: Dell
A50: Monitor 18.5”, HD , 60Hz | B50: 9P1E | C50: 049 | D50: 674 | E50: Comercial | F50: AMANDA | G50: Dell
A51: Monitor 18.5”, HD , 60Hz | B51: 9P1E | C51: 050 | D51: 672 | E51: Comercial | F51: AMANDA | G51: Dell
A52: Monitor 18.5”, HD , 60Hz | B52: 9P1E | C52: 051 | D52: 670 | E52: Comercial | F52: FABIANA | G52: Dell
A53: Monitor 18.5”, HD , 60Hz | B53: 9P1E | C53: 052 | D53: 671 | E53: Comercial | F53: FABIANA | G53: Dell
A54: Monitor 18.5”, HD , 60Hz | B54: 9P1E | C54: 053 | D54: 451 | E54: Técnica | F54: GUILHERME STREVINKI | G54: Dell
A55: Monitor 18.5”, HD , 60Hz | B55: 9P1E | C55: 054 | D55: 423 | E55: Técnica | F55: FABIO | G55: Dell
A56: Monitor 18.5”, HD , 60Hz | B56: 9P1E | C56: 055 | D56: 446 | E56: Técnica | F56: FABIO | G56: Dell
A57: Monitor 18.5”, HD , 60Hz | B57: 9P1E | C57: 058 | D57: 434 | E57: Técnica | F57: SAMIR | G57: Dell
A58: Monitor 18.5”, HD , 60Hz | B58: 9P1E | C58: 059 | D58: 454 | E58: Técnica | F58: SAMIR | G58: Dell
A59: Monitor 18.5”, HD , 60Hz | B59: 9P1E | C59: 060 | D59: 452 | E59: Técnica | F59: PACHECO | G59: Dell
A60: Monitor 18.5”, HD , 60Hz | B60: 9P1E | C60: 061 | D60: 453 | E60: Almoxarifado | G60: Dell
A61: Monitor 18.5”, HD , 60Hz | B61: 9P1E | C61: 062 | D61: 418 | E61: Operações | F61: DIOGENES MORAES | G61: Dell
A62: Monitor 18.5”, HD , 60Hz | B62: 9P1E | C62: 063 | D62: 425 | E62: Operações | F62: DIOGENES MORAES | G62: Dell
A63: Monitor 24'', FHD, 100HZ | B63: 24B3HMF2 | C63: 064 | D63: 431 | E63: Cabine OFF | G63: Dell
A64: Monitor 18.5”, HD , 60Hz | B64: 9P1E | C64: 065 | D64: 417 | E64: Camarim | G64: Dell
A65: Monitor 18.5”, HD , 60Hz | B65: 9P1E | C65: 066 | D65: 430 | E65: Programação | F65: LUIS FABIANO | G65: Dell
A66: Monitor 18.5”, HD , 60Hz | B66: 9P1E | C66: 067 | D66: 428 | E66: Programação | F66: LUIS FABIANO | G66: Dell
A67: Monitor 18.5”, HD , 60Hz | B67: 9P1E | C67: 068 | D67: 449 | E67: Programação | F67: BERNARDO | G67: Dell
A68: Monitor 18.5”, HD , 60Hz | B68: 9P1E | C68: 069 | D68: 436 | E68: Programação | F68: BERNARDO | G68: Dell
A69: Monitor 24'', FHD, 100HZ | B69: 24B3HMF2 | C69: 070 | D69: 746 | E69: Jornalismo | F69: GUILHERME KEPLER | G69: Dell
A70: Monitor 21.5'', FHD, 75HZ | B70: 22B3HMF | C70: 071 | D70: 709 | E70: MEET | F70: MEET | G70: Dell
A71: Monitor 23" , FHD , 60Hz | B71: P2317H | C71: 072 | D71: 2GV4GL2 | E71: ILHA 4 | G71: Dell
A72: Monitor 23" , FHD , 60Hz | B72: P2317H | C72: 073 | D72: 81K5GL2 | E72: ILHA 4 | G72: Dell
A73: Monitor 24'', FHD, 100HZ | B73: 24B3HMF2 | C73: 074 | D73: 760 | E73: NUCLEOS | F73: GAVA | G73: Dell
A74: Monitor 24'', FHD, 100HZ | B74: 24B3HMF2 | C74: 075 | D74: 744 | E74: NUCLEOS | F74: CARLA SEABRA | G74: Dell
A75: Monitor 24'', FHD, 100HZ | B75: 24B3HMF2 | C75: 076 | D75: 742 | E75: NUCLEOS | F75: RICARDO AZEREDO | G75: Dell
A76: Monitor 18.5”, HD , 60Hz | B76: 9P1E | C76: 077 | D76: 433 | E76: Diretoria Comercial | F76: FRANCIELE ROSA | G76: Dell
A77: Monitor 18.5”, HD , 60Hz | B77: 9P1E | C77: 078 | D77: 685 | E77: Diretoria Comercial | F77: FRANCIELE ROSA | G77: Dell
A78: Monitor 24'', FHD, 100HZ | B78: 24B3HMF2 | C78: 079 | D78: 762 | E78: Diretoria Comercial | F78: SILVIO | G78: Dell
A79: Monitor 18.5”, HD , 60Hz | B79: 9P1E | C79: 080 | D79: 422 | E79: Recepção | F79: JULLIETE | G79: Dell
A80: Monitor 18.5”, HD , 60Hz | B80: 9P1E | C80: 081 | D80: 687 | E80: Recepção | F80: JULLIETE | G80: Dell
A81: Monitor 18.5”, HD , 60Hz | B81: 9P1E | C81: 082 | D81: 445 | E81: Diretoria Executiva | F81: MIRIAM | G81: Dell
A82: Monitor 24'', FHD, 100Hz | B82: 24B3HMF2 | C82: 083 | D82: 732 | E82: Jornalismo | F82: HENRI SOMENSI | G82: Dell
A83: Monitor 24'', FHD, 100Hz | B83: 24B3HMF2 | C83: 084 | D83: 753 | E83: Jornalismo | F83: LEONARDO LARA | G83: Dell
A84: Monitor 24'', FHD, 100Hz | B84: 24B3HMF2 | C84: 085 | D84: 761 | E84: Jornalismo | F84: BERNADO DA CUNHA | G84: Dell
A85: Monitor 24'', FHD, 100Hz | B85: 24B3HMF2 | C85: 086 | D85: 757 | E85: Jornalismo | F85: JOSÉ HENRIQUE | G85: Dell
A86: Monitor 24'', FHD, 100Hz | B86: 24B3HMF2 | C86: 087 | D86: 756 | E86: Jornalismo | F86: ALEXANDRE | G86: Dell
A87: Monitor 24'', FHD, 100Hz | B87: 24B3HMF2 | C87: 088 | D87: 734 | E87: Jornalismo | F87: CAMILA RAFAELA | G87: Dell
A88: Monitor 24'', FHD, 100Hz | B88: 24B3HMF2 | C88: 089 | D88: 749 | E88: Jornalismo | F88: BRUNA MARÇAL | G88: Dell
A89: Monitor 24'', FHD, 100Hz | B89: 24B3HMF2 | C89: 090 | D89: 755 | E89: Jornalismo | F89: ALANDER AGUIAR | G89: Dell
A90: Monitor 24'', FHD, 100Hz | B90: 24B3HMF2 | C90: 091 | D90: 754 | E90: Jornalismo | F90: NATAN MOREIRA | G90: Dell
A91: Monitor 24'', FHD, 100Hz | B91: 24B3HMF2 | C91: 092 | D91: 735 | E91: Jornalismo | F91: FELIPE CONTE | G91: Dell
A92: Monitor 24'', FHD, 100Hz | B92: 24B3HMF2 | C92: 093 | D92: 759 | E92: Jornalismo | F92: JOELLEN RIBEIRO | G92: Dell
A93: Monitor 24'', FHD, 100Hz | B93: 24B3HMF2 | C93: 094 | D93: 751 | E93: Jornalismo | F93: IGOR PEREIRA | G93: Dell
A94: Monitor 24'', FHD, 100Hz | B94: 24B3HMF2 | C94: 095 | D94: 752 | E94: Jornalismo | F94: ANA RITA | G94: Dell
A95: Monitor 24'', FHD, 100Hz | B95: 24B3HMF2 | C95: 096 | D95: 736 | E95: Jornalismo | F95: PAULA FABYOLLA | G95: Dell
A96: Monitor 24'', FHD, 100Hz | B96: 24B3HMF2 | C96: 097 | D96: 738 | E96: Jornalismo | F96: ROSA MARIA | G96: Dell
A97: Monitor 24'', FHD, 100Hz | B97: 24B3HMF2 | C97: 098 | D97: 737 | E97: Jornalismo | F97: VICENTE CIOTTA | G97: Dell
A98: Monitor 24'', FHD, 100Hz | B98: 24B3HMF2 | C98: 099 | D98: 733 | E98: Jornalismo | F98: FABIO ANDRE | G98: Dell
A99: Monitor 24'', FHD, 100Hz | B99: 24B3HMF2 | C99: 100 | D99: 739 | E99: Jornalismo | F99: FERNANDA PENNA | G99: Dell
A100: Monitor 24'', FHD, 100Hz | B100: 24B3HMF2 | C100: 101 | D100: 758 | E100: Jornalismo | F100: FERNANDA OLIVEIRA | G100: Dell
...

Sheet Responsável
A1: NOME | B1: CARGO | C1: SETOR
A2: PATRICIA INES BALDASSO | B2: Advogado | C2: Juridico
A3: LEANDRO MARTINS BONES | B3: Almoxarife Técnico | C3: Operacional
A4: MAURECI FERREIRA PIRES | B4: Almoxarife Técnico | C4: Operacional
A5: PAULO DA SILVA BANDEIRA | B5: Almoxarife Técnico | C5: Operacional
A6: AMANDA GOMES PACHECO SEVERO | B6: Analista Administrativo(a) | C6: Administração
A7: DAISY DA SILVA RUSSO | B7: Analista Administrativo(a) | C7: Administração
A8: SABRINA CARVALHO DA SILVA | B8: Analista Administrativo(a) | C8: Administração
A9: FABIANA ALMINHANA | B9: Analista Comercial | C9: Comercial
A10: ISABEL CRISTINA GIUSTI DA SILVA | B10: Analista Comercial | C10: Comercial
A11: SUSI SILVETE DA SILVA | B11: Analista Contábil | C11: Contabilidade
A12: RODRIGO CHAGAS FREITAS | B12: Analista de Criação | C12: Marketing
... A177: THIAGO COSTA NARDON | B177: Técnico de Manutenção TV | C177: Técnica

Sheet celular 
A1: MARCA | B1: MODELO | C1: RES | D1: PROCESSADOR | E1: RAM | F1: ARMAZENAMENTO | G1: CAMERA | H1: TELA | I1: SISTEMA | J1: DEPARTAMENTO | K1: ESTADO | L1: AVARIA | M1: BATERIA | N1: M/ BATERIA | O1: VOLTAGEM | P1: CAPACIDADE | Q1: Imagem | R1: LINK
A2: LG K10 (2016) | B2: LG-M2-2 | C2: HD (1280 x 720p) | D2: MediaTek MT6753 | E2: 1GB | F2: 16GB | G2: 13MP | H2: 5,3 polegadas, IPS LCD, resolução HD (1280 x 720 pixels), 277 ppi | I2: Android 6.0 | J2: Depósito do RH | K2: OK | L2: alguns arranhões na tela | M2: LG | N2: BL - 45A1H | O2: 3.8V | P2: 2220mAh(8.5Wh) | R2: https://kommodo.ai/i/8tgS2SIJc8RnlNsSLG6I
A3: LG K10 (2016) | B3: LG-M2-2 | C3: HD (1280 x 720p) | D3: MediaTek MT6753 | E3: 1GB | F3: 16GB | G3: 13MP | H3: 5,3 polegadas, IPS LCD, resolução HD (1280 x 720 pixels), 277 ppi | I3: Android 6.0 | J3: Depósito do RH | K3: OK | L3: alguns arranhões na tela | M3: LG | N3: BL - 45A1H | O3: 3.8V | P3: 2220mAh(8.5Wh) | Q3: Imagem inserida | R3: https://kommodo.ai/i/8tgS2SIJc8RnlNsSLG6I
A4: LG K10 (2016) | B4: LG-M2-2 | C4: HD (1280 x 720p) | D4: MediaTek MT6753 | E4: 1GB | F4: 16GB | G4: 13MP | H4: 5,3 polegadas, IPS LCD, resolução HD (1280 x 720 pixels), 277 ppi | I4: Android 6.0 | J4: Depósito do RH | K4: OK | L4: alguns arranhões na tela | M4: LG | N4: BL - 45A1H | O4: 3.8V | P4: 2.220mAh(8.5Wh) | Q4: Imagem inserida | R4: https://kommodo.ai/i/8tgS2SIJc8RnlNsSLG6I
A5: LG K10 (2017) | B5: M250 | C5: HD (720 x 1280 pixels) | D5: MediaTek MT6750 Octa- Core (4x 1.5GHz + 4x 1.0 GHz) | E5: 2GB | F5: 32GB | G5: 13MP (Abertura f/2.2) com Flash LED | H5: 5.3 polegadas, IPS LCD ,Resolução HD (1280 x 720 pixels) | I5: Android 7.0 Nouat | J5: Depósito do RH | K5: RUIM | L5: amarelamento tela quebrada varias partes lascadas | M5: LG | N5: BL-46G1F | O5: 3.85V | P5: 2700mAh | Q5: Imagem inserida | R5: https://kommodo.ai/i/nHaPLmGBovJMLHLOUKfH
A6: LG K10 (2017) | B6: M250 | C6: HD (720 x 1280 pixels) | D6: MediaTek MT6750 Octa- Core (4x 1.5GHz + 4x 1.0 GHz) | E6: 2GB | F6: 32GB | G6: 13MP (Abertura f/2.2) com Flash LED | H6: 5.3 polegadas, IPS LCD ,Resolução HD (1280 x 720 pixels) | I6: Android 7.0 Nouat | J6: Depósito do RH | K6: RUIM | L6: amarelamento tela quebrada varias partes lascadas | M6: LG | N6: BL-46G1F | O6: 3.85V | P6: 2700mAh | Q6: Imagem inserida | R6: https://kommodo.ai/i/nHaPLmGBovJMLHLOUKfH
A7: LG K10 (2017) | B7: M250 | C7: HD (720 x 1280 pixels) | D7: MediaTek MT6750 Octa- Core (4x 1.5GHz + 4x 1.0 GHz) | E7: 2GB | F7: 32GB | G7: 13MP (Abertura f/2.2) com Flash LED | H7: 5.3 polegadas, IPS LCD ,Resolução HD (1280 x 720 pixels) | I7: Android 7.0 Nouat | J7: Depósito do RH | K7: RUIM | L7: amarelamento tela quebrada varias partes lascadas | M7: LG | N7: BL-46G1F | O7: 3.85V | P7: 2700mAh | Q7: Imagem inserida | R7: https://kommodo.ai/i/nHaPLmGBovJMLHLOUKfH
A8: Motorol G8 | B8: XT2019-2 | C8: FULL HD+ ( 1080 x 2280 pixels) | D8: Qualcomm Snapdragon 665 (Octa-Core até 2.0GHz) | E8: 4GB | F8: 64GB | G8: Tripla: 48Mp (principal) + 16Mp ( Câmera de ação ultrawide) + 5MP(profundidade) | H8: IPS LCD de 6,3 polegadas | I8: Android 9.0 Pie (atualizável para Android 10) | J8: Depósito do RH | K8: RUIM | L8: amarelamento tela quebrada camera quebrada muitas partes lascadas | M8: fundo não abre | N8: fundo não abre | O8: fundo não abre | P8: fundo não abre | R8: https://kommodo.ai/i/8Ya9extv8J2wcSP7yTkq
A9: Motorol G8 | B9: XT2019-2 | C9: FULL HD+ ( 1080 x 2280 pixels) | D9: Qualcomm Snapdragon 665 (Octa-Core até 2.0GHz) | E9: 4GB | F9: 64GB | G9: Tripla: 48Mp (principal) + 16Mp ( Câmera de ação ultrawide) + 5MP(profundidade) | H9: IPS LCD de 6,3 polegadas | I9: Android 9.0 Pie (atualizável para Android 10) | J9: Depósito do RH | K9: RUIM | L9: amarelamento tela quebrada camera quebrada muitas partes lascadas | M9: fundo não abre | N9: fundo não abre | O9: fundo não abre | P9: fundo não abre | R9: https://kommodo.ai/i/8Ya9extv8J2wcSP7yTkq
A10: Nokia | B10: C2-01.5 | C10: QVGA (240 x 320 pixels) | D10: 235 MHz ARM9 | E10: 64 MB | F10: 45 a 65 MB internos, expansivel com microSD | G10: 3.2 Megapixels com zoom digital de 4x(sem flash) | H10: LCD TFT de 2.8 polegadas (Resolução: 240 x 320 pixels) | I10: Plataforma Symbian Series 40 (S40) | J10: Depósito do RH | K10: RUIM | L10: partes lascadas partes desgastadas e muitos arranhões | M10: Nokia | N10: BL-5C | O10: 3.7V | P10: 2.8Wh | R10: https://kommodo.ai/i/YhK1Vlol0LJVDobuZAFH
A11: Nokia | B11: C2-01.5 | C11: QVGA (240 x 320 pixels) | D11: 235 MHz ARM9 | E11: 64 MB | F11: 45 a 65 MB internos, expansivel com microSD | G11: 3.2 Megapixels com zoom digital de 4x(sem flash) | H11: LCD TFT de 2.8 polegadas (Resolução: 240 x 320 pixels) | I11: Plataforma Symbian Series 40 (S40) | J11: Depósito do RH | K11: RUIM | L11: partes lascadas partes desgastadas e muitos arranhões | M11: Nokia | N11: BL-5C | O11: 3.7V | P11: 2.8Wh | Q11: Imagem inserida | R11: https://kommodo.ai/i/YhK1Vlol0LJVDobuZAFH
A12: Nokia | B12: C2-01.5 | C12: QVGA (240 x 320 pixels) | D12: 235 MHz ARM9 | E12: 64 MB | F12: 45 a 65 MB internos, expansivel com microSD | G12: 3.2 Megapixels com zoom digital de 4x(sem flash) | H12: LCD TFT de 2.8 polegadas (Resolução: 240 x 320 pixels) | I12: Plataforma Symbian Series 40 (S40) | J12: Depósito do RH | K12: RUIM | L12: partes lascadas partes desgastadas e muitos arranhões | M12: Nokia | N12: BL-5C | O12: 3.7V | P12: 2.8Wh | R12: https://kommodo.ai/i/YhK1Vlol0LJVDobuZAFH
A13: Iphone 7 | C13: 1334 x 750 pixels a 326 ppi (Resolução Retina HD). | D13: Apple A10 Fusion (Quad-core) | E13: 2 GB | F13: 128 GB | G13: 12 MP (Abertura f/1.8) com Estabilização Óptica (OIS) | H13: Retina HD de 4,7 polegadas com tecnologia IPS | I13: iOS 10 | J13: Depósito do RH | K13: OK | L13: sem avarias aparentes | M13: fundo não abre | N13: fundo não abre | O13: fundo não abre | P13: 1.960 mAh | R13: https://kommodo.ai/i/PfWLMPq5pvjbYT4p38G4

Sheet conectores 
A1: MARCA | B1: POTÊNCIA | C1: TEN/E (IN) | D1: TEN/S (OUT) | E1: MODELO | F1: N/DP | G1: FAMILIA ADP | H1: FABRICANTE | I1: OBS | J1: ESTADO | K1: AVARIA | L1: IMAGEM
A2: DELL | B2: 65W | C2: 100-240V~1.6A/50-60Hz (bivolt) | D2: 19.5V ~ 3.34A | E2: LA65NS2-01 | F2: 06TM1C | G2: PA-12 FAMILY | H2: LITE-ON TECHNOLOGY CORPORATION | I2: 1 carregador completo | J2: BOM | K2: Sem avarias aparentes | L2: #VALUE!
A3: DELL | B3: 65W | C3: 100-240V~1.6A/50-60Hz (bivolt) | D3: 19.5V ~ 3.34A | E3: LA65NS2-01 | F3: 06TM1C | G3: PA-12 FAMILY | H3: LITE-ON TECHNOLOGY CORPORATION | I3: Sem cabo de força | J3: BOM | K3: Sem avarias aparentes | L3: #VALUE!
A4: DELL | B4: 65W | C4: 100-240V~1.6A/50-60Hz (bivolt) | D4: 19.5V ~ 3.34A | E4: LA65NS2-01 | F4: 06TM1C | G4: PA-12 FAMILY | H4: LITE-ON TECHNOLOGY CORPORATION | I4: 1 carregador completo - c/adaptador | J4: BOM | K4: Sem avarias aparentes | L4: #VALUE!
A5: DELL | B5: 65W | C5: 100-240V~1.6A/50-60Hz (bivolt) | D5: 19.5V ~ 3.34A | E5: LA65NS2-01 | F5: 06TM1C | G5: PA-12 FAMILY | H5: LITE-ON TECHNOLOGY CORPORATION | I5: 1 carregador completo | J5: BOM | K5: Sem avarias aparentes | L5: #VALUE!
A6: DELL | B6: 65W | C6: 100-240V~1.6A/50-60Hz (bivolt) | D6: 19.5V ~ 3.34A | E6: LA65NS2-01 | F6: 06TM1C | G6: PA-12 FAMILY | H6: LITE-ON TECHNOLOGY CORPORATION | I6: 1 carregador completo | J6: BOM | K6: Sem avarias aparentes | L6: #VALUE!
A7: DELL | B7: 65W | C7: 100-240V~1.6A/50-60Hz (bivolt) | D7: 19.5V ~ 3.34A | E7: LA65NS2-01 | F7: 06TM1C | G7: PA-12 FAMILY | H7: LITE-ON TECHNOLOGY CORPORATION | I7: 1 carregador completo | J7: BOM | K7: Sem avarias aparentes | L7: #VALUE!
A8: DELL | B8: 65W | C8: 100-240V~1.6A/50-60Hz (bivolt) | D8: 19.5V ~ 3.34A | E8: LA65NS2-01 | F8: 06TM1C | G8: PA-12 FAMILY | H8: LITE-ON TECHNOLOGY CORPORATION | I8: Sem cabo de força | J8: OK | K8: Bastante arranhado
A9: DELL | B9: 65W | C9: 100-240V~1.5A/50-60Hz (bivolt) | D9: 19.5V ~ 3.34A | E9: DA65PM111 | F9: MK947 | G9: CA Dell | H9: DELL Inc. | I9: 1 carregador completo | J9: BOM | K9: sem avarias aparentes | L9: #VALUE!
A10: DELL | B10: 65W | C10: Bivolt automatico (100-240V ~ 1.6A) | D10: 19.5V ~ 3.34A | E10: LA65NS2-01 | F10: 01N1FJ | G10: PA-12 FAMILY | H10: DELL Inc. | I10: 1 carregador COMPLETO | J10: BOM | K10: sem avarias aparentes
A11: DELL | B11: 65W | C11: Bivolt automatico (100-240V ~ 1.6A) | D11: 19.5V ~ 3.34A | E11: LA65NS2-01 | F11: 01N1FJ | G11: PA-12 FAMILY | H11: DELL Inc. | I11: 1 carregador COMPLETO | J11: BOM | K11: sem avarias aparentes | L11: #VALUE!
A12: Leader Electronics | C12: 100-240V ~ 50/60Hz 0.5A(Bivolt) | D12: 12V - 1.0A | E12: MU12-2120100-A1 | I12: 1 fonte de alimentação | J12: BOM | K12: sem avarias aparentes
A13: Leader Electronics | C13: 100-240V(Bivolt) | D13: 12V - 1.0A | E13: MU12-2120100-C5 | I13: 1 fonte de alimentação | J13: BOM | K13: sem avarias aparentes | L13: #VALUE!
A14: SWITCHING ADAPTOR | C14: 100-240V(Bivolt) | D14: DC 12V E 1000mA(1A) | I14: Adaptador de energia | J14: OK | K14: bastante sujo e com marcas de amarelamento
A15: Samsung | B15: 15W | C15: 100-240V ~ 50/60Hz 0.5A(Bivolt) | D15: 9,0V-1,67A | I15: Carregador COMPLETO cabo USB-C e adapatador sansung | J15: BOM | K15: sem avarias aparentes | L15: #VALUE!
A16: Samsung | B16: 15W | C16: 100-240V ~ 50/60Hz 0.5A(Bivolt) | D16: 9,0V-1,67A | I16: Carregador COMPLETO cabo USB-C e adapatador sansung | J16: BOM | K16: sem avarias aparentes | L16: #VALUE!
A17: Mass Power | C17: 100-240V~, 50/60Hz, 0.2A(Bivolt) | D17: 5.0V-0.6A | E17: NBS05B050060VB | I17: Adaptador de tomada | J17: BOM | K17: sem avarias aparentes
A18: Vasata | C18: 100-240V~50/60Hz 0.3A(Bivolt) | D18: 9.0V-0.6A (5.4W) | E18: P090060-2C1 | I18: Alimentação/Carregador | J18: BOM | K18: sem avarias aparentes
A19: FG | C19: 100-240V | D19: 12V em Corrente Contínua (DC) | E19: FC 12 02SI | I19: fonte de alimentação | J19: BOM | K19: sem avarias aparentes

Sheet A+
A1: MARCA | B1: MODELO | C1: Padrão Wi-Fi | D1: Velocidade Max | E1: Frequência | F1: Recursos extras | G1: Tec/REDE | H1: INTERFACE | I1: IMAGEM
A2: Genérico | B2: WiFi6-1300M (SKU: FY-01076) | C2: Wi-Fi 6 | D2: 1300Mbps | E2: Banda Dupla (2.4 GHz e 5.0 GHz) | F2: Conectividade Bluetooth(BT) integrada | G2: MU-MIMO | H2: Conexão USB
A3: Genérico | B3: WiFi6-1300M (SKU: FY-01076) | C3: Wi-Fi 6 | D3: 1300Mbps | E3: Banda Dupla (2.4 GHz e 5.0 GHz) | F3: Conectividade Bluetooth(BT) integrada | G3: MU-MIMO | H3: Conexão USB
A4: Genérico | B4: WiFi6-1300M (SKU: FY-01076) | C4: Wi-Fi 6 | D4: 1300Mbps | E4: Banda Dupla (2.4 GHz e 5.0 GHz) | F4: Conectividade Bluetooth(BT) integrada | G4: MU-MIMO | H4: Conexão USB
A5: Genérico | B5: WiFi6-1300M (SKU: FY-01076) | C5: Wi-Fi 6 | D5: 1300Mbps | E5: Banda Dupla (2.4 GHz e 5.0 GHz) | F5: Conectividade Bluetooth(BT) integrada | G5: MU-MIMO | H5: Conexão USB
A7: MARCA | B7: MODELO | C7: Padrão Wi-Fi | D7: Tipo de Dispositivo | E7: Interface/Rede | F7: Recursos/Segurança | G7: Suporte/VPN | H7: Alime/Elétrica | I7: Homologação | J7: OBS | K7: IMAGEM
A8: CISCO | B8: WRVS4400N V2 | C8: IEEE 802.11n | D8: Roteador de Segurança Gigabit Wireless-N com VPN | E8: 4 portas LAN Gigabit(10/100/1000 Mbps) 1 porta WAN Gigabit (10/100/1000 Mbps) | F8: Firewall SPI, Prevenção de Dos, Filtro de URL/Palavras-chave | G8: IPsec VPN (até 32 túneis simultaneos), QuickVPN | H8: 12V DC, 1A | I8: Certificado Anatel | J8: Alguns arranhões estado OK
A9: CISCO | B9: Cisco Aironet 1602I | C9: IEEE 802.11a, 802.11b, 802.11g e 802.11n | D9: Ponto de acesso corporativo indoor dual-band, com antenas internas | E9: 1 porta 10/100/1000BASE-T (RJ-45) + porta de console (RJ-45) | F9: WPA/WPA2, 802.1X, AES/TKIP; detecção de AP não autorizado e proteção de quadros de gerenciamento | G9: Sem VPN integrada; operação por controladora Cisco ou autônoma, conforme a versão | H9: 44–57 V DC; PoE IEEE 802.3af; consumo de 12,95 W | I9: Homologação Anatel não confirmada; verificar a etiqueta e o número do equipamento | J9: Amarelado e alguns arranhões estado Ok
A11: MARCA | B11: Modelo | C11: Área Ativa (Diagonal) | D11: Dimensões da Área Ativa | E11: Alimentação da Mesa | F11: Código de Barras (EAN)/FCC | G11: Alimentação da Caneta | H11: Níveis de Pressão da Caneta | I11: Resolução | J11: País de Fabricação | K11: IMAGEM
A12: C3 Tech (Distribuído por Coletek) | B12: Media Tablet 14.1" Prata (TB141) | C12: 14.1 Polegadas | D12: Aproximadamente 30,4 cm x 19,0 cm | E12: USB DC 5V - 40mA (Consumo elétrico ultra baixo) | F12: 7898927890254 | G12: 1 Pilha AAA (Palito) | H12: 1024 níveis de sensibilidade | I12: Até 4000 LPI (Linhas por polegada) | J12: w
A13: Wacom | B13: Intuos4 Large (PTK-840) | C13: 15,1 polegadas (383,5 mm) | D13: 325,1 x 203,2 mm | E13: 5V ⎓ 300mA (Via USB) | F13: HV4PTK | G13: Ressonância Eletromagnética (Sem fio e sem bateria) | H13: 2.048 níveis | I13: 5.080 lpi (Linhas por polegada) | J13: China
A15: COMPONENTE | B15: FORMATO | C15: TIPO | D15: QUANT | E15: MODELO | F15: OBSERVAÇÃO | G15: imagem
A16: RAM | B16: UDIMM/DIMM | C16: DDR | D16: 21
A17: RAM | B17: UDIMM/DIMM | C17: DDR | D17: 4
A18: PLACA DE VIDEO | C18: baixo perfil | D18: 6 | E18: ATI/AMD RADEON
A19: PLACA PCI | D19: 1 | E19: Pinnacle Systems
A20: Placa de Rede Sem Fio (Wi-Fi) | D20: 6 | E20: D-Link DWA-525 Wireless N 150 | F20: Circuito verde, etiqueta branca grande, grafismo laranja e preto com detalhes em triângulo.
A21: Placa Controladora / Interface | B21: PCI Padrão ou PCIe x1 | D21: 1 | E21: Genérica / Antiga | F21: Placa pequena escura (preta) com conectores externos no espelho (pode ser USB ou Som).
A22: Placa de Vídeo ou Rede de Servidor | B22: PCI / AGP ou PCIe | C22: PCI com porta paralela DB25 (ou serial/paralela), | D22: 1 | E22: Modelo com refrigeração passiva (Ex: GPU básica antiga ou placa de rede dedicada) | F22: Placa de circuito verde comprida com um grande dissipador de calor preto passivo.
A23: Placa de Expansão / Interface | D23: 2 | E23: Placa vertical estreita com circuito escuro/preto e conexão traseira (provável controladora). | F23: Genérica
A24: RAM | B24: Corsair | C24: DIMM | D24: 12 | E24: Corsair Value Select DDR3 | F24: Indicado para motherboards (placas-mãe) de PCs de escritório ou computadores desktop mais antigos compatíveis com tecnologia DDR3.
A25: RAM | C25: DIMM | D25: 10 | F25: Tecnologias mais antigas como SDRAM, DDR1 ou DDR2
A26: RAM | C26: DIMM | D26: 2 | F26: computadores de secretária (desktop)
A27: RAM | C27: dependendo do formato exato (DIMM/RDIMM) | D27: 2 | F27: DDR3
A28: RAM | C28: DIMM | D28: 6 | F28: Pentes de memória RAM UDIMM/DIMM de 240 pinos para PC de secretária
A29: RAM | C29: SO-DIMM | D29: 8 | F29: chips de memória soldados à placa de circuito impresso (PCB) verde, com contactos dourados na parte inferior e etiquetas autocolantes brancas com códigos de barras e especificações técnicas de fábrica.

Sheet Dados Gráfico
A1: Família | B1: Departamento normalizado | D1: Departamento | E1: Desktops/Micros | F1: Monitores | G1: Notebooks | H1: Impressoras | I1: Telefonia | J1: Outros
A2: =IF(TRIM(#REF!)="","Categoria não informada",IF(LEFT(UPPER(TRIM(#REF!)),7)="MONITOR","Monitores",IF(OR(LEFT(UPPER(TRIM(#REF!)),7)="DESKTOP",UPPER(TRIM(#REF!))="MICRO",LEFT(UPPER(TRIM(#REF!)),7)="MONTADO"),"Desktops/Micros",IF(LEFT(UPPER(TRIM(#REF!)),8)="NOTEBOOK","Notebooks",IF(LEFT(UPPER(TRIM(#REF!)),10)="IMPRESSORA","Impressoras",IF(LEFT(UPPER(TRIM(#REF!)),8)="TELEFONE","Telefonia","Outros")))))) -> #REF! | B2: =IF(TRIM(#REF!)="","SEM DEPARTAMENTO",IF(OR(UPPER(TRIM(#REF!))="TI",UPPER(TRIM(#REF!))="T.I"),"T.I",IF(OR(UPPER(TRIM(#REF!))="TECNICA",UPPER(TRIM(#REF!))="TÉCNICA"),"TÉCNICA",SUBSTITUTE(UPPER(TRIM(#REF!)),"SWICHER","SWITCHER")))) -> #REF! | D2: DEPÓSITO RH | E2: =COUNTIFS($B$2:$B$511,$D2,$A$2:$A$511,E$1) -> 0 | F2: =COUNTIFS($B$2:$B$511,$D2,$A$2:$A$511,F$1) -> 0 | G2: =COUNTIFS($B$2:$B$511,$D2,$A$2:$A$511,G$1) -> 0 | H2: =COUNTIFS($B$2:$B$511,$D2,$A$2:$A$511,H$1) -> 0 | I2: =COUNTIFS($B$2:$B$511,$D2,$A$2:$A$511,I$1) -> 0 | J2: =COUNTIFS($B$2:$B$511,$D2,$A$2:$A$511,J$1) -> 0
A3: =IF(TRIM(#REF!)="","Categoria não informada",IF(LEFT(UPPER(TRIM(#REF!)),7)="MONITOR","Monitores",IF(OR(LEFT(UPPER(TRIM(#REF!)),7)="DESKTOP",UPPER(TRIM(#REF!))="MICRO",LEFT(UPPER(TRIM(#REF!)),7)="MONTADO"),"Desktops/Micros",IF(LEFT(UPPER(TRIM(#REF!)),8)="NOTEBOOK","Notebooks",IF(LEFT(UPPER(TRIM(#REF!)),10)="IMPRESSORA","Impressoras",IF(LEFT(UPPER(TRIM(#REF!)),8)="TELEFONE","Telefonia","Outros")))))) -> #REF! | B3: =IF(TRIM(#REF!)="","SEM DEPARTAMENTO",IF(OR(UPPER(TRIM(#REF!))="TI",UPPER(TRIM(#REF!))="T.I"),"T.I",IF(OR(UPPER(TRIM(#REF!))="TECNICA",UPPER(TRIM(#REF!))="TÉCNICA"),"TÉCNICA",SUBSTITUTE(UPPER(TRIM(#REF!)),"SWICHER","SWITCHER")))) -> #REF! | D3: JORNALISMO | E3: =COUNTIFS($B$2:$B$511,$D3,$A$2:$A$511,E$1) -> 0 | F3: =COUNTIFS($B$2:$B$511,$D3,$A$2:$A$511,F$1) -> 0 | G3: =COUNTIFS($B$2:$B$511,$D3,$A$2:$A$511,G$1) -> 0 | H3: =COUNTIFS($B$2:$B$511,$D3,$A$2:$A$511,H$1) -> 0 | I3: =COUNTIFS($B$2:$B$511,$D3,$A$2:$A$511,I$1) -> 0 | J3: =COUNTIFS($B$2:$B$511,$D3,$A$2:$A$511,J$1) -> 0
A4: =IF(TRIM(#REF!)="","Categoria não informada",IF(LEFT(UPPER(TRIM(#REF!)),7)="MONITOR","Monitores",IF(OR(LEFT(UPPER(TRIM(#REF!)),7)="DESKTOP",UPPER(TRIM(#REF!))="MICRO",LEFT(UPPER(TRIM(#REF!)),7)="MONTADO"),"Desktops/Micros",IF(LEFT(UPPER(TRIM(#REF!)),8)="NOTEBOOK","Notebooks",IF(LEFT(UPPER(TRIM(#REF!)),10)="IMPRESSORA","Impressoras",IF(LEFT(UPPER(TRIM(#REF!)),8)="TELEFONE","Telefonia","Outros")))))) -> #REF! | B4: =IF(TRIM(#REF!)="","SEM DEPARTAMENTO",IF(OR(UPPER(TRIM(#REF!))="TI",UPPER(TRIM(#REF!))="T.I"),"T.I",IF(OR(UPPER(TRIM(#REF!))="TECNICA",UPPER(TRIM(#REF!))="TÉCNICA"),"TÉCNICA",SUBSTITUTE(UPPER(TRIM(#REF!)),"SWICHER","SWITCHER")))) -> #REF! | D4: MARKETING | E4: =COUNTIFS($B$2:$B$511,$D4,$A$2:$A$511,E$1) -> 0 | F4: =COUNTIFS($B$2:$B$511,$D4,$A$2:$A$511,F$1) -> 0 | G4: =COUNTIFS($B$2:$B$511,$D4,$A$2:$A$511,G$1) -> 0 | H4: =COUNTIFS($B$2:$B$511,$D4,$A$2:$A$511,H$1) -> 0 | I4: =COUNTIFS($B$2:$B$511,$D4,$A$2:$A$511,I$1) -> 0 | J4: =COUNTIFS($B$2:$B$511,$D4,$A$2:$A$511,J$1) -> 0
A5: =IF(TRIM(#REF!)="","Categoria não informada",IF(LEFT(UPPER(TRIM(#REF!)),7)="MONITOR","Monitores",IF(OR(LEFT(UPPER(TRIM(#REF!)),7)="DESKTOP",UPPER(TRIM(#REF!))="MICRO",LEFT(UPPER(TRIM(#REF!)),7)="MONTADO"),"Desktops/Micros",IF(LEFT(UPPER(TRIM(#REF!)),8)="NOTEBOOK","Notebooks",IF(LEFT(UPPER(TRIM(#REF!)),10)="IMPRESSORA","Impressoras",IF(LEFT(UPPER(TRIM(#REF!)),8)="TELEFONE","Telefonia","Outros")))))) -> #REF! | B5: =IF(TRIM(#REF!)="","SEM DEPARTAMENTO",IF(OR(UPPER(TRIM(#REF!))="TI",UPPER(TRIM(#REF!))="T.I"),"T.I",IF(OR(UPPER(TRIM(#REF!))="TECNICA",UPPER(TRIM(#REF!))="TÉCNICA"),"TÉCNICA",SUBSTITUTE(UPPER(TRIM(#REF!)),"SWICHER","SWITCHER")))) -> #REF! | D5: SWITCHER | E5: =COUNTIFS($B$2:$B$511,$D5,$A$2:$A$511,E$1) -> 0 | F5: =COUNTIFS($B$2:$B$511,$D5,$A$2:$A$511,F$1) -> 0 | G5: =COUNTIFS($B$2:$B$511,$D5,$A$2:$A$511,G$1) -> 0 | H5: =COUNTIFS($B$2:$B$511,$D5,$A$2:$A$511,H$1) -> 0 | I5: =COUNTIFS($B$2:$B$511,$D5,$A$2:$A$511,I$1) -> 0 | J5: =COUNTIFS($B$2:$B$511,$D5,$A$2:$A$511,J$1) -> 0
A6: =IF(TRIM(#REF!)="","Categoria não informada",IF(LEFT(UPPER(TRIM(#REF!)),7)="MONITOR","Monitores",IF(OR(LEFT(UPPER(TRIM(#REF!)),7)="DESKTOP",UPPER(TRIM(#REF!))="MICRO",LEFT(UPPER(TRIM(#REF!)),7)="MONTADO"),"Desktops/Micros",IF(LEFT(UPPER(TRIM(#REF!)),8)="NOTEBOOK","Notebooks",IF(LEFT(UPPER(TRIM(#REF!)),10)="IMPRESSORA","Impressoras",IF(LEFT(UPPER(TRIM(#REF!)),8)="TELEFONE","Telefonia","Outros")))))) -> #REF! | B6: =IF(TRIM(#REF!)="","SEM DEPARTAMENTO",IF(OR(UPPER(TRIM(#REF!))="TI",UPPER(TRIM(#REF!))="T.I"),"T.I",IF(OR(UPPER(TRIM(#REF!))="TECNICA",UPPER(TRIM(#REF!))="TÉCNICA"),"TÉCNICA",SUBSTITUTE(UPPER(TRIM(#REF!)),"SWICHER","SWITCHER")))) -> #REF! | D6: COMERCIAL | E6: =COUNTIFS($B$2:$B$511,$D6,$A$2:$A$511,E$1) -> 0 | F6: =COUNTIFS($B$2:$B$511,$D6,$A$2:$A$511,F$1) -> 0 | G6: =COUNTIFS($B$2:$B$511,$D6,$A$2:$A$511,G$1) -> 0 | H6: =COUNTIFS($B$2:$B$511,$D6,$A$2:$A$511,H$1) -> 0 | I6: =COUNTIFS($B$2:$B$511,$D6,$A$2:$A$511,I$1) -> 0 | J6: =COUNTIFS($B$2:$B$511,$D6,$A$2:$A$511,J$1) -> 0
A7: =IF(TRIM(#REF!)="","Categoria não informada",IF(LEFT(UPPER(TRIM(#REF!)),7)="MONITOR","Monitores",IF(OR(LEFT(UPPER(TRIM(#REF!)),7)="DESKTOP",UPPER(TRIM(#REF!))="MICRO",LEFT(UPPER(TRIM(#REF!)),7)="MONTADO"),"Desktops/Micros",IF(LEFT(UPPER(TRIM(#REF!)),8)="NOTEBOOK","Notebooks",IF(LEFT(UPPER(TRIM(#REF!)),10)="IMPRESSORA","Impressoras",IF(LEFT(UPPER(TRIM(#REF!)),8)="TELEFONE","Telefonia","Outros")))))) -> #REF! | B7: =IF(TRIM(#REF!)="","SEM DEPARTAMENTO",IF(OR(UPPER(TRIM(#REF!))="TI",UPPER(TRIM(#REF!))="T.I"),"T.I",IF(OR(UPPER(TRIM(#REF!))="TECNICA",UPPER(TRIM(#REF!))="TÉCNICA"),"TÉCNICA",SUBSTITUTE(UPPER(TRIM(#REF!)),"SWICHER","SWITCHER")))) -> #REF! | D7: TÉCNICA | E7: =COUNTIFS($B$2:$B$511,$D7,$A$2:$A$511,E$1) -> 0 | F7: =COUNTIFS($B$2:$B$511,$D7,$A$2:$A$511,F$1) -> 0 | G7: =COUNTIFS($B$2:$B$511,$D7,$A$2:$A$511,G$1) -> 0 | H7: =COUNTIFS($B$2:$B$511,$D7,$A$2:$A$511,H$1) -> 0 | I7: =COUNTIFS($B$2:$B$511,$D7,$A$2:$A$511,I$1) -> 0 | J7: =COUNTIFS($B$2:$B$511,$D7,$A$2:$A$511,J$1) -> 0
A8: =IF(TRIM(#REF!)="","Categoria não informada",IF(LEFT(UPPER(TRIM(#REF!)),7)="MONITOR","Monitores",IF(OR(LEFT(UPPER(TRIM(#REF!)),7)="DESKTOP",UPPER(TRIM(#REF!))="MICRO",LEFT(UPPER(TRIM(#REF!)),7)="MONTADO"),"Desktops/Micros",IF(LEFT(UPPER(TRIM(#REF!)),8)="NOTEBOOK","Notebooks",IF(LEFT(UPPER(TRIM(#REF!)),10)="IMPRESSORA","Impressoras",IF(LEFT(UPPER(TRIM(#REF!)),8)="TELEFONE","Telefonia","Outros")))))) -> #REF! | B8: =IF(TRIM(#REF!)="","SEM DEPARTAMENTO",IF(OR(UPPER(TRIM(#REF!))="TI",UPPER(TRIM(#REF!))="T.I"),"T.I",IF(OR(UPPER(TRIM(#REF!))="TECNICA",UPPER(TRIM(#REF!))="TÉCNICA"),"TÉCNICA",SUBSTITUTE(UPPER(TRIM(#REF!)),"SWICHER","SWITCHER")))) -> #REF! | D8: ADMINISTRATIVO | E8: =COUNTIFS($B$2:$B$511,$D8,$A$2:$A$511,E$1) -> 0 | F8: =COUNTIFS($B$2:$B$511,$D8,$A$2:$A$511,F$1) -> 0 | G8: =COUNTIFS($B$2:$B$511,$D8,$A$2:$A$511,G$1) -> 0 | H8: =COUNTIFS($B$2:$B$511,$D8,$A$2:$A$511,H$1) -> 0 | I8: =COUNTIFS($B$2:$B$511,$D8,$A$2:$A$511,I$1) -> 0 | J8: =COUNTIFS($B$2:$B$511,$D8,$A$2:$A$511,J$1) -> 0
A9: =IF(TRIM(#REF!)="","Categoria não informada",IF(LEFT(UPPER(TRIM(#REF!)),7)="MONITOR","Monitores",IF(OR(LEFT(UPPER(TRIM(#REF!)),7)="DESKTOP",UPPER(TRIM(#REF!))="MICRO",LEFT(UPPER(TRIM(#REF!)),7)="MONTADO"),"Desktops/Micros",IF(LEFT(UPPER(TRIM(#REF!)),8)="NOTEBOOK","Notebooks",IF(LEFT(UPPER(TRIM(#REF!)),10)="IMPRESSORA","Impressoras",IF(LEFT(UPPER(TRIM(#REF!)),8)="TELEFONE","Telefonia","Outros")))))) -> #REF! | B9: =IF(TRIM(#REF!)="","SEM DEPARTAMENTO",IF(OR(UPPER(TRIM(#REF!))="TI",UPPER(TRIM(#REF!))="T.I"),"T.I",IF(OR(UPPER(TRIM(#REF!))="TECNICA",UPPER(TRIM(#REF!))="TÉCNICA"),"TÉCNICA",SUBSTITUTE(UPPER(TRIM(#REF!)),"SWICHER","SWITCHER")))) -> #REF! | D9: RH | E9: =COUNTIFS($B$2:$B$511,$D9,$A$2:$A$511,E$1) -> 0 | F9: =COUNTIFS($B$2:$B$511,$D9,$A$2:$A$511,F$1) -> 0 | G9: =COUNTIFS($B$2:$B$511,$D9,$A$2:$A$511,G$1) -> 0 | H9: =COUNTIFS($B$2:$B$511,$D9,$A$2:$A$511,H$1) -> 0 | I9: =COUNTIFS($B$2:$B$511,$D9,$A$2:$A$511,I$1) -> 0 | J9: =COUNTIFS($B$2:$B$511,$D9,$A$2:$A$511,J$1) -> 0
A10: =IF(TRIM(#REF!)="","Categoria não informada",IF(LEFT(UPPER(TRIM(#REF!)),7)="MONITOR","Monitores",IF(OR(LEFT(UPPER(TRIM(#REF!)),7)="DESKTOP",UPPER(TRIM(#REF!))="MICRO",LEFT(UPPER(TRIM(#REF!)),7)="MONTADO"),"Desktops/Micros",IF(LEFT(UPPER(TRIM(#REF!)),8)="NOTEBOOK","Notebooks",IF(LEFT(UPPER(TRIM(#REF!)),10)="IMPRESSORA","Impressoras",IF(LEFT(UPPER(TRIM(#REF!)),8)="TELEFONE","Telefonia","Outros")))))) -> #REF! | B10: =IF(TRIM(#REF!)="","SEM DEPARTAMENTO",IF(OR(UPPER(TRIM(#REF!))="TI",UPPER(TRIM(#REF!))="T.I"),"T.I",IF(OR(UPPER(TRIM(#REF!))="TECNICA",UPPER(TRIM(#REF!))="TÉCNICA"),"TÉCNICA",SUBSTITUTE(UPPER(TRIM(#REF!)),"SWICHER","SWITCHER")))) -> #REF! | D10: T.I | E10: =COUNTIFS($B$2:$B$511,$D10,$A$2:$A$511,E$1) -> 0 | F10: =COUNTIFS($B$2:$B$511,$D10,$A$2:$A$511,F$1) -> 0 | G10: =COUNTIFS($B$2:$B$511,$D10,$A$2:$A$511,G$1) -> 0 | H10: =COUNTIFS($B$2:$B$511,$D10,$A$2:$A$511,H$1) -> 0 | I10: =COUNTIFS($B$2:$B$511,$D10,$A$2:$A$511,I$1) -> 0 | J10: =COUNTIFS($B$2:$B$511,$D10,$A$2:$A$511,J$1) -> 0
A11: =IF(TRIM(#REF!)="","Categoria não informada",IF(LEFT(UPPER(TRIM(#REF!)),7)="MONITOR","Monitores",IF(OR(LEFT(UPPER(TRIM(#REF!)),7)="DESKTOP",UPPER(TRIM(#REF!))="MICRO",LEFT(UPPER(TRIM(#REF!)),7)="MONTADO"),"Desktops/Micros",IF(LEFT(UPPER(TRIM(#REF!)),8)="NOTEBOOK","Notebooks",IF(LEFT(UPPER(TRIM(#REF!)),10)="IMPRESSORA","Impressoras",IF(LEFT(UPPER(TRIM(#REF!)),8)="TELEFONE","Telefonia","Outros")))))) -> #REF! | B11: =IF(TRIM(#REF!)="","SEM DEPARTAMENTO",IF(OR(UPPER(TRIM(#REF!))="TI",UPPER(TRIM(#REF!))="T.I"),"T.I",IF(OR(UPPER(TRIM(#REF!))="TECNICA",UPPER(TRIM(#REF!))="TÉCNICA"),"TÉCNICA",SUBSTITUTE(UPPER(TRIM(#REF!)),"SWICHER","SWITCHER")))) -> #REF! | D11: FINANCEIRO | E11: =COUNTIFS($B$2:$B$511,$D11,$A$2:$A$511,E$1) -> 0 | F11: =COUNTIFS($B$2:$B$511,$D11,$A$2:$A$511,F$1) -> 0 | G11: =COUNTIFS($B$2:$B$511,$D11,$A$2:$A$511,G$1) -> 0 | H11: =COUNTIFS($B$2:$B$511,$D11,$A$2:$A$511,H$1) -> 0 | I11: =COUNTIFS($B$2:$B$511,$D11,$A$2:$A$511,I$1) -> 0 | J11: =COUNTIFS($B$2:$B$511,$D11,$A$2:$A$511,J$1) -> 0
A12: =IF(TRIM(#REF!)="","Categoria não informada",IF(LEFT(UPPER(TRIM(#REF!)),7)="MONITOR","Monitores",IF(OR(LEFT(UPPER(TRIM(#REF!)),7)="DESKTOP",UPPER(TRIM(#REF!))="MICRO",LEFT(UPPER(TRIM(#REF!)),7)="MONTADO"),"Desktops/Micros",IF(LEFT(UPPER(TRIM(#REF!)),8)="NOTEBOOK","Notebooks",IF(LEFT(UPPER(TRIM(#REF!)),10)="IMPRESSORA","Impressoras",IF(LEFT(UPPER(TRIM(#REF!)),8)="TELEFONE","Telefonia","Outros")))))) -> #REF! | B12: =IF(TRIM(#REF!)="","SEM DEPARTAMENTO",IF(OR(UPPER(TRIM(#REF!))="TI",UPPER(TRIM(#REF!))="T.I"),"T.I",IF(OR(UPPER(TRIM(#REF!))="TECNICA",UPPER(TRIM(#REF!))="TÉCNICA"),"TÉCNICA",SUBSTITUTE(UPPER(TRIM(#REF!)),"SWICHER","SWITCHER")))) -> #REF! | D12: OPEC | E12: =COUNTIFS($B$2:$B$511,$D12,$A$2:$A$511,E$1) -> 0 | F12: =COUNTIFS($B$2:$B$511,$D12,$A$2:$A$511,F$1) -> 0 | G12: =COUNTIFS($B$2:$B$511,$D12,$A$2:$A$511,G$1) -> 0 | H12: =COUNTIFS($B$2:$B$511,$D12,$A$2:$A$511,H$1) -> 0 | I12: =COUNTIFS($B$2:$B$511,$D12,$A$2:$A$511,I$1) -> 0 | J12: =COUNTIFS($B$2:$B$511,$D12,$A$2:$A$511,J$1) -> 0
A13: =IF(TRIM(#REF!)="","Categoria não informada",IF(LEFT(UPPER(TRIM(#REF!)),7)="MONITOR","Monitores",IF(OR(LEFT(UPPER(TRIM(#REF!)),7)="DESKTOP",UPPER(TRIM(#REF!))="MICRO",LEFT(UPPER(TRIM(#REF!)),7)="MONTADO"),"Desktops/Micros",IF(LEFT(UPPER(TRIM(#REF!)),8)="NOTEBOOK","Notebooks",IF(LEFT(UPPER(TRIM(#REF!)),10)="IMPRESSORA","Impressoras",IF(LEFT(UPPER(TRIM(#REF!)),8)="TELEFONE","Telefonia","Outros")))))) -> #REF! | B13: =IF(TRIM(#REF!)="","SEM DEPARTAMENTO",IF(OR(UPPER(TRIM(#REF!))="TI",UPPER(TRIM(#REF!))="T.I"),"T.I",IF(OR(UPPER(TRIM(#REF!))="TECNICA",UPPER(TRIM(#REF!))="TÉCNICA"),"TÉCNICA",SUBSTITUTE(UPPER(TRIM(#REF!)),"SWICHER","SWITCHER")))) -> #REF! | D13: CONTABILIDADE | E13: =COUNTIFS($B$2:$B$511,$D13,$A$2:$A$511,E$1) -> 0 | F13: =COUNTIFS($B$2:$B$511,$D13,$A$2:$A$511,F$1) -> 0 | G13: =COUNTIFS($B$2:$B$511,$D13,$A$2:$A$511,G$1) -> 0 | H13: =COUNTIFS($B$2:$B$511,$D13,$A$2:$A$511,H$1) -> 0 | I13: =COUNTIFS($B$2:$B$511,$D13,$A$2:$A$511,I$1) -> 0 | J13: =COUNTIFS($B$2:$B$511,$D13,$A$2:$A$511,J$1) -> 0
A14: =IF(TRIM(#REF!)="","Categoria não informada",IF(LEFT(UPPER(TRIM(#REF!)),7)="MONITOR","Monitores",IF(OR(LEFT(UPPER(TRIM(#REF!)),7)="DESKTOP",UPPER(TRIM(#REF!))="MICRO",LEFT(UPPER(TRIM(#REF!)),7)="MONTADO"),"Desktops/Micros",IF(LEFT(UPPER(TRIM(#REF!)),8)="NOTEBOOK","Notebooks",IF(LEFT(UPPER(TRIM(#REF!)),10)="IMPRESSORA","Impressoras",IF(LEFT(UPPER(TRIM(#REF!)),8)="TELEFONE","Telefonia","Outros")))))) -> #REF! | B14: =IF(TRIM(#REF!)="","SEM DEPARTAMENTO",IF(OR(UPPER(TRIM(#REF!))="TI",UPPER(TRIM(#REF!))="T.I"),"T.I",IF(OR(UPPER(TRIM(#REF!))="TECNICA",UPPER(TRIM(#REF!))="TÉCNICA"),"TÉCNICA",SUBSTITUTE(UPPER(TRIM(#REF!)),"SWICHER","SWITCHER")))) -> #REF! | D14: DEMAIS DEPARTAMENTOS | E14: =COUNTIF($A$2:$A$511,E$1)-SUM(E2:E13)-E15 -> 0 | F14: =COUNTIF($A$2:$A$511,F$1)-SUM(F2:F13)-F15 -> 0 | G14: =COUNTIF($A$2:$A$511,G$1)-SUM(G2:G13)-G15 -> 0 | H14: =COUNTIF($A$2:$A$511,H$1)-SUM(H2:H13)-H15 -> 0 | I14: =COUNTIF($A$2:$A$511,I$1)-SUM(I2:I13)-I15 -> 0 | J14: =COUNTIF($A$2:$A$511,J$1)-SUM(J2:J13)-J15 -> 0
A15: =IF(TRIM(#REF!)="","Categoria não informada",IF(LEFT(UPPER(TRIM(#REF!)),7)="MONITOR","Monitores",IF(OR(LEFT(UPPER(TRIM(#REF!)),7)="DESKTOP",UPPER(TRIM(#REF!))="MICRO",LEFT(UPPER(TRIM(#REF!)),7)="MONTADO"),"Desktops/Micros",IF(LEFT(UPPER(TRIM(#REF!)),8)="NOTEBOOK","Notebooks",IF(LEFT(UPPER(TRIM(#REF!)),10)="IMPRESSORA","Impressoras",IF(LEFT(UPPER(TRIM(#REF!)),8)="TELEFONE","Telefonia","Outros")))))) -> #REF! | B15: =IF(TRIM(#REF!)="","SEM DEPARTAMENTO",IF(OR(UPPER(TRIM(#REF!))="TI",UPPER(TRIM(#REF!))="T.I"),"T.I",IF(OR(UPPER(TRIM(#REF!))="TECNICA",UPPER(TRIM(#REF!))="TÉCNICA"),"TÉCNICA",SUBSTITUTE(UPPER(TRIM(#REF!)),"SWICHER","SWITCHER")))) -> #REF! | D15: SEM DEPARTAMENTO | E15: =COUNTIFS($B$2:$B$511,"SEM DEPARTAMENTO",$A$2:$A$511,E$1) -> 0 | F15: =COUNTIFS($B$2:$B$511,"SEM DEPARTAMENTO",$A$2:$A$511,F$1) -> 0 | G15: =COUNTIFS($B$2:$B$511,"SEM DEPARTAMENTO",$A$2:$A$511,G$1) -> 0 | H15: =COUNTIFS($B$2:$B$511,"SEM DEPARTAMENTO",$A$2:$A$511,H$1) -> 0 | I15: =COUNTIFS($B$2:$B$511,"SEM DEPARTAMENTO",$A$2:$A$511,I$1) -> 0 | J15: =COUNTIFS($B$2:$B$511,"SEM DEPARTAMENTO",$A$2:$A$511,J$1) -> 0
A16: =IF(TRIM(#REF!)="","Categoria não informada",IF(LEFT(UPPER(TRIM(#REF!)),7)="MONITOR","Monitores",IF(OR(LEFT(UPPER(TRIM(#REF!)),7)="DESKTOP",UPPER(TRIM(#REF!))="MICRO",LEFT(UPPER(TRIM(#REF!)),7)="MONTADO"),"Desktops/Micros",IF(LEFT(UPPER(TRIM(#REF!)),8)="NOTEBOOK","Notebooks",IF(LEFT(UPPER(TRIM(#REF!)),10)="IMPRESSORA","Impressoras",IF(LEFT(UPPER(TRIM(#REF!)),8)="TELEFONE","Telefonia","Outros")))))) -> #REF! | B16: =IF(TRIM(#REF!)="","SEM DEPARTAMENTO",IF(OR(UPPER(TRIM(#REF!))="TI",UPPER(TRIM(#REF!))="T.I"),"T.I",IF(OR(UPPER(TRIM(#REF!))="TECNICA",UPPER(TRIM(#REF!))="TÉCNICA"),"TÉCNICA",SUBSTITUTE(UPPER(TRIM(#REF!)),"SWICHER","SWITCHER")))) -> #REF!
A17: =IF(TRIM(#REF!)="","Categoria não informada",IF(LEFT(UPPER(TRIM(#REF!)),7)="MONITOR","Monitores",IF(OR(LEFT(UPPER(TRIM(#REF!)),7)="DESKTOP",UPPER(TRIM(#REF!))="MICRO",LEFT(UPPER(TRIM(#REF!)),7)="MONTADO"),"Desktops/Micros",IF(LEFT(UPPER(TRIM(#REF!)),8)="NOTEBOOK","Notebooks",IF(LEFT(UPPER(TRIM(#REF!)),10)="IMPRESSORA","Impressoras",IF(LEFT(UPPER(TRIM(#REF!)),8)="TELEFONE","Telefonia","Outros")))))) -> #REF! | B17: =IF(TRIM(#REF!)="","SEM DEPARTAMENTO",IF(OR(UPPER(TRIM(#REF!))="TI",UPPER(TRIM(#REF!))="T.I"),"T.I",IF(OR(UPPER(TRIM(#REF!))="TECNICA",UPPER(TRIM(#REF!))="TÉCNICA"),"TÉCNICA",SUBSTITUTE(UPPER(TRIM(#REF!)),"SWICHER","SWITCHER")))) -> #REF!
A18: =IF(TRIM(#REF!)="","Categoria não informada",IF(LEFT(UPPER(TRIM(#REF!)),7)="MONITOR","Monitores",IF(OR(LEFT(UPPER(TRIM(#REF!)),7)="DESKTOP",UPPER(TRIM(#REF!))="MICRO",LEFT(UPPER(TRIM(#REF!)),7)="MONTADO"),"Desktops/Micros",IF(LEFT(UPPER(TRIM(#REF!)),8)="NOTEBOOK","Notebooks",IF(LEFT(UPPER(TRIM(#REF!)),10)="IMPRESSORA","Impressoras",IF(LEFT(UPPER(TRIM(#REF!)),8)="TELEFONE","Telefonia","Outros")))))) -> #REF! | B18: =IF(TRIM(#REF!)="","SEM DEPARTAMENTO",IF(OR(UPPER(TRIM(#REF!))="TI",UPPER(TRIM(#REF!))="T.I"),"T.I",IF(OR(UPPER(TRIM(#REF!))="TECNICA",UPPER(TRIM(#REF!))="TÉCNICA"),"TÉCNICA",SUBSTITUTE(UPPER(TRIM(#REF!)),"SWICHER","SWITCHER")))) -> #REF!
A19: =IF(TRIM(#REF!)="","Categoria não informada",IF(LEFT(UPPER(TRIM(#REF!)),7)="MONITOR","Monitores",IF(OR(LEFT(UPPER(TRIM(#REF!)),7)="DESKTOP",UPPER(TRIM(#REF!))="MICRO",LEFT(UPPER(TRIM(#REF!)),7)="MONTADO"),"Desktops/Micros",IF(LEFT(UPPER(TRIM(#REF!)),8)="NOTEBOOK","Notebooks",IF(LEFT(UPPER(TRIM(#REF!)),10)="IMPRESSORA","Impressoras",IF(LEFT(UPPER(TRIM(#REF!)),8)="TELEFONE","Telefonia","Outros")))))) -> #REF! | B19: =IF(TRIM(#REF!)="","SEM DEPARTAMENTO",IF(OR(UPPER(TRIM(#REF!))="TI",UPPER(TRIM(#REF!))="T.I"),"T.I",IF(OR(UPPER(TRIM(#REF!))="TECNICA",UPPER(TRIM(#REF!))="TÉCNICA"),"TÉCNICA",SUBSTITUTE(UPPER(TRIM(#REF!)),"SWICHER","SWITCHER")))) -> #REF!
A20: =IF(TRIM(#REF!)="","Categoria não informada",IF(LEFT(UPPER(TRIM(#REF!)),7)="MONITOR","Monitores",IF(OR(LEFT(UPPER(TRIM(#REF!)),7)="DESKTOP",UPPER(TRIM(#REF!))="MICRO",LEFT(UPPER(TRIM(#REF!)),7)="MONTADO"),"Desktops/Micros",IF(LEFT(UPPER(TRIM(#REF!)),8)="NOTEBOOK","Notebooks",IF(LEFT(UPPER(TRIM(#REF!)),10)="IMPRESSORA","Impressoras",IF(LEFT(UPPER(TRIM(#REF!)),8)="TELEFONE","Telefonia","Outros")))))) -> #REF! | B20: =IF(TRIM(#REF!)="","SEM DEPARTAMENTO",IF(OR(UPPER(TRIM(#REF!))="TI",UPPER(TRIM(#REF!))="T.I"),"T.I",IF(OR(UPPER(TRIM(#REF!))="TECNICA",UPPER(TRIM(#REF!))="TÉCNICA"),"TÉCNICA",SUBSTITUTE(UPPER(TRIM(#REF!)),"SWICHER","SWITCHER")))) -> #REF!
A21: =IF(TRIM(#REF!)="","Categoria não informada",IF(LEFT(UPPER(TRIM(#REF!)),7)="MONITOR","Monitores",IF(OR(LEFT(UPPER(TRIM(#REF!)),7)="DESKTOP",UPPER(TRIM(#REF!))="MICRO",LEFT(UPPER(TRIM(#REF!)),7)="MONTADO"),"Desktops/Micros",IF(LEFT(UPPER(TRIM(#REF!)),8)="NOTEBOOK","Notebooks",IF(LEFT(UPPER(TRIM(#REF!)),10)="IMPRESSORA","Impressoras",IF(LEFT(UPPER(TRIM(#REF!)),8)="TELEFONE","Telefonia","Outros")))))) -> #REF! | B21: =IF(TRIM(#REF!)="","SEM DEPARTAMENTO",IF(OR(UPPER(TRIM(#REF!))="TI",UPPER(TRIM(#REF!))="T.I"),"T.I",IF(OR(UPPER(TRIM(#REF!))="TECNICA",UPPER(TRIM(#REF!))="TÉCNICA"),"TÉCNICA",SUBSTITUTE(UPPER(TRIM(#REF!)),"SWICHER","SWITCHER")))) -> #REF!
A22: =IF(TRIM(#REF!)="","Categoria não informada",IF(LEFT(UPPER(TRIM(#REF!)),7)="MONITOR","Monitores",IF(OR(LEFT(UPPER(TRIM(#REF!)),7)="DESKTOP",UPPER(TRIM(#REF!))="MICRO",LEFT(UPPER(TRIM(#REF!)),7)="MONTADO"),"Desktops/Micros",IF(LEFT(UPPER(TRIM(#REF!)),8)="NOTEBOOK","Notebooks",IF(LEFT(UPPER(TRIM(#REF!)),10)="IMPRESSORA","Impressoras",IF(LEFT(UPPER(TRIM(#REF!)),8)="TELEFONE","Telefonia","Outros")))))) -> #REF! | B22: =IF(TRIM(#REF!)="","SEM DEPARTAMENTO",IF(OR(UPPER(TRIM(#REF!))="TI",UPPER(TRIM(#REF!))="T.I"),"T.I",IF(OR(UPPER(TRIM(#REF!))="TECNICA",UPPER(TRIM(#REF!))="TÉCNICA"),"TÉCNICA",SUBSTITUTE(UPPER(TRIM(#REF!)),"SWICHER","SWITCHER")))) -> #REF!
A23: =IF(TRIM(#REF!)="","Categoria não informada",IF(LEFT(UPPER(TRIM(#REF!)),7)="MONITOR","Monitores",IF(OR(LEFT(UPPER(TRIM(#REF!)),7)="DESKTOP",UPPER(TRIM(#REF!))="MICRO",LEFT(UPPER(TRIM(#REF!)),7)="MONTADO"),"Desktops/Micros",IF(LEFT(UPPER(TRIM(#REF!)),8)="NOTEBOOK","Notebooks",IF(LEFT(UPPER(TRIM(#REF!)),10)="IMPRESSORA","Impressoras",IF(LEFT(UPPER(TRIM(#REF!)),8)="TELEFONE","Telefonia","Outros")))))) -> #REF! | B23: =IF(TRIM(#REF!)="","SEM DEPARTAMENTO",IF(OR(UPPER(TRIM(#REF!))="TI",UPPER(TRIM(#REF!))="T.I"),"T.I",IF(OR(UPPER(TRIM(#REF!))="TECNICA",UPPER(TRIM(#REF!))="TÉCNICA"),"TÉCNICA",SUBSTITUTE(UPPER(TRIM(#REF!)),"SWICHER","SWITCHER")))) -> #REF!
A24: =IF(TRIM(#REF!)="","Categoria não informada",IF(LEFT(UPPER(TRIM(#REF!)),7)="MONITOR","Monitores",IF(OR(LEFT(UPPER(TRIM(#REF!)),7)="DESKTOP",UPPER(TRIM(#REF!))="MICRO",LEFT(UPPER(TRIM(#REF!)),7)="MONTADO"),"Desktops/Micros",IF(LEFT(UPPER(TRIM(#REF!)),8)="NOTEBOOK","Notebooks",IF(LEFT(UPPER(TRIM(#REF!)),10)="IMPRESSORA","Impressoras",IF(LEFT(UPPER(TRIM(#REF!)),8)="TELEFONE","Telefonia","Outros")))))) -> #REF! | B24: =IF(TRIM(#REF!)="","SEM DEPARTAMENTO",IF(OR(UPPER(TRIM(#REF!))="TI",UPPER(TRIM(#REF!))="T.I"),"T.I",IF(OR(UPPER(TRIM(#REF!))="TECNICA",UPPER(TRIM(#REF!))="TÉCNICA"),"TÉCNICA",SUBSTITUTE(UPPER(TRIM(#REF!)),"SWICHER","SWITCHER")))) -> #REF!
A25: =IF(TRIM(#REF!)="","Categoria não informada",IF(LEFT(UPPER(TRIM(#REF!)),7)="MONITOR","Monitores",IF(OR(LEFT(UPPER(TRIM(#REF!)),7)="DESKTOP",UPPER(TRIM(#REF!))="MICRO",LEFT(UPPER(TRIM(#REF!)),7)="MONTADO"),"Desktops/Micros",IF(LEFT(UPPER(TRIM(#REF!)),8)="NOTEBOOK","Notebooks",IF(LEFT(UPPER(TRIM(#REF!)),10)="IMPRESSORA","Impressoras",IF(LEFT(UPPER(TRIM(#REF!)),8)="TELEFONE","Telefonia","Outros")))))) -> #REF! | B25: =IF(TRIM(#REF!)="","SEM DEPARTAMENTO",IF(OR(UPPER(TRIM(#REF!))="TI",UPPER(TRIM(#REF!))="T.I"),"T.I",IF(OR(UPPER(TRIM(#REF!))="TECNICA",UPPER(TRIM(#REF!))="TÉCNICA"),"TÉCNICA",SUBSTITUTE(UPPER(TRIM(#REF!)),"SWICHER","SWITCHER")))) -> #REF!
A26: =IF(TRIM(#REF!)="","Categoria não informada",IF(LEFT(UPPER(TRIM(#REF!)),7)="MONITOR","Monitores",IF(OR(LEFT(UPPER(TRIM(#REF!)),7)="DESKTOP",UPPER(TRIM(#REF!))="MICRO",LEFT(UPPER(TRIM(#REF!)),7)="MONTADO"),"Desktops/Micros",IF(LEFT(UPPER(TRIM(#REF!)),8)="NOTEBOOK","Notebooks",IF(LEFT(UPPER(TRIM(#REF!)),10)="IMPRESSORA","Impressoras",IF(LEFT(UPPER(TRIM(#REF!)),8)="TELEFONE","Telefonia","Outros")))))) -> #REF! | B26: =IF(TRIM(#REF!)="","SEM DEPARTAMENTO",IF(OR(UPPER(TRIM(#REF!))="TI",UPPER(TRIM(#REF!))="T.I"),"T.I",IF(OR(UPPER(TRIM(#REF!))="TECNICA",UPPER(TRIM(#REF!))="TÉCNICA"),"TÉCNICA",SUBSTITUTE(UPPER(TRIM(#REF!)),"SWICHER","SWITCHER")))) -> #REF!
A27: =IF(TRIM(#REF!)="","Categoria não informada",IF(LEFT(UPPER(TRIM(#REF!)),7)="MONITOR","Monitores",IF(OR(LEFT(UPPER(TRIM(#REF!)),7)="DESKTOP",UPPER(TRIM(#REF!))="MICRO",LEFT(UPPER(TRIM(#REF!)),7)="MONTADO"),"Desktops/Micros",IF(LEFT(UPPER(TRIM(#REF!)),8)="NOTEBOOK","Notebooks",IF(LEFT(UPPER(TRIM(#REF!)),10)="IMPRESSORA","Impressoras",IF(LEFT(UPPER(TRIM(#REF!)),8)="TELEFONE","Telefonia","Outros")))))) -> #REF! | B27: =IF(TRIM(#REF!)="","SEM DEPARTAMENTO",IF(OR(UPPER(TRIM(#REF!))="TI",UPPER(TRIM(#REF!))="T.I"),"T.I",IF(OR(UPPER(TRIM(#REF!))="TECNICA",UPPER(TRIM(#REF!))="TÉCNICA"),"TÉCNICA",SUBSTITUTE(UPPER(TRIM(#REF!)),"SWICHER","SWITCHER")))) -> #REF!
... A511: =IF(TRIM(#REF!)="","Categoria não informada",IF(LEFT(UPPER(TRIM(#REF!)),7)="MONITOR","Monitores",IF(OR(LEFT(UPPER(TRIM(#REF!)),7)="DESKTOP",UPPER(TRIM(#REF!))="MICRO",LEFT(UPPER(TRIM(#REF!)),7)="MONTADO"),"Desktops/Micros",IF(LEFT(UPPER(TRIM(#REF!)),8)="NOTEBOOK","Notebooks",IF(LEFT(UPPER(TRIM(#REF!)),10)="IMPRESSORA","Impressoras",IF(LEFT(UPPER(TRIM(#REF!)),8)="TELEFONE","Telefonia","Outros")))))) -> #REF! | B511: =IF(TRIM(#REF!)="","SEM DEPARTAMENTO",IF(OR(UPPER(TRIM(#REF!))="TI",UPPER(TRIM(#REF!))="T.I"),"T.I",IF(OR(UPPER(TRIM(#REF!))="TECNICA",UPPER(TRIM(#REF!))="TÉCNICA"),"TÉCNICA",SUBSTITUTE(UPPER(TRIM(#REF!)),"SWICHER","SWITCHER")))) -> #REF!

Sheet Dados Dashboard
A1: Família | B1: Departamento normalizado | C1: Condição | D1: Marca normalizada | F1: Família | G1: Quantidade | I1: Departamento | J1: Quantidade | L1: Condição | M1: Quantidade | O1: Marca | P1: Quantidade | R1: Ranking Departamento | S1: Quantidade | U1: Ranking Marca | V1: Quantidade | X1: Departamento | Y1: Quantidade
A2: =IF(TRIM(controle!A2)="","Não informado",IF(LEFT(UPPER(TRIM(controle!A2)),7)="MONITOR","Monitores",IF(OR(LEFT(UPPER(TRIM(controle!A2)),7)="DESKTOP",UPPER(TRIM(controle!A2))="MICRO",LEFT(UPPER(TRIM(controle!A2)),7)="MONTADO"),"Desktops/Micros",IF(LEFT(UPPER(TRIM(controle!A2)),8)="NOTEBOOK","Notebooks",IF(LEFT(UPPER(TRIM(controle!A2)),10)="IMPRESSORA","Impressoras",IF(LEFT(UPPER(TRIM(controle!A2)),8)="TELEFONE","Telefonia","Outros")))))) -> Desktops/Micros | B2: =IF(TRIM(controle!E2)="","Sem departamento",IF(OR(UPPER(TRIM(controle!E2))="TI",UPPER(TRIM(controle!E2))="T.I"),"T.I",IF(OR(UPPER(TRIM(controle!E2))="TECNICA",UPPER(TRIM(controle!E2))="TÉCNICA"),"TÉCNICA",SUBSTITUTE(UPPER(TRIM(controle!E2)),"SWICHER","SWITCHER")))) -> DEPÓSITO RH | C2: =IF(TRIM(controle!K2)="","Não informado",IF(ISNUMBER(SEARCH("DESCARTE",UPPER(controle!K2))),"Descarte",IF(ISNUMBER(SEARCH("INATIVO",UPPER(controle!K2))),"Inativo",IF(OR(ISNUMBER(SEARCH("BOM",UPPER(controle!K2))),ISNUMBER(SEARCH("OK",UPPER(controle!K2)))),"Bom/OK","Outros")))) -> Inativo | D2: =IF(TRIM(controle!G2)="","Não informado",UPPER(TRIM(controle!G2))) -> DELL | F2: Desktops/Micros | G2: =COUNTIF(ListaInventario[Categoria],"Desktop*")+COUNTIF(ListaInventario[Categoria],"Micro")+COUNTIF(ListaInventario[Categoria],"MONTADO*") -> 196 | I2: =R2 -> Depósito RH | J2: =S2 -> 114 | L2: Bom/OK | M2: {=SUMPRODUCT(--(TRIM(ListaInventario[Observação])<>""),--((ISNUMBER(SEARCH("BOM",UPPER(ListaInventario[Observação])))+ISNUMBER(SEARCH("OK",UPPER(ListaInventario[Observação]))))>0),--(NOT(ISNUMBER(SEARCH("DESCARTE",UPPER(ListaInventario[Observação]))))),--(NOT(ISNUMBER(SEARCH("INATIVO",UPPER(ListaInventario[Observação]))))))} -> 404 | O2: =U2 -> Dell | P2: =V2 -> 405 | R2: {=_xlfn.LET(_xlpm.u,_xlfn.UNIQUE(_xlfn._xlws.FILTER(ListaInventario[Departamento],ListaInventario[Departamento]<>"")),_xlpm.c,COUNTIF(ListaInventario[Departamento],_xlpm.u),_xlfn.TAKE(_xlfn.SORTBY(_xlfn.HSTACK(_xlpm.u,_xlpm.c),_xlpm.c,-1),12))} -> Depósito RH | S2: 114 | U2: {=_xlfn.LET(_xlpm.u,_xlfn.UNIQUE(_xlfn._xlws.FILTER(ListaInventario[Marca],ListaInventario[Marca]<>"")),_xlpm.c,COUNTIF(ListaInventario[Marca],_xlpm.u),_xlfn.TAKE(_xlfn.SORTBY(_xlfn.HSTACK(_xlpm.u,_xlpm.c),_xlpm.c,-1),6))} -> Dell | V2: 405 | X2: {=_xlfn.LET(_xlpm.d,TRIM(ListaInventario[Departamento]),_xlpm.u,_xlfn.UNIQUE(_xlfn._xlws.FILTER(_xlpm.d,_xlpm.d<>"")),_xlpm.c,_xlfn.MAP(_xlpm.u,_xlfn.LAMBDA(_xlpm.x,SUM(--(_xlpm.d=_xlpm.x)))),_xlpm.s,_xlfn.SORTBY(_xlfn.HSTACK(_xlpm.u,_xlpm.c),_xlpm.c,-1),_xlpm.n,ROWS(_xlpm.s),IF(_xlpm.n<=60,_xlpm.s,_xlfn.VSTACK(_xlfn.TAKE(_xlpm.s,59),_xlfn.HSTACK("Demais departamentos",SUM(_xlfn.CHOOSECOLS(_xlfn.DROP(_xlpm.s,59),2))))))} -> Depósito RH | Y2: 207
A3: =IF(TRIM(controle!A3)="","Não informado",IF(LEFT(UPPER(TRIM(controle!A3)),7)="MONITOR","Monitores",IF(OR(LEFT(UPPER(TRIM(controle!A3)),7)="DESKTOP",UPPER(TRIM(controle!A3))="MICRO",LEFT(UPPER(TRIM(controle!A3)),7)="MONTADO"),"Desktops/Micros",IF(LEFT(UPPER(TRIM(controle!A3)),8)="NOTEBOOK","Notebooks",IF(LEFT(UPPER(TRIM(controle!A3)),10)="IMPRESSORA","Impressoras",IF(LEFT(UPPER(TRIM(controle!A3)),8)="TELEFONE","Telefonia","Outros")))))) -> Desktops/Micros | B3: =IF(TRIM(controle!E3)="","Sem departamento",IF(OR(UPPER(TRIM(controle!E3))="TI",UPPER(TRIM(controle!E3))="T.I"),"T.I",IF(OR(UPPER(TRIM(controle!E3))="TECNICA",UPPER(TRIM(controle!E3))="TÉCNICA"),"TÉCNICA",SUBSTITUTE(UPPER(TRIM(controle!E3)),"SWICHER","SWITCHER")))) -> DEPÓSITO RH | C3: =IF(TRIM(controle!K3)="","Não informado",IF(ISNUMBER(SEARCH("DESCARTE",UPPER(controle!K3))),"Descarte",IF(ISNUMBER(SEARCH("INATIVO",UPPER(controle!K3))),"Inativo",IF(OR(ISNUMBER(SEARCH("BOM",UPPER(controle!K3))),ISNUMBER(SEARCH("OK",UPPER(controle!K3)))),"Bom/OK","Outros")))) -> Bom/OK | D3: =IF(TRIM(controle!G3)="","Não informado",UPPER(TRIM(controle!G3))) -> DELL | F3: Monitores | G3: =COUNTIF(ListaInventario[Categoria],"Monitor*") -> 235 | I3: =R3 -> Depósito RH | J3: =S3 -> 93 | L3: Descarte | M3: =COUNTIF(ListaInventario[Observação],"*DESCARTE*") -> 81 | O3: =U3 -> Grandstream | P3: =V3 -> 53 | R3: Depósito RH | S3: 93 | U3: Grandstream | V3: 53 | X3: Jornalismo | Y3: 59
A4: =IF(TRIM(controle!A4)="","Não informado",IF(LEFT(UPPER(TRIM(controle!A4)),7)="MONITOR","Monitores",IF(OR(LEFT(UPPER(TRIM(controle!A4)),7)="DESKTOP",UPPER(TRIM(controle!A4))="MICRO",LEFT(UPPER(TRIM(controle!A4)),7)="MONTADO"),"Desktops/Micros",IF(LEFT(UPPER(TRIM(controle!A4)),8)="NOTEBOOK","Notebooks",IF(LEFT(UPPER(TRIM(controle!A4)),10)="IMPRESSORA","Impressoras",IF(LEFT(UPPER(TRIM(controle!A4)),8)="TELEFONE","Telefonia","Outros")))))) -> Desktops/Micros | B4: =IF(TRIM(controle!E4)="","Sem departamento",IF(OR(UPPER(TRIM(controle!E4))="TI",UPPER(TRIM(controle!E4))="T.I"),"T.I",IF(OR(UPPER(TRIM(controle!E4))="TECNICA",UPPER(TRIM(controle!E4))="TÉCNICA"),"TÉCNICA",SUBSTITUTE(UPPER(TRIM(controle!E4)),"SWICHER","SWITCHER")))) -> DEPÓSITO RH | C4: =IF(TRIM(controle!K4)="","Não informado",IF(ISNUMBER(SEARCH("DESCARTE",UPPER(controle!K4))),"Descarte",IF(ISNUMBER(SEARCH("INATIVO",UPPER(controle!K4))),"Inativo",IF(OR(ISNUMBER(SEARCH("BOM",UPPER(controle!K4))),ISNUMBER(SEARCH("OK",UPPER(controle!K4)))),"Bom/OK","Outros")))) -> Bom/OK | D4: =IF(TRIM(controle!G4)="","Não informado",UPPER(TRIM(controle!G4))) -> DELL | F4: Notebooks | G4: =COUNTIF(ListaInventario[Categoria],"Notebook*") -> 22 | I4: =R4 -> Jornalismo | J4: =S4 -> 59 | L4: Inativo | M4: =COUNTIF(ListaInventario[Observação],"*INATIVO*") -> 15 | O4: =U4 -> LG | P4: =V4 -> 42 | R4: Jornalismo | S4: 59 | U4: LG | V4: 42 | X4: Marketing | Y4: 21
A5: =IF(TRIM(controle!A5)="","Não informado",IF(LEFT(UPPER(TRIM(controle!A5)),7)="MONITOR","Monitores",IF(OR(LEFT(UPPER(TRIM(controle!A5)),7)="DESKTOP",UPPER(TRIM(controle!A5))="MICRO",LEFT(UPPER(TRIM(controle!A5)),7)="MONTADO"),"Desktops/Micros",IF(LEFT(UPPER(TRIM(controle!A5)),8)="NOTEBOOK","Notebooks",IF(LEFT(UPPER(TRIM(controle!A5)),10)="IMPRESSORA","Impressoras",IF(LEFT(UPPER(TRIM(controle!A5)),8)="TELEFONE","Telefonia","Outros")))))) -> Desktops/Micros | B5: =IF(TRIM(controle!E5)="","Sem departamento",IF(OR(UPPER(TRIM(controle!E5))="TI",UPPER(TRIM(controle!E5))="T.I"),"T.I",IF(OR(UPPER(TRIM(controle!E5))="TECNICA",UPPER(TRIM(controle!E5))="TÉCNICA"),"TÉCNICA",SUBSTITUTE(UPPER(TRIM(controle!E5)),"SWICHER","SWITCHER")))) -> DEPÓSITO RH | C5: =IF(TRIM(controle!K5)="","Não informado",IF(ISNUMBER(SEARCH("DESCARTE",UPPER(controle!K5))),"Descarte",IF(ISNUMBER(SEARCH("INATIVO",UPPER(controle!K5))),"Inativo",IF(OR(ISNUMBER(SEARCH("BOM",UPPER(controle!K5))),ISNUMBER(SEARCH("OK",UPPER(controle!K5)))),"Bom/OK","Outros")))) -> Bom/OK | D5: =IF(TRIM(controle!G5)="","Não informado",UPPER(TRIM(controle!G5))) -> DELL | F5: Impressoras | G5: =COUNTIF(ListaInventario[Categoria],"Impressora*") -> 7 | I5: =R5 -> Marketing | J5: =S5 -> 21 | L5: Outros | M5: =ROWS(ListaInventario[Observação])-SUM(M2:M4)-COUNTBLANK(ListaInventario[Observação]) -> 13 | O5: =U5 -> XEROX | P5: =V5 -> 4 | R5: Marketing | S5: 21 | U5: XEROX | V5: 4 | X5: Switcher | Y5: 16
A6: =IF(TRIM(controle!A6)="","Não informado",IF(LEFT(UPPER(TRIM(controle!A6)),7)="MONITOR","Monitores",IF(OR(LEFT(UPPER(TRIM(controle!A6)),7)="DESKTOP",UPPER(TRIM(controle!A6))="MICRO",LEFT(UPPER(TRIM(controle!A6)),7)="MONTADO"),"Desktops/Micros",IF(LEFT(UPPER(TRIM(controle!A6)),8)="NOTEBOOK","Notebooks",IF(LEFT(UPPER(TRIM(controle!A6)),10)="IMPRESSORA","Impressoras",IF(LEFT(UPPER(TRIM(controle!A6)),8)="TELEFONE","Telefonia","Outros")))))) -> Desktops/Micros | B6: =IF(TRIM(controle!E6)="","Sem departamento",IF(OR(UPPER(TRIM(controle!E6))="TI",UPPER(TRIM(controle!E6))="T.I"),"T.I",IF(OR(UPPER(TRIM(controle!E6))="TECNICA",UPPER(TRIM(controle!E6))="TÉCNICA"),"TÉCNICA",SUBSTITUTE(UPPER(TRIM(controle!E6)),"SWICHER","SWITCHER")))) -> DEPÓSITO RH | C6: =IF(TRIM(controle!K6)="","Não informado",IF(ISNUMBER(SEARCH("DESCARTE",UPPER(controle!K6))),"Descarte",IF(ISNUMBER(SEARCH("INATIVO",UPPER(controle!K6))),"Inativo",IF(OR(ISNUMBER(SEARCH("BOM",UPPER(controle!K6))),ISNUMBER(SEARCH("OK",UPPER(controle!K6)))),"Bom/OK","Outros")))) -> Bom/OK | D6: =IF(TRIM(controle!G6)="","Não informado",UPPER(TRIM(controle!G6))) -> DELL | F6: Telefonia | G6: =COUNTIF(ListaInventario[Categoria],"Telefone*") -> 53 | I6: =R6 -> Switcher | J6: =S6 -> 16 | L6: Não informado | M6: =COUNTBLANK(ListaInventario[Observação]) -> 0 | O6: =U6 -> Apple | P6: =V6 -> 3 | R6: Switcher | S6: 16 | U6: Apple | V6: 3 | X6: Comercial | Y6: 15
A7: =IF(TRIM(controle!A7)="","Não informado",IF(LEFT(UPPER(TRIM(controle!A7)),7)="MONITOR","Monitores",IF(OR(LEFT(UPPER(TRIM(controle!A7)),7)="DESKTOP",UPPER(TRIM(controle!A7))="MICRO",LEFT(UPPER(TRIM(controle!A7)),7)="MONTADO"),"Desktops/Micros",IF(LEFT(UPPER(TRIM(controle!A7)),8)="NOTEBOOK","Notebooks",IF(LEFT(UPPER(TRIM(controle!A7)),10)="IMPRESSORA","Impressoras",IF(LEFT(UPPER(TRIM(controle!A7)),8)="TELEFONE","Telefonia","Outros")))))) -> Desktops/Micros | B7: =IF(TRIM(controle!E7)="","Sem departamento",IF(OR(UPPER(TRIM(controle!E7))="TI",UPPER(TRIM(controle!E7))="T.I"),"T.I",IF(OR(UPPER(TRIM(controle!E7))="TECNICA",UPPER(TRIM(controle!E7))="TÉCNICA"),"TÉCNICA",SUBSTITUTE(UPPER(TRIM(controle!E7)),"SWICHER","SWITCHER")))) -> DEPÓSITO RH | C7: =IF(TRIM(controle!K7)="","Não informado",IF(ISNUMBER(SEARCH("DESCARTE",UPPER(controle!K7))),"Descarte",IF(ISNUMBER(SEARCH("INATIVO",UPPER(controle!K7))),"Inativo",IF(OR(ISNUMBER(SEARCH("BOM",UPPER(controle!K7))),ISNUMBER(SEARCH("OK",UPPER(controle!K7)))),"Bom/OK","Outros")))) -> Bom/OK | D7: =IF(TRIM(controle!G7)="","Não informado",UPPER(TRIM(controle!G7))) -> DELL | F7: Outros | G7: =ROWS(ListaInventario[Categoria])-SUM(G2:G6) -> 0 | I7: =R7 -> Comercial | J7: =S7 -> 15 | O7: =U7 -> Samsung | P7: =V7 -> 2 | R7: Comercial | S7: 15 | U7: Samsung | V7: 2 | X7: Administrativo | Y7: 13
A8: =IF(TRIM(controle!A8)="","Não informado",IF(LEFT(UPPER(TRIM(controle!A8)),7)="MONITOR","Monitores",IF(OR(LEFT(UPPER(TRIM(controle!A8)),7)="DESKTOP",UPPER(TRIM(controle!A8))="MICRO",LEFT(UPPER(TRIM(controle!A8)),7)="MONTADO"),"Desktops/Micros",IF(LEFT(UPPER(TRIM(controle!A8)),8)="NOTEBOOK","Notebooks",IF(LEFT(UPPER(TRIM(controle!A8)),10)="IMPRESSORA","Impressoras",IF(LEFT(UPPER(TRIM(controle!A8)),8)="TELEFONE","Telefonia","Outros")))))) -> Desktops/Micros | B8: =IF(TRIM(controle!E8)="","Sem departamento",IF(OR(UPPER(TRIM(controle!E8))="TI",UPPER(TRIM(controle!E8))="T.I"),"T.I",IF(OR(UPPER(TRIM(controle!E8))="TECNICA",UPPER(TRIM(controle!E8))="TÉCNICA"),"TÉCNICA",SUBSTITUTE(UPPER(TRIM(controle!E8)),"SWICHER","SWITCHER")))) -> DEPÓSITO RH | C8: =IF(TRIM(controle!K8)="","Não informado",IF(ISNUMBER(SEARCH("DESCARTE",UPPER(controle!K8))),"Descarte",IF(ISNUMBER(SEARCH("INATIVO",UPPER(controle!K8))),"Inativo",IF(OR(ISNUMBER(SEARCH("BOM",UPPER(controle!K8))),ISNUMBER(SEARCH("OK",UPPER(controle!K8)))),"Bom/OK","Outros")))) -> Bom/OK | D8: =IF(TRIM(controle!G8)="","Não informado",UPPER(TRIM(controle!G8))) -> DELL | I8: =R8 -> Administrativo | J8: =S8 -> 13 | O8: OUTRAS | P8: =ROWS(ListaInventario[Marca])-SUM(P2:P7)-P9 -> 4 | R8: Administrativo | S8: 13 | X8: RH | Y8: 13
A9: =IF(TRIM(controle!A9)="","Não informado",IF(LEFT(UPPER(TRIM(controle!A9)),7)="MONITOR","Monitores",IF(OR(LEFT(UPPER(TRIM(controle!A9)),7)="DESKTOP",UPPER(TRIM(controle!A9))="MICRO",LEFT(UPPER(TRIM(controle!A9)),7)="MONTADO"),"Desktops/Micros",IF(LEFT(UPPER(TRIM(controle!A9)),8)="NOTEBOOK","Notebooks",IF(LEFT(UPPER(TRIM(controle!A9)),10)="IMPRESSORA","Impressoras",IF(LEFT(UPPER(TRIM(controle!A9)),8)="TELEFONE","Telefonia","Outros")))))) -> Desktops/Micros | B9: =IF(TRIM(controle!E9)="","Sem departamento",IF(OR(UPPER(TRIM(controle!E9))="TI",UPPER(TRIM(controle!E9))="T.I"),"T.I",IF(OR(UPPER(TRIM(controle!E9))="TECNICA",UPPER(TRIM(controle!E9))="TÉCNICA"),"TÉCNICA",SUBSTITUTE(UPPER(TRIM(controle!E9)),"SWICHER","SWITCHER")))) -> DEPÓSITO RH | C9: =IF(TRIM(controle!K9)="","Não informado",IF(ISNUMBER(SEARCH("DESCARTE",UPPER(controle!K9))),"Descarte",IF(ISNUMBER(SEARCH("INATIVO",UPPER(controle!K9))),"Inativo",IF(OR(ISNUMBER(SEARCH("BOM",UPPER(controle!K9))),ISNUMBER(SEARCH("OK",UPPER(controle!K9)))),"Bom/OK","Outros")))) -> Bom/OK | D9: =IF(TRIM(controle!G9)="","Não informado",UPPER(TRIM(controle!G9))) -> DELL | I9: =R9 -> RH | J9: =S9 -> 13 | O9: NÃO INFORMADO | P9: =COUNTBLANK(ListaInventario[Marca]) -> 0 | R9: RH | S9: 13 | X9: T.I | Y9: 12
A10: =IF(TRIM(controle!A10)="","Não informado",IF(LEFT(UPPER(TRIM(controle!A10)),7)="MONITOR","Monitores",IF(OR(LEFT(UPPER(TRIM(controle!A10)),7)="DESKTOP",UPPER(TRIM(controle!A10))="MICRO",LEFT(UPPER(TRIM(controle!A10)),7)="MONTADO"),"Desktops/Micros",IF(LEFT(UPPER(TRIM(controle!A10)),8)="NOTEBOOK","Notebooks",IF(LEFT(UPPER(TRIM(controle!A10)),10)="IMPRESSORA","Impressoras",IF(LEFT(UPPER(TRIM(controle!A10)),8)="TELEFONE","Telefonia","Outros")))))) -> Desktops/Micros | B10: =IF(TRIM(controle!E10)="","Sem departamento",IF(OR(UPPER(TRIM(controle!E10))="TI",UPPER(TRIM(controle!E10))="T.I"),"T.I",IF(OR(UPPER(TRIM(controle!E10))="TECNICA",UPPER(TRIM(controle!E10))="TÉCNICA"),"TÉCNICA",SUBSTITUTE(UPPER(TRIM(controle!E10)),"SWICHER","SWITCHER")))) -> DEPÓSITO RH | C10: =IF(TRIM(controle!K10)="","Não informado",IF(ISNUMBER(SEARCH("DESCARTE",UPPER(controle!K10))),"Descarte",IF(ISNUMBER(SEARCH("INATIVO",UPPER(controle!K10))),"Inativo",IF(OR(ISNUMBER(SEARCH("BOM",UPPER(controle!K10))),ISNUMBER(SEARCH("OK",UPPER(controle!K10)))),"Bom/OK","Outros")))) -> Bom/OK | D10: =IF(TRIM(controle!G10)="","Não informado",UPPER(TRIM(controle!G10))) -> DELL | I10: =R10 -> T.I | J10: =S10 -> 12 | R10: T.I | S10: 12 | X10: Técnica | Y10: 12
A11: =IF(TRIM(controle!A11)="","Não informado",IF(LEFT(UPPER(TRIM(controle!A11)),7)="MONITOR","Monitores",IF(OR(LEFT(UPPER(TRIM(controle!A11)),7)="DESKTOP",UPPER(TRIM(controle!A11))="MICRO",LEFT(UPPER(TRIM(controle!A11)),7)="MONTADO"),"Desktops/Micros",IF(LEFT(UPPER(TRIM(controle!A11)),8)="NOTEBOOK","Notebooks",IF(LEFT(UPPER(TRIM(controle!A11)),10)="IMPRESSORA","Impressoras",IF(LEFT(UPPER(TRIM(controle!A11)),8)="TELEFONE","Telefonia","Outros")))))) -> Desktops/Micros | B11: =IF(TRIM(controle!E11)="","Sem departamento",IF(OR(UPPER(TRIM(controle!E11))="TI",UPPER(TRIM(controle!E11))="T.I"),"T.I",IF(OR(UPPER(TRIM(controle!E11))="TECNICA",UPPER(TRIM(controle!E11))="TÉCNICA"),"TÉCNICA",SUBSTITUTE(UPPER(TRIM(controle!E11)),"SWICHER","SWITCHER")))) -> DEPÓSITO RH | C11: =IF(TRIM(controle!K11)="","Não informado",IF(ISNUMBER(SEARCH("DESCARTE",UPPER(controle!K11))),"Descarte",IF(ISNUMBER(SEARCH("INATIVO",UPPER(controle!K11))),"Inativo",IF(OR(ISNUMBER(SEARCH("BOM",UPPER(controle!K11))),ISNUMBER(SEARCH("OK",UPPER(controle!K11)))),"Bom/OK","Outros")))) -> Bom/OK | D11: =IF(TRIM(controle!G11)="","Não informado",UPPER(TRIM(controle!G11))) -> DELL | I11: =R11 -> Financeiro | J11: =S11 -> 11 | R11: Financeiro | S11: 11 | X11: Financeiro | Y11: 11
A12: =IF(TRIM(controle!A12)="","Não informado",IF(LEFT(UPPER(TRIM(controle!A12)),7)="MONITOR","Monitores",IF(OR(LEFT(UPPER(TRIM(controle!A12)),7)="DESKTOP",UPPER(TRIM(controle!A12))="MICRO",LEFT(UPPER(TRIM(controle!A12)),7)="MONTADO"),"Desktops/Micros",IF(LEFT(UPPER(TRIM(controle!A12)),8)="NOTEBOOK","Notebooks",IF(LEFT(UPPER(TRIM(controle!A12)),10)="IMPRESSORA","Impressoras",IF(LEFT(UPPER(TRIM(controle!A12)),8)="TELEFONE","Telefonia","Outros")))))) -> Desktops/Micros | B12: =IF(TRIM(controle!E12)="","Sem departamento",IF(OR(UPPER(TRIM(controle!E12))="TI",UPPER(TRIM(controle!E12))="T.I"),"T.I",IF(OR(UPPER(TRIM(controle!E12))="TECNICA",UPPER(TRIM(controle!E12))="TÉCNICA"),"TÉCNICA",SUBSTITUTE(UPPER(TRIM(controle!E12)),"SWICHER","SWITCHER")))) -> DEPÓSITO RH | C12: =IF(TRIM(controle!K12)="","Não informado",IF(ISNUMBER(SEARCH("DESCARTE",UPPER(controle!K12))),"Descarte",IF(ISNUMBER(SEARCH("INATIVO",UPPER(controle!K12))),"Inativo",IF(OR(ISNUMBER(SEARCH("BOM",UPPER(controle!K12))),ISNUMBER(SEARCH("OK",UPPER(controle!K12)))),"Bom/OK","Outros")))) -> Bom/OK | D12: =IF(TRIM(controle!G12)="","Não informado",UPPER(TRIM(controle!G12))) -> DELL | I12: =R12 -> Técnica | J12: =S12 -> 11 | R12: Técnica | S12: 11 | X12: OPEC | Y12: 9
A13: =IF(TRIM(controle!A13)="","Não informado",IF(LEFT(UPPER(TRIM(controle!A13)),7)="MONITOR","Monitores",IF(OR(LEFT(UPPER(TRIM(controle!A13)),7)="DESKTOP",UPPER(TRIM(controle!A13))="MICRO",LEFT(UPPER(TRIM(controle!A13)),7)="MONTADO"),"Desktops/Micros",IF(LEFT(UPPER(TRIM(controle!A13)),8)="NOTEBOOK","Notebooks",IF(LEFT(UPPER(TRIM(controle!A13)),10)="IMPRESSORA","Impressoras",IF(LEFT(UPPER(TRIM(controle!A13)),8)="TELEFONE","Telefonia","Outros")))))) -> Desktops/Micros | B13: =IF(TRIM(controle!E13)="","Sem departamento",IF(OR(UPPER(TRIM(controle!E13))="TI",UPPER(TRIM(controle!E13))="T.I"),"T.I",IF(OR(UPPER(TRIM(controle!E13))="TECNICA",UPPER(TRIM(controle!E13))="TÉCNICA"),"TÉCNICA",SUBSTITUTE(UPPER(TRIM(controle!E13)),"SWICHER","SWITCHER")))) -> DEPÓSITO RH | C13: =IF(TRIM(controle!K13)="","Não informado",IF(ISNUMBER(SEARCH("DESCARTE",UPPER(controle!K13))),"Descarte",IF(ISNUMBER(SEARCH("INATIVO",UPPER(controle!K13))),"Inativo",IF(OR(ISNUMBER(SEARCH("BOM",UPPER(controle!K13))),ISNUMBER(SEARCH("OK",UPPER(controle!K13)))),"Bom/OK","Outros")))) -> Bom/OK | D13: =IF(TRIM(controle!G13)="","Não informado",UPPER(TRIM(controle!G13))) -> DELL | I13: =R13 -> OPEC | J13: =S13 -> 9 | R13: OPEC | S13: 9 | X13: Contabilidade | Y13: 8
A14: =IF(TRIM(controle!A14)="","Não informado",IF(LEFT(UPPER(TRIM(controle!A14)),7)="MONITOR","Monitores",IF(OR(LEFT(UPPER(TRIM(controle!A14)),7)="DESKTOP",UPPER(TRIM(controle!A14))="MICRO",LEFT(UPPER(TRIM(controle!A14)),7)="MONTADO"),"Desktops/Micros",IF(LEFT(UPPER(TRIM(controle!A14)),8)="NOTEBOOK","Notebooks",IF(LEFT(UPPER(TRIM(controle!A14)),10)="IMPRESSORA","Impressoras",IF(LEFT(UPPER(TRIM(controle!A14)),8)="TELEFONE","Telefonia","Outros")))))) -> Desktops/Micros | B14: =IF(TRIM(controle!E14)="","Sem departamento",IF(OR(UPPER(TRIM(controle!E14))="TI",UPPER(TRIM(controle!E14))="T.I"),"T.I",IF(OR(UPPER(TRIM(controle!E14))="TECNICA",UPPER(TRIM(controle!E14))="TÉCNICA"),"TÉCNICA",SUBSTITUTE(UPPER(TRIM(controle!E14)),"SWICHER","SWITCHER")))) -> DEPÓSITO RH | C14: =IF(TRIM(controle!K14)="","Não informado",IF(ISNUMBER(SEARCH("DESCARTE",UPPER(controle!K14))),"Descarte",IF(ISNUMBER(SEARCH("INATIVO",UPPER(controle!K14))),"Inativo",IF(OR(ISNUMBER(SEARCH("BOM",UPPER(controle!K14))),ISNUMBER(SEARCH("OK",UPPER(controle!K14)))),"Bom/OK","Outros")))) -> Bom/OK | D14: =IF(TRIM(controle!G14)="","Não informado",UPPER(TRIM(controle!G14))) -> DELL | I14: DEMAIS DEPARTAMENTOS | J14: =ROWS(ListaInventario[Categoria])-SUM(J2:J13) -> 126 | X14: Programação | Y14: 8
A15: =IF(TRIM(controle!A15)="","Não informado",IF(LEFT(UPPER(TRIM(controle!A15)),7)="MONITOR","Monitores",IF(OR(LEFT(UPPER(TRIM(controle!A15)),7)="DESKTOP",UPPER(TRIM(controle!A15))="MICRO",LEFT(UPPER(TRIM(controle!A15)),7)="MONTADO"),"Desktops/Micros",IF(LEFT(UPPER(TRIM(controle!A15)),8)="NOTEBOOK","Notebooks",IF(LEFT(UPPER(TRIM(controle!A15)),10)="IMPRESSORA","Impressoras",IF(LEFT(UPPER(TRIM(controle!A15)),8)="TELEFONE","Telefonia","Outros")))))) -> Desktops/Micros | B15: =IF(TRIM(controle!E15)="","Sem departamento",IF(OR(UPPER(TRIM(controle!E15))="TI",UPPER(TRIM(controle!E15))="T.I"),"T.I",IF(OR(UPPER(TRIM(controle!E15))="TECNICA",UPPER(TRIM(controle!E15))="TÉCNICA"),"TÉCNICA",SUBSTITUTE(UPPER(TRIM(controle!E15)),"SWICHER","SWITCHER")))) -> DEPÓSITO RH | C15: =IF(TRIM(controle!K15)="","Não informado",IF(ISNUMBER(SEARCH("DESCARTE",UPPER(controle!K15))),"Descarte",IF(ISNUMBER(SEARCH("INATIVO",UPPER(controle!K15))),"Inativo",IF(OR(ISNUMBER(SEARCH("BOM",UPPER(controle!K15))),ISNUMBER(SEARCH("OK",UPPER(controle!K15)))),"Bom/OK","Outros")))) -> Bom/OK | D15: =IF(TRIM(controle!G15)="","Não informado",UPPER(TRIM(controle!G15))) -> DELL | X15: DIRETORIA EXECUTIVA | Y15: 6
A16: =IF(TRIM(controle!A16)="","Não informado",IF(LEFT(UPPER(TRIM(controle!A16)),7)="MONITOR","Monitores",IF(OR(LEFT(UPPER(TRIM(controle!A16)),7)="DESKTOP",UPPER(TRIM(controle!A16))="MICRO",LEFT(UPPER(TRIM(controle!A16)),7)="MONTADO"),"Desktops/Micros",IF(LEFT(UPPER(TRIM(controle!A16)),8)="NOTEBOOK","Notebooks",IF(LEFT(UPPER(TRIM(controle!A16)),10)="IMPRESSORA","Impressoras",IF(LEFT(UPPER(TRIM(controle!A16)),8)="TELEFONE","Telefonia","Outros")))))) -> Desktops/Micros | B16: =IF(TRIM(controle!E16)="","Sem departamento",IF(OR(UPPER(TRIM(controle!E16))="TI",UPPER(TRIM(controle!E16))="T.I"),"T.I",IF(OR(UPPER(TRIM(controle!E16))="TECNICA",UPPER(TRIM(controle!E16))="TÉCNICA"),"TÉCNICA",SUBSTITUTE(UPPER(TRIM(controle!E16)),"SWICHER","SWITCHER")))) -> DEPÓSITO RH | C16: =IF(TRIM(controle!K16)="","Não informado",IF(ISNUMBER(SEARCH("DESCARTE",UPPER(controle!K16))),"Descarte",IF(ISNUMBER(SEARCH("INATIVO",UPPER(controle!K16))),"Inativo",IF(OR(ISNUMBER(SEARCH("BOM",UPPER(controle!K16))),ISNUMBER(SEARCH("OK",UPPER(controle!K16)))),"Bom/OK","Outros")))) -> Bom/OK | D16: =IF(TRIM(controle!G16)="","Não informado",UPPER(TRIM(controle!G16))) -> DELL | X16: Frente do swicher | Y16: 5
A17: =IF(TRIM(controle!A17)="","Não informado",IF(LEFT(UPPER(TRIM(controle!A17)),7)="MONITOR","Monitores",IF(OR(LEFT(UPPER(TRIM(controle!A17)),7)="DESKTOP",UPPER(TRIM(controle!A17))="MICRO",LEFT(UPPER(TRIM(controle!A17)),7)="MONTADO"),"Desktops/Micros",IF(LEFT(UPPER(TRIM(controle!A17)),8)="NOTEBOOK","Notebooks",IF(LEFT(UPPER(TRIM(controle!A17)),10)="IMPRESSORA","Impressoras",IF(LEFT(UPPER(TRIM(controle!A17)),8)="TELEFONE","Telefonia","Outros")))))) -> Desktops/Micros | B17: =IF(TRIM(controle!E17)="","Sem departamento",IF(OR(UPPER(TRIM(controle!E17))="TI",UPPER(TRIM(controle!E17))="T.I"),"T.I",IF(OR(UPPER(TRIM(controle!E17))="TECNICA",UPPER(TRIM(controle!E17))="TÉCNICA"),"TÉCNICA",SUBSTITUTE(UPPER(TRIM(controle!E17)),"SWICHER","SWITCHER")))) -> DEPÓSITO RH | C17: =IF(TRIM(controle!K17)="","Não informado",IF(ISNUMBER(SEARCH("DESCARTE",UPPER(controle!K17))),"Descarte",IF(ISNUMBER(SEARCH("INATIVO",UPPER(controle!K17))),"Inativo",IF(OR(ISNUMBER(SEARCH("BOM",UPPER(controle!K17))),ISNUMBER(SEARCH("OK",UPPER(controle!K17)))),"Bom/OK","Outros")))) -> Inativo | D17: =IF(TRIM(controle!G17)="","Não informado",UPPER(TRIM(controle!G17))) -> DELL | X17: Operações | Y17: 5
A18: =IF(TRIM(controle!A18)="","Não informado",IF(LEFT(UPPER(TRIM(controle!A18)),7)="MONITOR","Monitores",IF(OR(LEFT(UPPER(TRIM(controle!A18)),7)="DESKTOP",UPPER(TRIM(controle!A18))="MICRO",LEFT(UPPER(TRIM(controle!A18)),7)="MONTADO"),"Desktops/Micros",IF(LEFT(UPPER(TRIM(controle!A18)),8)="NOTEBOOK","Notebooks",IF(LEFT(UPPER(TRIM(controle!A18)),10)="IMPRESSORA","Impressoras",IF(LEFT(UPPER(TRIM(controle!A18)),8)="TELEFONE","Telefonia","Outros")))))) -> Desktops/Micros | B18: =IF(TRIM(controle!E18)="","Sem departamento",IF(OR(UPPER(TRIM(controle!E18))="TI",UPPER(TRIM(controle!E18))="T.I"),"T.I",IF(OR(UPPER(TRIM(controle!E18))="TECNICA",UPPER(TRIM(controle!E18))="TÉCNICA"),"TÉCNICA",SUBSTITUTE(UPPER(TRIM(controle!E18)),"SWICHER","SWITCHER")))) -> DEPÓSITO RH | C18: =IF(TRIM(controle!K18)="","Não informado",IF(ISNUMBER(SEARCH("DESCARTE",UPPER(controle!K18))),"Descarte",IF(ISNUMBER(SEARCH("INATIVO",UPPER(controle!K18))),"Inativo",IF(OR(ISNUMBER(SEARCH("BOM",UPPER(controle!K18))),ISNUMBER(SEARCH("OK",UPPER(controle!K18)))),"Bom/OK","Outros")))) -> Bom/OK | D18: =IF(TRIM(controle!G18)="","Não informado",UPPER(TRIM(controle!G18))) -> DELL | X18: Master | Y18: 5
A19: =IF(TRIM(controle!A19)="","Não informado",IF(LEFT(UPPER(TRIM(controle!A19)),7)="MONITOR","Monitores",IF(OR(LEFT(UPPER(TRIM(controle!A19)),7)="DESKTOP",UPPER(TRIM(controle!A19))="MICRO",LEFT(UPPER(TRIM(controle!A19)),7)="MONTADO"),"Desktops/Micros",IF(LEFT(UPPER(TRIM(controle!A19)),8)="NOTEBOOK","Notebooks",IF(LEFT(UPPER(TRIM(controle!A19)),10)="IMPRESSORA","Impressoras",IF(LEFT(UPPER(TRIM(controle!A19)),8)="TELEFONE","Telefonia","Outros")))))) -> Desktops/Micros | B19: =IF(TRIM(controle!E19)="","Sem departamento",IF(OR(UPPER(TRIM(controle!E19))="TI",UPPER(TRIM(controle!E19))="T.I"),"T.I",IF(OR(UPPER(TRIM(controle!E19))="TECNICA",UPPER(TRIM(controle!E19))="TÉCNICA"),"TÉCNICA",SUBSTITUTE(UPPER(TRIM(controle!E19)),"SWICHER","SWITCHER")))) -> DEPÓSITO RH | C19: =IF(TRIM(controle!K19)="","Não informado",IF(ISNUMBER(SEARCH("DESCARTE",UPPER(controle!K19))),"Descarte",IF(ISNUMBER(SEARCH("INATIVO",UPPER(controle!K19))),"Inativo",IF(OR(ISNUMBER(SEARCH("BOM",UPPER(controle!K19))),ISNUMBER(SEARCH("OK",UPPER(controle!K19)))),"Bom/OK","Outros")))) -> Bom/OK | D19: =IF(TRIM(controle!G19)="","Não informado",UPPER(TRIM(controle!G19))) -> DELL | X19: Diretoria Administrativa | Y19: 4
A20: =IF(TRIM(controle!A20)="","Não informado",IF(LEFT(UPPER(TRIM(controle!A20)),7)="MONITOR","Monitores",IF(OR(LEFT(UPPER(TRIM(controle!A20)),7)="DESKTOP",UPPER(TRIM(controle!A20))="MICRO",LEFT(UPPER(TRIM(controle!A20)),7)="MONTADO"),"Desktops/Micros",IF(LEFT(UPPER(TRIM(controle!A20)),8)="NOTEBOOK","Notebooks",IF(LEFT(UPPER(TRIM(controle!A20)),10)="IMPRESSORA","Impressoras",IF(LEFT(UPPER(TRIM(controle!A20)),8)="TELEFONE","Telefonia","Outros")))))) -> Desktops/Micros | B20: =IF(TRIM(controle!E20)="","Sem departamento",IF(OR(UPPER(TRIM(controle!E20))="TI",UPPER(TRIM(controle!E20))="T.I"),"T.I",IF(OR(UPPER(TRIM(controle!E20))="TECNICA",UPPER(TRIM(controle!E20))="TÉCNICA"),"TÉCNICA",SUBSTITUTE(UPPER(TRIM(controle!E20)),"SWICHER","SWITCHER")))) -> DEPÓSITO RH | C20: =IF(TRIM(controle!K20)="","Não informado",IF(ISNUMBER(SEARCH("DESCARTE",UPPER(controle!K20))),"Descarte",IF(ISNUMBER(SEARCH("INATIVO",UPPER(controle!K20))),"Inativo",IF(OR(ISNUMBER(SEARCH("BOM",UPPER(controle!K20))),ISNUMBER(SEARCH("OK",UPPER(controle!K20)))),"Bom/OK","Outros")))) -> Bom/OK | D20: =IF(TRIM(controle!G20)="","Não informado",UPPER(TRIM(controle!G20))) -> DELL | X20: Áudio | Y20: 4
A21: =IF(TRIM(controle!A21)="","Não informado",IF(LEFT(UPPER(TRIM(controle!A21)),7)="MONITOR","Monitores",IF(OR(LEFT(UPPER(TRIM(controle!A21)),7)="DESKTOP",UPPER(TRIM(controle!A21))="MICRO",LEFT(UPPER(TRIM(controle!A21)),7)="MONTADO"),"Desktops/Micros",IF(LEFT(UPPER(TRIM(controle!A21)),8)="NOTEBOOK","Notebooks",IF(LEFT(UPPER(TRIM(controle!A21)),10)="IMPRESSORA","Impressoras",IF(LEFT(UPPER(TRIM(controle!A21)),8)="TELEFONE","Telefonia","Outros")))))) -> Desktops/Micros | B21: =IF(TRIM(controle!E21)="","Sem departamento",IF(OR(UPPER(TRIM(controle!E21))="TI",UPPER(TRIM(controle!E21))="T.I"),"T.I",IF(OR(UPPER(TRIM(controle!E21))="TECNICA",UPPER(TRIM(controle!E21))="TÉCNICA"),"TÉCNICA",SUBSTITUTE(UPPER(TRIM(controle!E21)),"SWICHER","SWITCHER")))) -> DEPÓSITO RH | C21: =IF(TRIM(controle!K21)="","Não informado",IF(ISNUMBER(SEARCH("DESCARTE",UPPER(controle!K21))),"Descarte",IF(ISNUMBER(SEARCH("INATIVO",UPPER(controle!K21))),"Inativo",IF(OR(ISNUMBER(SEARCH("BOM",UPPER(controle!K21))),ISNUMBER(SEARCH("OK",UPPER(controle!K21)))),"Bom/OK","Outros")))) -> Bom/OK | D21: =IF(TRIM(controle!G21)="","Não informado",UPPER(TRIM(controle!G21))) -> DELL | X21: Controladoria | Y21: 4
A22: =IF(TRIM(controle!A22)="","Não informado",IF(LEFT(UPPER(TRIM(controle!A22)),7)="MONITOR","Monitores",IF(OR(LEFT(UPPER(TRIM(controle!A22)),7)="DESKTOP",UPPER(TRIM(controle!A22))="MICRO",LEFT(UPPER(TRIM(controle!A22)),7)="MONTADO"),"Desktops/Micros",IF(LEFT(UPPER(TRIM(controle!A22)),8)="NOTEBOOK","Notebooks",IF(LEFT(UPPER(TRIM(controle!A22)),10)="IMPRESSORA","Impressoras",IF(LEFT(UPPER(TRIM(controle!A22)),8)="TELEFONE","Telefonia","Outros")))))) -> Desktops/Micros | B22: =IF(TRIM(controle!E22)="","Sem departamento",IF(OR(UPPER(TRIM(controle!E22))="TI",UPPER(TRIM(controle!E22))="T.I"),"T.I",IF(OR(UPPER(TRIM(controle!E22))="TECNICA",UPPER(TRIM(controle!E22))="TÉCNICA"),"TÉCNICA",SUBSTITUTE(UPPER(TRIM(controle!E22)),"SWICHER","SWITCHER")))) -> DEPÓSITO RH | C22: =IF(TRIM(controle!K22)="","Não informado",IF(ISNUMBER(SEARCH("DESCARTE",UPPER(controle!K22))),"Descarte",IF(ISNUMBER(SEARCH("INATIVO",UPPER(controle!K22))),"Inativo",IF(OR(ISNUMBER(SEARCH("BOM",UPPER(controle!K22))),ISNUMBER(SEARCH("OK",UPPER(controle!K22)))),"Bom/OK","Outros")))) -> Bom/OK | D22: =IF(TRIM(controle!G22)="","Não informado",UPPER(TRIM(controle!G22))) -> DELL | X22: Dallet | Y22: 4
A23: =IF(TRIM(controle!A23)="","Não informado",IF(LEFT(UPPER(TRIM(controle!A23)),7)="MONITOR","Monitores",IF(OR(LEFT(UPPER(TRIM(controle!A23)),7)="DESKTOP",UPPER(TRIM(controle!A23))="MICRO",LEFT(UPPER(TRIM(controle!A23)),7)="MONTADO"),"Desktops/Micros",IF(LEFT(UPPER(TRIM(controle!A23)),8)="NOTEBOOK","Notebooks",IF(LEFT(UPPER(TRIM(controle!A23)),10)="IMPRESSORA","Impressoras",IF(LEFT(UPPER(TRIM(controle!A23)),8)="TELEFONE","Telefonia","Outros")))))) -> Desktops/Micros | B23: =IF(TRIM(controle!E23)="","Sem departamento",IF(OR(UPPER(TRIM(controle!E23))="TI",UPPER(TRIM(controle!E23))="T.I"),"T.I",IF(OR(UPPER(TRIM(controle!E23))="TECNICA",UPPER(TRIM(controle!E23))="TÉCNICA"),"TÉCNICA",SUBSTITUTE(UPPER(TRIM(controle!E23)),"SWICHER","SWITCHER")))) -> DEPÓSITO RH | C23: =IF(TRIM(controle!K23)="","Não informado",IF(ISNUMBER(SEARCH("DESCARTE",UPPER(controle!K23))),"Descarte",IF(ISNUMBER(SEARCH("INATIVO",UPPER(controle!K23))),"Inativo",IF(OR(ISNUMBER(SEARCH("BOM",UPPER(controle!K23))),ISNUMBER(SEARCH("OK",UPPER(controle!K23)))),"Bom/OK","Outros")))) -> Bom/OK | D23: =IF(TRIM(controle!G23)="","Não informado",UPPER(TRIM(controle!G23))) -> DELL | X23: Recepção | Y23: 4
A24: =IF(TRIM(controle!A24)="","Não informado",IF(LEFT(UPPER(TRIM(controle!A24)),7)="MONITOR","Monitores",IF(OR(LEFT(UPPER(TRIM(controle!A24)),7)="DESKTOP",UPPER(TRIM(controle!A24))="MICRO",LEFT(UPPER(TRIM(controle!A24)),7)="MONTADO"),"Desktops/Micros",IF(LEFT(UPPER(TRIM(controle!A24)),8)="NOTEBOOK","Notebooks",IF(LEFT(UPPER(TRIM(controle!A24)),10)="IMPRESSORA","Impressoras",IF(LEFT(UPPER(TRIM(controle!A24)),8)="TELEFONE","Telefonia","Outros")))))) -> Desktops/Micros | B24: =IF(TRIM(controle!E24)="","Sem departamento",IF(OR(UPPER(TRIM(controle!E24))="TI",UPPER(TRIM(controle!E24))="T.I"),"T.I",IF(OR(UPPER(TRIM(controle!E24))="TECNICA",UPPER(TRIM(controle!E24))="TÉCNICA"),"TÉCNICA",SUBSTITUTE(UPPER(TRIM(controle!E24)),"SWICHER","SWITCHER")))) -> DEPÓSITO RH | C24: =IF(TRIM(controle!K24)="","Não informado",IF(ISNUMBER(SEARCH("DESCARTE",UPPER(controle!K24))),"Descarte",IF(ISNUMBER(SEARCH("INATIVO",UPPER(controle!K24))),"Inativo",IF(OR(ISNUMBER(SEARCH("BOM",UPPER(controle!K24))),ISNUMBER(SEARCH("OK",UPPER(controle!K24)))),"Bom/OK","Outros")))) -> Bom/OK | D24: =IF(TRIM(controle!G24)="","Não informado",UPPER(TRIM(controle!G24))) -> DELL | X24: Diretoria Comercial | Y24: 4
A25: =IF(TRIM(controle!A25)="","Não informado",IF(LEFT(UPPER(TRIM(controle!A25)),7)="MONITOR","Monitores",IF(OR(LEFT(UPPER(TRIM(controle!A25)),7)="DESKTOP",UPPER(TRIM(controle!A25))="MICRO",LEFT(UPPER(TRIM(controle!A25)),7)="MONTADO"),"Desktops/Micros",IF(LEFT(UPPER(TRIM(controle!A25)),8)="NOTEBOOK","Notebooks",IF(LEFT(UPPER(TRIM(controle!A25)),10)="IMPRESSORA","Impressoras",IF(LEFT(UPPER(TRIM(controle!A25)),8)="TELEFONE","Telefonia","Outros")))))) -> Desktops/Micros | B25: =IF(TRIM(controle!E25)="","Sem departamento",IF(OR(UPPER(TRIM(controle!E25))="TI",UPPER(TRIM(controle!E25))="T.I"),"T.I",IF(OR(UPPER(TRIM(controle!E25))="TECNICA",UPPER(TRIM(controle!E25))="TÉCNICA"),"TÉCNICA",SUBSTITUTE(UPPER(TRIM(controle!E25)),"SWICHER","SWITCHER")))) -> DEPÓSITO RH | C25: =IF(TRIM(controle!K25)="","Não informado",IF(ISNUMBER(SEARCH("DESCARTE",UPPER(controle!K25))),"Descarte",IF(ISNUMBER(SEARCH("INATIVO",UPPER(controle!K25))),"Inativo",IF(OR(ISNUMBER(SEARCH("BOM",UPPER(controle!K25))),ISNUMBER(SEARCH("OK",UPPER(controle!K25)))),"Bom/OK","Outros")))) -> Bom/OK | D25: =IF(TRIM(controle!G25)="","Não informado",UPPER(TRIM(controle!G25))) -> DELL | X25: ILHA 1 | Y25: 3
A26: =IF(TRIM(controle!A26)="","Não informado",IF(LEFT(UPPER(TRIM(controle!A26)),7)="MONITOR","Monitores",IF(OR(LEFT(UPPER(TRIM(controle!A26)),7)="DESKTOP",UPPER(TRIM(controle!A26))="MICRO",LEFT(UPPER(TRIM(controle!A26)),7)="MONTADO"),"Desktops/Micros",IF(LEFT(UPPER(TRIM(controle!A26)),8)="NOTEBOOK","Notebooks",IF(LEFT(UPPER(TRIM(controle!A26)),10)="IMPRESSORA","Impressoras",IF(LEFT(UPPER(TRIM(controle!A26)),8)="TELEFONE","Telefonia","Outros")))))) -> Desktops/Micros | B26: =IF(TRIM(controle!E26)="","Sem departamento",IF(OR(UPPER(TRIM(controle!E26))="TI",UPPER(TRIM(controle!E26))="T.I"),"T.I",IF(OR(UPPER(TRIM(controle!E26))="TECNICA",UPPER(TRIM(controle!E26))="TÉCNICA"),"TÉCNICA",SUBSTITUTE(UPPER(TRIM(controle!E26)),"SWICHER","SWITCHER")))) -> DEPÓSITO RH | C26: =IF(TRIM(controle!K26)="","Não informado",IF(ISNUMBER(SEARCH("DESCARTE",UPPER(controle!K26))),"Descarte",IF(ISNUMBER(SEARCH("INATIVO",UPPER(controle!K26))),"Inativo",IF(OR(ISNUMBER(SEARCH("BOM",UPPER(controle!K26))),ISNUMBER(SEARCH("OK",UPPER(controle!K26)))),"Bom/OK","Outros")))) -> Bom/OK | D26: =IF(TRIM(controle!G26)="","Não informado",UPPER(TRIM(controle!G26))) -> DELL | X26: ILHA 2 | Y26: 3
... A57: =IF(TRIM(controle!A57)="","Não informado",IF(LEFT(UPPER(TRIM(controle!A57)),7)="MONITOR","Monitores",IF(OR(LEFT(UPPER(TRIM(controle!A57)),7)="DESKTOP",UPPER(TRIM(controle!A57))="MICRO",LEFT(UPPER(TRIM(controle!A57)),7)="MONTADO"),"Desktops/Micros",IF(LEFT(UPPER(TRIM(controle!A57)),8)="NOTEBOOK","Notebooks",IF(LEFT(UPPER(TRIM(controle!A57)),10)="IMPRESSORA","Impressoras",IF(LEFT(UPPER(TRIM(controle!A57)),8)="TELEFONE","Telefonia","Outros")))))) -> Desktops/Micros | B57: =IF(TRIM(controle!E57)="","Sem departamento",IF(OR(UPPER(TRIM(controle!E57))="TI",UPPER(TRIM(controle!E57))="T.I"),"T.I",IF(OR(UPPER(TRIM(controle!E57))="TECNICA",UPPER(TRIM(controle!E57))="TÉCNICA"),"TÉCNICA",SUBSTITUTE(UPPER(TRIM(controle!E57)),"SWICHER","SWITCHER")))) -> DEPÓSITO RH | C57: =IF(TRIM(controle!K57)="","Não informado",IF(ISNUMBER(SEARCH("DESCARTE",UPPER(controle!K57))),"Descarte",IF(ISNUMBER(SEARCH("INATIVO",UPPER(controle!K57))),"Inativo",IF(OR(ISNUMBER(SEARCH("BOM",UPPER(controle!K57))),ISNUMBER(SEARCH("OK",UPPER(controle!K57)))),"Bom/OK","Outros")))) -> Bom/OK | D57: =IF(TRIM(controle!G57)="","Não informado",UPPER(TRIM(controle!G57))) -> DELL | X57: Secretaria de Diretoria | Y57: 1
A58: =IF(TRIM(controle!A58)="","Não informado",IF(LEFT(UPPER(TRIM(controle!A58)),7)="MONITOR","Monitores",IF(OR(LEFT(UPPER(TRIM(controle!A58)),7)="DESKTOP",UPPER(TRIM(controle!A58))="MICRO",LEFT(UPPER(TRIM(controle!A58)),7)="MONTADO"),"Desktops/Micros",IF(LEFT(UPPER(TRIM(controle!A58)),8)="NOTEBOOK","Notebooks",IF(LEFT(UPPER(TRIM(controle!A58)),10)="IMPRESSORA","Impressoras",IF(LEFT(UPPER(TRIM(controle!A58)),8)="TELEFONE","Telefonia","Outros")))))) -> Desktops/Micros | B58: =IF(TRIM(controle!E58)="","Sem departamento",IF(OR(UPPER(TRIM(controle!E58))="TI",UPPER(TRIM(controle!E58))="T.I"),"T.I",IF(OR(UPPER(TRIM(controle!E58))="TECNICA",UPPER(TRIM(controle!E58))="TÉCNICA"),"TÉCNICA",SUBSTITUTE(UPPER(TRIM(controle!E58)),"SWICHER","SWITCHER")))) -> DEPÓSITO RH | C58: =IF(TRIM(controle!K58)="","Não informado",IF(ISNUMBER(SEARCH("DESCARTE",UPPER(controle!K58))),"Descarte",IF(ISNUMBER(SEARCH("INATIVO",UPPER(controle!K58))),"Inativo",IF(OR(ISNUMBER(SEARCH("BOM",UPPER(controle!K58))),ISNUMBER(SEARCH("OK",UPPER(controle!K58)))),"Bom/OK","Outros")))) -> Bom/OK | D58: =IF(TRIM(controle!G58)="","Não informado",UPPER(TRIM(controle!G58))) -> DELL
A59: =IF(TRIM(controle!A59)="","Não informado",IF(LEFT(UPPER(TRIM(controle!A59)),7)="MONITOR","Monitores",IF(OR(LEFT(UPPER(TRIM(controle!A59)),7)="DESKTOP",UPPER(TRIM(controle!A59))="MICRO",LEFT(UPPER(TRIM(controle!A59)),7)="MONTADO"),"Desktops/Micros",IF(LEFT(UPPER(TRIM(controle!A59)),8)="NOTEBOOK","Notebooks",IF(LEFT(UPPER(TRIM(controle!A59)),10)="IMPRESSORA","Impressoras",IF(LEFT(UPPER(TRIM(controle!A59)),8)="TELEFONE","Telefonia","Outros")))))) -> Desktops/Micros | B59: =IF(TRIM(controle!E59)="","Sem departamento",IF(OR(UPPER(TRIM(controle!E59))="TI",UPPER(TRIM(controle!E59))="T.I"),"T.I",IF(OR(UPPER(TRIM(controle!E59))="TECNICA",UPPER(TRIM(controle!E59))="TÉCNICA"),"TÉCNICA",SUBSTITUTE(UPPER(TRIM(controle!E59)),"SWICHER","SWITCHER")))) -> DEPÓSITO RH | C59: =IF(TRIM(controle!K59)="","Não informado",IF(ISNUMBER(SEARCH("DESCARTE",UPPER(controle!K59))),"Descarte",IF(ISNUMBER(SEARCH("INATIVO",UPPER(controle!K59))),"Inativo",IF(OR(ISNUMBER(SEARCH("BOM",UPPER(controle!K59))),ISNUMBER(SEARCH("OK",UPPER(controle!K59)))),"Bom/OK","Outros")))) -> Bom/OK | D59: =IF(TRIM(controle!G59)="","Não informado",UPPER(TRIM(controle!G59))) -> DELL
A60: =IF(TRIM(controle!A60)="","Não informado",IF(LEFT(UPPER(TRIM(controle!A60)),7)="MONITOR","Monitores",IF(OR(LEFT(UPPER(TRIM(controle!A60)),7)="DESKTOP",UPPER(TRIM(controle!A60))="MICRO",LEFT(UPPER(TRIM(controle!A60)),7)="MONTADO"),"Desktops/Micros",IF(LEFT(UPPER(TRIM(controle!A60)),8)="NOTEBOOK","Notebooks",IF(LEFT(UPPER(TRIM(controle!A60)),10)="IMPRESSORA","Impressoras",IF(LEFT(UPPER(TRIM(controle!A60)),8)="TELEFONE","Telefonia","Outros")))))) -> Desktops/Micros | B60: =IF(TRIM(controle!E60)="","Sem departamento",IF(OR(UPPER(TRIM(controle!E60))="TI",UPPER(TRIM(controle!E60))="T.I"),"T.I",IF(OR(UPPER(TRIM(controle!E60))="TECNICA",UPPER(TRIM(controle!E60))="TÉCNICA"),"TÉCNICA",SUBSTITUTE(UPPER(TRIM(controle!E60)),"SWICHER","SWITCHER")))) -> DEPÓSITO RH | C60: =IF(TRIM(controle!K60)="","Não informado",IF(ISNUMBER(SEARCH("DESCARTE",UPPER(controle!K60))),"Descarte",IF(ISNUMBER(SEARCH("INATIVO",UPPER(controle!K60))),"Inativo",IF(OR(ISNUMBER(SEARCH("BOM",UPPER(controle!K60))),ISNUMBER(SEARCH("OK",UPPER(controle!K60)))),"Bom/OK","Outros")))) -> Bom/OK | D60: =IF(TRIM(controle!G60)="","Não informado",UPPER(TRIM(controle!G60))) -> DELL
A61: =IF(TRIM(controle!A61)="","Não informado",IF(LEFT(UPPER(TRIM(controle!A61)),7)="MONITOR","Monitores",IF(OR(LEFT(UPPER(TRIM(controle!A61)),7)="DESKTOP",UPPER(TRIM(controle!A61))="MICRO",LEFT(UPPER(TRIM(controle!A61)),7)="MONTADO"),"Desktops/Micros",IF(LEFT(UPPER(TRIM(controle!A61)),8)="NOTEBOOK","Notebooks",IF(LEFT(UPPER(TRIM(controle!A61)),10)="IMPRESSORA","Impressoras",IF(LEFT(UPPER(TRIM(controle!A61)),8)="TELEFONE","Telefonia","Outros")))))) -> Desktops/Micros | B61: =IF(TRIM(controle!E61)="","Sem departamento",IF(OR(UPPER(TRIM(controle!E61))="TI",UPPER(TRIM(controle!E61))="T.I"),"T.I",IF(OR(UPPER(TRIM(controle!E61))="TECNICA",UPPER(TRIM(controle!E61))="TÉCNICA"),"TÉCNICA",SUBSTITUTE(UPPER(TRIM(controle!E61)),"SWICHER","SWITCHER")))) -> DEPÓSITO RH | C61: =IF(TRIM(controle!K61)="","Não informado",IF(ISNUMBER(SEARCH("DESCARTE",UPPER(controle!K61))),"Descarte",IF(ISNUMBER(SEARCH("INATIVO",UPPER(controle!K61))),"Inativo",IF(OR(ISNUMBER(SEARCH("BOM",UPPER(controle!K61))),ISNUMBER(SEARCH("OK",UPPER(controle!K61)))),"Bom/OK","Outros")))) -> Bom/OK | D61: =IF(TRIM(controle!G61)="","Não informado",UPPER(TRIM(controle!G61))) -> DELL
A62: =IF(TRIM(controle!A62)="","Não informado",IF(LEFT(UPPER(TRIM(controle!A62)),7)="MONITOR","Monitores",IF(OR(LEFT(UPPER(TRIM(controle!A62)),7)="DESKTOP",UPPER(TRIM(controle!A62))="MICRO",LEFT(UPPER(TRIM(controle!A62)),7)="MONTADO"),"Desktops/Micros",IF(LEFT(UPPER(TRIM(controle!A62)),8)="NOTEBOOK","Notebooks",IF(LEFT(UPPER(TRIM(controle!A62)),10)="IMPRESSORA","Impressoras",IF(LEFT(UPPER(TRIM(controle!A62)),8)="TELEFONE","Telefonia","Outros")))))) -> Desktops/Micros | B62: =IF(TRIM(controle!E62)="","Sem departamento",IF(OR(UPPER(TRIM(controle!E62))="TI",UPPER(TRIM(controle!E62))="T.I"),"T.I",IF(OR(UPPER(TRIM(controle!E62))="TECNICA",UPPER(TRIM(controle!E62))="TÉCNICA"),"TÉCNICA",SUBSTITUTE(UPPER(TRIM(controle!E62)),"SWICHER","SWITCHER")))) -> DEPÓSITO RH | C62: =IF(TRIM(controle!K62)="","Não informado",IF(ISNUMBER(SEARCH("DESCARTE",UPPER(controle!K62))),"Descarte",IF(ISNUMBER(SEARCH("INATIVO",UPPER(controle!K62))),"Inativo",IF(OR(ISNUMBER(SEARCH("BOM",UPPER(controle!K62))),ISNUMBER(SEARCH("OK",UPPER(controle!K62)))),"Bom/OK","Outros")))) -> Bom/OK | D62: =IF(TRIM(controle!G62)="","Não informado",UPPER(TRIM(controle!G62))) -> DELL
A63: =IF(TRIM(controle!A63)="","Não informado",IF(LEFT(UPPER(TRIM(controle!A63)),7)="MONITOR","Monitores",IF(OR(LEFT(UPPER(TRIM(controle!A63)),7)="DESKTOP",UPPER(TRIM(controle!A63))="MICRO",LEFT(UPPER(TRIM(controle!A63)),7)="MONTADO"),"Desktops/Micros",IF(LEFT(UPPER(TRIM(controle!A63)),8)="NOTEBOOK","Notebooks",IF(LEFT(UPPER(TRIM(controle!A63)),10)="IMPRESSORA","Impressoras",IF(LEFT(UPPER(TRIM(controle!A63)),8)="TELEFONE","Telefonia","Outros")))))) -> Desktops/Micros | B63: =IF(TRIM(controle!E63)="","Sem departamento",IF(OR(UPPER(TRIM(controle!E63))="TI",UPPER(TRIM(controle!E63))="T.I"),"T.I",IF(OR(UPPER(TRIM(controle!E63))="TECNICA",UPPER(TRIM(controle!E63))="TÉCNICA"),"TÉCNICA",SUBSTITUTE(UPPER(TRIM(controle!E63)),"SWICHER","SWITCHER")))) -> DEPÓSITO RH | C63: =IF(TRIM(controle!K63)="","Não informado",IF(ISNUMBER(SEARCH("DESCARTE",UPPER(controle!K63))),"Descarte",IF(ISNUMBER(SEARCH("INATIVO",UPPER(controle!K63))),"Inativo",IF(OR(ISNUMBER(SEARCH("BOM",UPPER(controle!K63))),ISNUMBER(SEARCH("OK",UPPER(controle!K63)))),"Bom/OK","Outros")))) -> Bom/OK | D63: =IF(TRIM(controle!G63)="","Não informado",UPPER(TRIM(controle!G63))) -> DELL
A64: =IF(TRIM(controle!A64)="","Não informado",IF(LEFT(UPPER(TRIM(controle!A64)),7)="MONITOR","Monitores",IF(OR(LEFT(UPPER(TRIM(controle!A64)),7)="DESKTOP",UPPER(TRIM(controle!A64))="MICRO",LEFT(UPPER(TRIM(controle!A64)),7)="MONTADO"),"Desktops/Micros",IF(LEFT(UPPER(TRIM(controle!A64)),8)="NOTEBOOK","Notebooks",IF(LEFT(UPPER(TRIM(controle!A64)),10)="IMPRESSORA","Impressoras",IF(LEFT(UPPER(TRIM(controle!A64)),8)="TELEFONE","Telefonia","Outros")))))) -> Desktops/Micros | B64: =IF(TRIM(controle!E64)="","Sem departamento",IF(OR(UPPER(TRIM(controle!E64))="TI",UPPER(TRIM(controle!E64))="T.I"),"T.I",IF(OR(UPPER(TRIM(controle!E64))="TECNICA",UPPER(TRIM(controle!E64))="TÉCNICA"),"TÉCNICA",SUBSTITUTE(UPPER(TRIM(controle!E64)),"SWICHER","SWITCHER")))) -> DEPÓSITO RH | C64: =IF(TRIM(controle!K64)="","Não informado",IF(ISNUMBER(SEARCH("DESCARTE",UPPER(controle!K64))),"Descarte",IF(ISNUMBER(SEARCH("INATIVO",UPPER(controle!K64))),"Inativo",IF(OR(ISNUMBER(SEARCH("BOM",UPPER(controle!K64))),ISNUMBER(SEARCH("OK",UPPER(controle!K64)))),"Bom/OK","Outros")))) -> Bom/OK | D64: =IF(TRIM(controle!G64)="","Não informado",UPPER(TRIM(controle!G64))) -> DELL
A65: =IF(TRIM(controle!A65)="","Não informado",IF(LEFT(UPPER(TRIM(controle!A65)),7)="MONITOR","Monitores",IF(OR(LEFT(UPPER(TRIM(controle!A65)),7)="DESKTOP",UPPER(TRIM(controle!A65))="MICRO",LEFT(UPPER(TRIM(controle!A65)),7)="MONTADO"),"Desktops/Micros",IF(LEFT(UPPER(TRIM(controle!A65)),8)="NOTEBOOK","Notebooks",IF(LEFT(UPPER(TRIM(controle!A65)),10)="IMPRESSORA","Impressoras",IF(LEFT(UPPER(TRIM(controle!A65)),8)="TELEFONE","Telefonia","Outros")))))) -> Desktops/Micros | B65: =IF(TRIM(controle!E65)="","Sem departamento",IF(OR(UPPER(TRIM(controle!E65))="TI",UPPER(TRIM(controle!E65))="T.I"),"T.I",IF(OR(UPPER(TRIM(controle!E65))="TECNICA",UPPER(TRIM(controle!E65))="TÉCNICA"),"TÉCNICA",SUBSTITUTE(UPPER(TRIM(controle!E65)),"SWICHER","SWITCHER")))) -> DEPÓSITO RH | C65: =IF(TRIM(controle!K65)="","Não informado",IF(ISNUMBER(SEARCH("DESCARTE",UPPER(controle!K65))),"Descarte",IF(ISNUMBER(SEARCH("INATIVO",UPPER(controle!K65))),"Inativo",IF(OR(ISNUMBER(SEARCH("BOM",UPPER(controle!K65))),ISNUMBER(SEARCH("OK",UPPER(controle!K65)))),"Bom/OK","Outros")))) -> Bom/OK | D65: =IF(TRIM(controle!G65)="","Não informado",UPPER(TRIM(controle!G65))) -> DELL
A66: =IF(TRIM(controle!A66)="","Não informado",IF(LEFT(UPPER(TRIM(controle!A66)),7)="MONITOR","Monitores",IF(OR(LEFT(UPPER(TRIM(controle!A66)),7)="DESKTOP",UPPER(TRIM(controle!A66))="MICRO",LEFT(UPPER(TRIM(controle!A66)),7)="MONTADO"),"Desktops/Micros",IF(LEFT(UPPER(TRIM(controle!A66)),8)="NOTEBOOK","Notebooks",IF(LEFT(UPPER(TRIM(controle!A66)),10)="IMPRESSORA","Impressoras",IF(LEFT(UPPER(TRIM(controle!A66)),8)="TELEFONE","Telefonia","Outros")))))) -> Desktops/Micros | B66: =IF(TRIM(controle!E66)="","Sem departamento",IF(OR(UPPER(TRIM(controle!E66))="TI",UPPER(TRIM(controle!E66))="T.I"),"T.I",IF(OR(UPPER(TRIM(controle!E66))="TECNICA",UPPER(TRIM(controle!E66))="TÉCNICA"),"TÉCNICA",SUBSTITUTE(UPPER(TRIM(controle!E66)),"SWICHER","SWITCHER")))) -> DEPÓSITO RH | C66: =IF(TRIM(controle!K66)="","Não informado",IF(ISNUMBER(SEARCH("DESCARTE",UPPER(controle!K66))),"Descarte",IF(ISNUMBER(SEARCH("INATIVO",UPPER(controle!K66))),"Inativo",IF(OR(ISNUMBER(SEARCH("BOM",UPPER(controle!K66))),ISNUMBER(SEARCH("OK",UPPER(controle!K66)))),"Bom/OK","Outros")))) -> Bom/OK | D66: =IF(TRIM(controle!G66)="","Não informado",UPPER(TRIM(controle!G66))) -> DELL
A67: =IF(TRIM(controle!A67)="","Não informado",IF(LEFT(UPPER(TRIM(controle!A67)),7)="MONITOR","Monitores",IF(OR(LEFT(UPPER(TRIM(controle!A67)),7)="DESKTOP",UPPER(TRIM(controle!A67))="MICRO",LEFT(UPPER(TRIM(controle!A67)),7)="MONTADO"),"Desktops/Micros",IF(LEFT(UPPER(TRIM(controle!A67)),8)="NOTEBOOK","Notebooks",IF(LEFT(UPPER(TRIM(controle!A67)),10)="IMPRESSORA","Impressoras",IF(LEFT(UPPER(TRIM(controle!A67)),8)="TELEFONE","Telefonia","Outros")))))) -> Desktops/Micros | B67: =IF(TRIM(controle!E67)="","Sem departamento",IF(OR(UPPER(TRIM(controle!E67))="TI",UPPER(TRIM(controle!E67))="T.I"),"T.I",IF(OR(UPPER(TRIM(controle!E67))="TECNICA",UPPER(TRIM(controle!E67))="TÉCNICA"),"TÉCNICA",SUBSTITUTE(UPPER(TRIM(controle!E67)),"SWICHER","SWITCHER")))) -> DEPÓSITO RH | C67: =IF(TRIM(controle!K67)="","Não informado",IF(ISNUMBER(SEARCH("DESCARTE",UPPER(controle!K67))),"Descarte",IF(ISNUMBER(SEARCH("INATIVO",UPPER(controle!K67))),"Inativo",IF(OR(ISNUMBER(SEARCH("BOM",UPPER(controle!K67))),ISNUMBER(SEARCH("OK",UPPER(controle!K67)))),"Bom/OK","Outros")))) -> Bom/OK | D67: =IF(TRIM(controle!G67)="","Não informado",UPPER(TRIM(controle!G67))) -> DELL
A68: =IF(TRIM(controle!A68)="","Não informado",IF(LEFT(UPPER(TRIM(controle!A68)),7)="MONITOR","Monitores",IF(OR(LEFT(UPPER(TRIM(controle!A68)),7)="DESKTOP",UPPER(TRIM(controle!A68))="MICRO",LEFT(UPPER(TRIM(controle!A68)),7)="MONTADO"),"Desktops/Micros",IF(LEFT(UPPER(TRIM(controle!A68)),8)="NOTEBOOK","Notebooks",IF(LEFT(UPPER(TRIM(controle!A68)),10)="IMPRESSORA","Impressoras",IF(LEFT(UPPER(TRIM(controle!A68)),8)="TELEFONE","Telefonia","Outros")))))) -> Desktops/Micros | B68: =IF(TRIM(controle!E68)="","Sem departamento",IF(OR(UPPER(TRIM(controle!E68))="TI",UPPER(TRIM(controle!E68))="T.I"),"T.I",IF(OR(UPPER(TRIM(controle!E68))="TECNICA",UPPER(TRIM(controle!E68))="TÉCNICA"),"TÉCNICA",SUBSTITUTE(UPPER(TRIM(controle!E68)),"SWICHER","SWITCHER")))) -> DEPÓSITO RH | C68: =IF(TRIM(controle!K68)="","Não informado",IF(ISNUMBER(SEARCH("DESCARTE",UPPER(controle!K68))),"Descarte",IF(ISNUMBER(SEARCH("INATIVO",UPPER(controle!K68))),"Inativo",IF(OR(ISNUMBER(SEARCH("BOM",UPPER(controle!K68))),ISNUMBER(SEARCH("OK",UPPER(controle!K68)))),"Bom/OK","Outros")))) -> Bom/OK | D68: =IF(TRIM(controle!G68)="","Não informado",UPPER(TRIM(controle!G68))) -> DELL
A69: =IF(TRIM(controle!A69)="","Não informado",IF(LEFT(UPPER(TRIM(controle!A69)),7)="MONITOR","Monitores",IF(OR(LEFT(UPPER(TRIM(controle!A69)),7)="DESKTOP",UPPER(TRIM(controle!A69))="MICRO",LEFT(UPPER(TRIM(controle!A69)),7)="MONTADO"),"Desktops/Micros",IF(LEFT(UPPER(TRIM(controle!A69)),8)="NOTEBOOK","Notebooks",IF(LEFT(UPPER(TRIM(controle!A69)),10)="IMPRESSORA","Impressoras",IF(LEFT(UPPER(TRIM(controle!A69)),8)="TELEFONE","Telefonia","Outros")))))) -> Desktops/Micros | B69: =IF(TRIM(controle!E69)="","Sem departamento",IF(OR(UPPER(TRIM(controle!E69))="TI",UPPER(TRIM(controle!E69))="T.I"),"T.I",IF(OR(UPPER(TRIM(controle!E69))="TECNICA",UPPER(TRIM(controle!E69))="TÉCNICA"),"TÉCNICA",SUBSTITUTE(UPPER(TRIM(controle!E69)),"SWICHER","SWITCHER")))) -> DEPÓSITO RH | C69: =IF(TRIM(controle!K69)="","Não informado",IF(ISNUMBER(SEARCH("DESCARTE",UPPER(controle!K69))),"Descarte",IF(ISNUMBER(SEARCH("INATIVO",UPPER(controle!K69))),"Inativo",IF(OR(ISNUMBER(SEARCH("BOM",UPPER(controle!K69))),ISNUMBER(SEARCH("OK",UPPER(controle!K69)))),"Bom/OK","Outros")))) -> Bom/OK | D69: =IF(TRIM(controle!G69)="","Não informado",UPPER(TRIM(controle!G69))) -> DELL
... A220: =IF(TRIM(controle!A220)="","Não informado",IF(LEFT(UPPER(TRIM(controle!A220)),7)="MONITOR","Monitores",IF(OR(LEFT(UPPER(TRIM(controle!A220)),7)="DESKTOP",UPPER(TRIM(controle!A220))="MICRO",LEFT(UPPER(TRIM(controle!A220)),7)="MONTADO"),"Desktops/Micros",IF(LEFT(UPPER(TRIM(controle!A220)),8)="NOTEBOOK","Notebooks",IF(LEFT(UPPER(TRIM(controle!A220)),10)="IMPRESSORA","Impressoras",IF(LEFT(UPPER(TRIM(controle!A220)),8)="TELEFONE","Telefonia","Outros")))))) -> Monitores | B220: =IF(TRIM(controle!E220)="","Sem departamento",IF(OR(UPPER(TRIM(controle!E220))="TI",UPPER(TRIM(controle!E220))="T.I"),"T.I",IF(OR(UPPER(TRIM(controle!E220))="TECNICA",UPPER(TRIM(controle!E220))="TÉCNICA"),"TÉCNICA",SUBSTITUTE(UPPER(TRIM(controle!E220)),"SWICHER","SWITCHER")))) -> DEPÓSITO RH | C220: =IF(TRIM(controle!K220)="","Não informado",IF(ISNUMBER(SEARCH("DESCARTE",UPPER(controle!K220))),"Descarte",IF(ISNUMBER(SEARCH("INATIVO",UPPER(controle!K220))),"Inativo",IF(OR(ISNUMBER(SEARCH("BOM",UPPER(controle!K220))),ISNUMBER(SEARCH("OK",UPPER(controle!K220)))),"Bom/OK","Outros")))) -> Descarte | D220: =IF(TRIM(controle!G220)="","Não informado",UPPER(TRIM(controle!G220))) -> DELL
A221: =IF(TRIM(controle!A221)="","Não informado",IF(LEFT(UPPER(TRIM(controle!A221)),7)="MONITOR","Monitores",IF(OR(LEFT(UPPER(TRIM(controle!A221)),7)="DESKTOP",UPPER(TRIM(controle!A221))="MICRO",LEFT(UPPER(TRIM(controle!A221)),7)="MONTADO"),"Desktops/Micros",IF(LEFT(UPPER(TRIM(controle!A221)),8)="NOTEBOOK","Notebooks",IF(LEFT(UPPER(TRIM(controle!A221)),10)="IMPRESSORA","Impressoras",IF(LEFT(UPPER(TRIM(controle!A221)),8)="TELEFONE","Telefonia","Outros")))))) -> Monitores | B221: =IF(TRIM(controle!E221)="","Sem departamento",IF(OR(UPPER(TRIM(controle!E221))="TI",UPPER(TRIM(controle!E221))="T.I"),"T.I",IF(OR(UPPER(TRIM(controle!E221))="TECNICA",UPPER(TRIM(controle!E221))="TÉCNICA"),"TÉCNICA",SUBSTITUTE(UPPER(TRIM(controle!E221)),"SWICHER","SWITCHER")))) -> DEPÓSITO RH | C221: =IF(TRIM(controle!K222)="","Não informado",IF(ISNUMBER(SEARCH("DESCARTE",UPPER(controle!K222))),"Descarte",IF(ISNUMBER(SEARCH("INATIVO",UPPER(controle!K222))),"Inativo",IF(OR(ISNUMBER(SEARCH("BOM",UPPER(controle!K222))),ISNUMBER(SEARCH("OK",UPPER(controle!K222)))),"Bom/OK","Outros")))) -> Descarte | D221: =IF(TRIM(controle!G221)="","Não informado",UPPER(TRIM(controle!G221))) -> DELL
A222: =IF(TRIM(controle!A222)="","Não informado",IF(LEFT(UPPER(TRIM(controle!A222)),7)="MONITOR","Monitores",IF(OR(LEFT(UPPER(TRIM(controle!A222)),7)="DESKTOP",UPPER(TRIM(controle!A222))="MICRO",LEFT(UPPER(TRIM(controle!A222)),7)="MONTADO"),"Desktops/Micros",IF(LEFT(UPPER(TRIM(controle!A222)),8)="NOTEBOOK","Notebooks",IF(LEFT(UPPER(TRIM(controle!A222)),10)="IMPRESSORA","Impressoras",IF(LEFT(UPPER(TRIM(controle!A222)),8)="TELEFONE","Telefonia","Outros")))))) -> Monitores | B222: =IF(TRIM(controle!E222)="","Sem departamento",IF(OR(UPPER(TRIM(controle!E222))="TI",UPPER(TRIM(controle!E222))="T.I"),"T.I",IF(OR(UPPER(TRIM(controle!E222))="TECNICA",UPPER(TRIM(controle!E222))="TÉCNICA"),"TÉCNICA",SUBSTITUTE(UPPER(TRIM(controle!E222)),"SWICHER","SWITCHER")))) -> DEPÓSITO RH | C222: =IF(TRIM(controle!K223)="","Não informado",IF(ISNUMBER(SEARCH("DESCARTE",UPPER(controle!K223))),"Descarte",IF(ISNUMBER(SEARCH("INATIVO",UPPER(controle!K223))),"Inativo",IF(OR(ISNUMBER(SEARCH("BOM",UPPER(controle!K223))),ISNUMBER(SEARCH("OK",UPPER(controle!K223)))),"Bom/OK","Outros")))) -> Descarte | D222: =IF(TRIM(controle!G222)="","Não informado",UPPER(TRIM(controle!G222))) -> DELL
A223: =IF(TRIM(controle!A223)="","Não informado",IF(LEFT(UPPER(TRIM(controle!A223)),7)="MONITOR","Monitores",IF(OR(LEFT(UPPER(TRIM(controle!A223)),7)="DESKTOP",UPPER(TRIM(controle!A223))="MICRO",LEFT(UPPER(TRIM(controle!A223)),7)="MONTADO"),"Desktops/Micros",IF(LEFT(UPPER(TRIM(controle!A223)),8)="NOTEBOOK","Notebooks",IF(LEFT(UPPER(TRIM(controle!A223)),10)="IMPRESSORA","Impressoras",IF(LEFT(UPPER(TRIM(controle!A223)),8)="TELEFONE","Telefonia","Outros")))))) -> Monitores | B223: =IF(TRIM(controle!E223)="","Sem departamento",IF(OR(UPPER(TRIM(controle!E223))="TI",UPPER(TRIM(controle!E223))="T.I"),"T.I",IF(OR(UPPER(TRIM(controle!E223))="TECNICA",UPPER(TRIM(controle!E223))="TÉCNICA"),"TÉCNICA",SUBSTITUTE(UPPER(TRIM(controle!E223)),"SWICHER","SWITCHER")))) -> DEPÓSITO RH | C223: =IF(TRIM(controle!#REF!)="","Não informado",IF(ISNUMBER(SEARCH("DESCARTE",UPPER(controle!#REF!))),"Descarte",IF(ISNUMBER(SEARCH("INATIVO",UPPER(controle!#REF!))),"Inativo",IF(OR(ISNUMBER(SEARCH("BOM",UPPER(controle!#REF!))),ISNUMBER(SEARCH("OK",UPPER(controle!#REF!)))),"Bom/OK","Outros")))) -> #REF! | D223: =IF(TRIM(controle!G223)="","Não informado",UPPER(TRIM(controle!G223))) -> DELL
A224: =IF(TRIM(controle!A224)="","Não informado",IF(LEFT(UPPER(TRIM(controle!A224)),7)="MONITOR","Monitores",IF(OR(LEFT(UPPER(TRIM(controle!A224)),7)="DESKTOP",UPPER(TRIM(controle!A224))="MICRO",LEFT(UPPER(TRIM(controle!A224)),7)="MONTADO"),"Desktops/Micros",IF(LEFT(UPPER(TRIM(controle!A224)),8)="NOTEBOOK","Notebooks",IF(LEFT(UPPER(TRIM(controle!A224)),10)="IMPRESSORA","Impressoras",IF(LEFT(UPPER(TRIM(controle!A224)),8)="TELEFONE","Telefonia","Outros")))))) -> Monitores | B224: =IF(TRIM(controle!E224)="","Sem departamento",IF(OR(UPPER(TRIM(controle!E224))="TI",UPPER(TRIM(controle!E224))="T.I"),"T.I",IF(OR(UPPER(TRIM(controle!E224))="TECNICA",UPPER(TRIM(controle!E224))="TÉCNICA"),"TÉCNICA",SUBSTITUTE(UPPER(TRIM(controle!E224)),"SWICHER","SWITCHER")))) -> DEPÓSITO RH | C224: =IF(TRIM(controle!K224)="","Não informado",IF(ISNUMBER(SEARCH("DESCARTE",UPPER(controle!K224))),"Descarte",IF(ISNUMBER(SEARCH("INATIVO",UPPER(controle!K224))),"Inativo",IF(OR(ISNUMBER(SEARCH("BOM",UPPER(controle!K224))),ISNUMBER(SEARCH("OK",UPPER(controle!K224)))),"Bom/OK","Outros")))) -> Descarte | D224: =IF(TRIM(controle!G224)="","Não informado",UPPER(TRIM(controle!G224))) -> DELL
A225: =IF(TRIM(controle!A225)="","Não informado",IF(LEFT(UPPER(TRIM(controle!A225)),7)="MONITOR","Monitores",IF(OR(LEFT(UPPER(TRIM(controle!A225)),7)="DESKTOP",UPPER(TRIM(controle!A225))="MICRO",LEFT(UPPER(TRIM(controle!A225)),7)="MONTADO"),"Desktops/Micros",IF(LEFT(UPPER(TRIM(controle!A225)),8)="NOTEBOOK","Notebooks",IF(LEFT(UPPER(TRIM(controle!A225)),10)="IMPRESSORA","Impressoras",IF(LEFT(UPPER(TRIM(controle!A225)),8)="TELEFONE","Telefonia","Outros")))))) -> Monitores | B225: =IF(TRIM(controle!E225)="","Sem departamento",IF(OR(UPPER(TRIM(controle!E225))="TI",UPPER(TRIM(controle!E225))="T.I"),"T.I",IF(OR(UPPER(TRIM(controle!E225))="TECNICA",UPPER(TRIM(controle!E225))="TÉCNICA"),"TÉCNICA",SUBSTITUTE(UPPER(TRIM(controle!E225)),"SWICHER","SWITCHER")))) -> DEPÓSITO RH | C225: =IF(TRIM(controle!K225)="","Não informado",IF(ISNUMBER(SEARCH("DESCARTE",UPPER(controle!K225))),"Descarte",IF(ISNUMBER(SEARCH("INATIVO",UPPER(controle!K225))),"Inativo",IF(OR(ISNUMBER(SEARCH("BOM",UPPER(controle!K225))),ISNUMBER(SEARCH("OK",UPPER(controle!K225)))),"Bom/OK","Outros")))) -> Descarte | D225: =IF(TRIM(controle!G225)="","Não informado",UPPER(TRIM(controle!G225))) -> DELL
A226: =IF(TRIM(controle!A226)="","Não informado",IF(LEFT(UPPER(TRIM(controle!A226)),7)="MONITOR","Monitores",IF(OR(LEFT(UPPER(TRIM(controle!A226)),7)="DESKTOP",UPPER(TRIM(controle!A226))="MICRO",LEFT(UPPER(TRIM(controle!A226)),7)="MONTADO"),"Desktops/Micros",IF(LEFT(UPPER(TRIM(controle!A226)),8)="NOTEBOOK","Notebooks",IF(LEFT(UPPER(TRIM(controle!A226)),10)="IMPRESSORA","Impressoras",IF(LEFT(UPPER(TRIM(controle!A226)),8)="TELEFONE","Telefonia","Outros")))))) -> Monitores | B226: =IF(TRIM(controle!E226)="","Sem departamento",IF(OR(UPPER(TRIM(controle!E226))="TI",UPPER(TRIM(controle!E226))="T.I"),"T.I",IF(OR(UPPER(TRIM(controle!E226))="TECNICA",UPPER(TRIM(controle!E226))="TÉCNICA"),"TÉCNICA",SUBSTITUTE(UPPER(TRIM(controle!E226)),"SWICHER","SWITCHER")))) -> DEPÓSITO RH | C226: =IF(TRIM(controle!K226)="","Não informado",IF(ISNUMBER(SEARCH("DESCARTE",UPPER(controle!K226))),"Descarte",IF(ISNUMBER(SEARCH("INATIVO",UPPER(controle!K226))),"Inativo",IF(OR(ISNUMBER(SEARCH("BOM",UPPER(controle!K226))),ISNUMBER(SEARCH("OK",UPPER(controle!K226)))),"Bom/OK","Outros")))) -> Descarte | D226: =IF(TRIM(controle!G226)="","Não informado",UPPER(TRIM(controle!G226))) -> DELL
A227: =IF(TRIM(controle!A227)="","Não informado",IF(LEFT(UPPER(TRIM(controle!A227)),7)="MONITOR","Monitores",IF(OR(LEFT(UPPER(TRIM(controle!A227)),7)="DESKTOP",UPPER(TRIM(controle!A227))="MICRO",LEFT(UPPER(TRIM(controle!A227)),7)="MONTADO"),"Desktops/Micros",IF(LEFT(UPPER(TRIM(controle!A227)),8)="NOTEBOOK","Notebooks",IF(LEFT(UPPER(TRIM(controle!A227)),10)="IMPRESSORA","Impressoras",IF(LEFT(UPPER(TRIM(controle!A227)),8)="TELEFONE","Telefonia","Outros")))))) -> Monitores | B227: =IF(TRIM(controle!E227)="","Sem departamento",IF(OR(UPPER(TRIM(controle!E227))="TI",UPPER(TRIM(controle!E227))="T.I"),"T.I",IF(OR(UPPER(TRIM(controle!E227))="TECNICA",UPPER(TRIM(controle!E227))="TÉCNICA"),"TÉCNICA",SUBSTITUTE(UPPER(TRIM(controle!E227)),"SWICHER","SWITCHER")))) -> DEPÓSITO RH | C227: =IF(TRIM(controle!K227)="","Não informado",IF(ISNUMBER(SEARCH("DESCARTE",UPPER(controle!K227))),"Descarte",IF(ISNUMBER(SEARCH("INATIVO",UPPER(controle!K227))),"Inativo",IF(OR(ISNUMBER(SEARCH("BOM",UPPER(controle!K227))),ISNUMBER(SEARCH("OK",UPPER(controle!K227)))),"Bom/OK","Outros")))) -> Descarte | D227: =IF(TRIM(controle!G227)="","Não informado",UPPER(TRIM(controle!G227))) -> DELL
A228: =IF(TRIM(controle!A228)="","Não informado",IF(LEFT(UPPER(TRIM(controle!A228)),7)="MONITOR","Monitores",IF(OR(LEFT(UPPER(TRIM(controle!A228)),7)="DESKTOP",UPPER(TRIM(controle!A228))="MICRO",LEFT(UPPER(TRIM(controle!A228)),7)="MONTADO"),"Desktops/Micros",IF(LEFT(UPPER(TRIM(controle!A228)),8)="NOTEBOOK","Notebooks",IF(LEFT(UPPER(TRIM(controle!A228)),10)="IMPRESSORA","Impressoras",IF(LEFT(UPPER(TRIM(controle!A228)),8)="TELEFONE","Telefonia","Outros")))))) -> Monitores | B228: =IF(TRIM(controle!E228)="","Sem departamento",IF(OR(UPPER(TRIM(controle!E228))="TI",UPPER(TRIM(controle!E228))="T.I"),"T.I",IF(OR(UPPER(TRIM(controle!E228))="TECNICA",UPPER(TRIM(controle!E228))="TÉCNICA"),"TÉCNICA",SUBSTITUTE(UPPER(TRIM(controle!E228)),"SWICHER","SWITCHER")))) -> DEPÓSITO RH | C228: =IF(TRIM(controle!K228)="","Não informado",IF(ISNUMBER(SEARCH("DESCARTE",UPPER(controle!K228))),"Descarte",IF(ISNUMBER(SEARCH("INATIVO",UPPER(controle!K228))),"Inativo",IF(OR(ISNUMBER(SEARCH("BOM",UPPER(controle!K228))),ISNUMBER(SEARCH("OK",UPPER(controle!K228)))),"Bom/OK","Outros")))) -> Descarte | D228: =IF(TRIM(controle!G228)="","Não informado",UPPER(TRIM(controle!G228))) -> DELL
A229: =IF(TRIM(controle!A229)="","Não informado",IF(LEFT(UPPER(TRIM(controle!A229)),7)="MONITOR","Monitores",IF(OR(LEFT(UPPER(TRIM(controle!A229)),7)="DESKTOP",UPPER(TRIM(controle!A229))="MICRO",LEFT(UPPER(TRIM(controle!A229)),7)="MONTADO"),"Desktops/Micros",IF(LEFT(UPPER(TRIM(controle!A229)),8)="NOTEBOOK","Notebooks",IF(LEFT(UPPER(TRIM(controle!A229)),10)="IMPRESSORA","Impressoras",IF(LEFT(UPPER(TRIM(controle!A229)),8)="TELEFONE","Telefonia","Outros")))))) -> Monitores | B229: =IF(TRIM(controle!E229)="","Sem departamento",IF(OR(UPPER(TRIM(controle!E229))="TI",UPPER(TRIM(controle!E229))="T.I"),"T.I",IF(OR(UPPER(TRIM(controle!E229))="TECNICA",UPPER(TRIM(controle!E229))="TÉCNICA"),"TÉCNICA",SUBSTITUTE(UPPER(TRIM(controle!E229)),"SWICHER","SWITCHER")))) -> SALA TECNICA | C229: =IF(TRIM(controle!K229)="","Não informado",IF(ISNUMBER(SEARCH("DESCARTE",UPPER(controle!K229))),"Descarte",IF(ISNUMBER(SEARCH("INATIVO",UPPER(controle!K229))),"Inativo",IF(OR(ISNUMBER(SEARCH("BOM",UPPER(controle!K229))),ISNUMBER(SEARCH("OK",UPPER(controle!K229)))),"Bom/OK","Outros")))) -> Bom/OK | D229: =IF(TRIM(controle!G229)="","Não informado",UPPER(TRIM(controle!G229))) -> DELL
A230: =IF(TRIM(controle!A230)="","Não informado",IF(LEFT(UPPER(TRIM(controle!A230)),7)="MONITOR","Monitores",IF(OR(LEFT(UPPER(TRIM(controle!A230)),7)="DESKTOP",UPPER(TRIM(controle!A230))="MICRO",LEFT(UPPER(TRIM(controle!A230)),7)="MONTADO"),"Desktops/Micros",IF(LEFT(UPPER(TRIM(controle!A230)),8)="NOTEBOOK","Notebooks",IF(LEFT(UPPER(TRIM(controle!A230)),10)="IMPRESSORA","Impressoras",IF(LEFT(UPPER(TRIM(controle!A230)),8)="TELEFONE","Telefonia","Outros")))))) -> Monitores | B230: =IF(TRIM(controle!E230)="","Sem departamento",IF(OR(UPPER(TRIM(controle!E230))="TI",UPPER(TRIM(controle!E230))="T.I"),"T.I",IF(OR(UPPER(TRIM(controle!E230))="TECNICA",UPPER(TRIM(controle!E230))="TÉCNICA"),"TÉCNICA",SUBSTITUTE(UPPER(TRIM(controle!E230)),"SWICHER","SWITCHER")))) -> SWITCHER | C230: =IF(TRIM(controle!K230)="","Não informado",IF(ISNUMBER(SEARCH("DESCARTE",UPPER(controle!K230))),"Descarte",IF(ISNUMBER(SEARCH("INATIVO",UPPER(controle!K230))),"Inativo",IF(OR(ISNUMBER(SEARCH("BOM",UPPER(controle!K230))),ISNUMBER(SEARCH("OK",UPPER(controle!K230)))),"Bom/OK","Outros")))) -> Bom/OK | D230: =IF(TRIM(controle!G230)="","Não informado",UPPER(TRIM(controle!G230))) -> DELL
A231: =IF(TRIM(controle!A231)="","Não informado",IF(LEFT(UPPER(TRIM(controle!A231)),7)="MONITOR","Monitores",IF(OR(LEFT(UPPER(TRIM(controle!A231)),7)="DESKTOP",UPPER(TRIM(controle!A231))="MICRO",LEFT(UPPER(TRIM(controle!A231)),7)="MONTADO"),"Desktops/Micros",IF(LEFT(UPPER(TRIM(controle!A231)),8)="NOTEBOOK","Notebooks",IF(LEFT(UPPER(TRIM(controle!A231)),10)="IMPRESSORA","Impressoras",IF(LEFT(UPPER(TRIM(controle!A231)),8)="TELEFONE","Telefonia","Outros")))))) -> Monitores | B231: =IF(TRIM(controle!E231)="","Sem departamento",IF(OR(UPPER(TRIM(controle!E231))="TI",UPPER(TRIM(controle!E231))="T.I"),"T.I",IF(OR(UPPER(TRIM(controle!E231))="TECNICA",UPPER(TRIM(controle!E231))="TÉCNICA"),"TÉCNICA",SUBSTITUTE(UPPER(TRIM(controle!E231)),"SWICHER","SWITCHER")))) -> SWITCHER | C231: =IF(TRIM(controle!K231)="","Não informado",IF(ISNUMBER(SEARCH("DESCARTE",UPPER(controle!K231))),"Descarte",IF(ISNUMBER(SEARCH("INATIVO",UPPER(controle!K231))),"Inativo",IF(OR(ISNUMBER(SEARCH("BOM",UPPER(controle!K231))),ISNUMBER(SEARCH("OK",UPPER(controle!K231)))),"Bom/OK","Outros")))) -> Bom/OK | D231: =IF(TRIM(controle!G231)="","Não informado",UPPER(TRIM(controle!G231))) -> DELL
A232: =IF(TRIM(controle!A232)="","Não informado",IF(LEFT(UPPER(TRIM(controle!A232)),7)="MONITOR","Monitores",IF(OR(LEFT(UPPER(TRIM(controle!A232)),7)="DESKTOP",UPPER(TRIM(controle!A232))="MICRO",LEFT(UPPER(TRIM(controle!A232)),7)="MONTADO"),"Desktops/Micros",IF(LEFT(UPPER(TRIM(controle!A232)),8)="NOTEBOOK","Notebooks",IF(LEFT(UPPER(TRIM(controle!A232)),10)="IMPRESSORA","Impressoras",IF(LEFT(UPPER(TRIM(controle!A232)),8)="TELEFONE","Telefonia","Outros")))))) -> Monitores | B232: =IF(TRIM(controle!E232)="","Sem departamento",IF(OR(UPPER(TRIM(controle!E232))="TI",UPPER(TRIM(controle!E232))="T.I"),"T.I",IF(OR(UPPER(TRIM(controle!E232))="TECNICA",UPPER(TRIM(controle!E232))="TÉCNICA"),"TÉCNICA",SUBSTITUTE(UPPER(TRIM(controle!E232)),"SWICHER","SWITCHER")))) -> SWITCHER | C232: =IF(TRIM(controle!K232)="","Não informado",IF(ISNUMBER(SEARCH("DESCARTE",UPPER(controle!K232))),"Descarte",IF(ISNUMBER(SEARCH("INATIVO",UPPER(controle!K232))),"Inativo",IF(OR(ISNUMBER(SEARCH("BOM",UPPER(controle!K232))),ISNUMBER(SEARCH("OK",UPPER(controle!K232)))),"Bom/OK","Outros")))) -> Bom/OK | D232: =IF(TRIM(controle!G232)="","Não informado",UPPER(TRIM(controle!G232))) -> DELL
A233: =IF(TRIM(controle!A233)="","Não informado",IF(LEFT(UPPER(TRIM(controle!A233)),7)="MONITOR","Monitores",IF(OR(LEFT(UPPER(TRIM(controle!A233)),7)="DESKTOP",UPPER(TRIM(controle!A233))="MICRO",LEFT(UPPER(TRIM(controle!A233)),7)="MONTADO"),"Desktops/Micros",IF(LEFT(UPPER(TRIM(controle!A233)),8)="NOTEBOOK","Notebooks",IF(LEFT(UPPER(TRIM(controle!A233)),10)="IMPRESSORA","Impressoras",IF(LEFT(UPPER(TRIM(controle!A233)),8)="TELEFONE","Telefonia","Outros")))))) -> Monitores | B233: =IF(TRIM(controle!E233)="","Sem departamento",IF(OR(UPPER(TRIM(controle!E233))="TI",UPPER(TRIM(controle!E233))="T.I"),"T.I",IF(OR(UPPER(TRIM(controle!E233))="TECNICA",UPPER(TRIM(controle!E233))="TÉCNICA"),"TÉCNICA",SUBSTITUTE(UPPER(TRIM(controle!E233)),"SWICHER","SWITCHER")))) -> SWITCHER | C233: =IF(TRIM(controle!K233)="","Não informado",IF(ISNUMBER(SEARCH("DESCARTE",UPPER(controle!K233))),"Descarte",IF(ISNUMBER(SEARCH("INATIVO",UPPER(controle!K233))),"Inativo",IF(OR(ISNUMBER(SEARCH("BOM",UPPER(controle!K233))),ISNUMBER(SEARCH("OK",UPPER(controle!K233)))),"Bom/OK","Outros")))) -> Bom/OK | D233: =IF(TRIM(controle!G233)="","Não informado",UPPER(TRIM(controle!G233))) -> DELL
A234: =IF(TRIM(controle!A234)="","Não informado",IF(LEFT(UPPER(TRIM(controle!A234)),7)="MONITOR","Monitores",IF(OR(LEFT(UPPER(TRIM(controle!A234)),7)="DESKTOP",UPPER(TRIM(controle!A234))="MICRO",LEFT(UPPER(TRIM(controle!A234)),7)="MONTADO"),"Desktops/Micros",IF(LEFT(UPPER(TRIM(controle!A234)),8)="NOTEBOOK","Notebooks",IF(LEFT(UPPER(TRIM(controle!A234)),10)="IMPRESSORA","Impressoras",IF(LEFT(UPPER(TRIM(controle!A234)),8)="TELEFONE","Telefonia","Outros")))))) -> Monitores | B234: =IF(TRIM(controle!E234)="","Sem departamento",IF(OR(UPPER(TRIM(controle!E234))="TI",UPPER(TRIM(controle!E234))="T.I"),"T.I",IF(OR(UPPER(TRIM(controle!E234))="TECNICA",UPPER(TRIM(controle!E234))="TÉCNICA"),"TÉCNICA",SUBSTITUTE(UPPER(TRIM(controle!E234)),"SWICHER","SWITCHER")))) -> DEPÓSITO RH | C234: =IF(TRIM(controle!K234)="","Não informado",IF(ISNUMBER(SEARCH("DESCARTE",UPPER(controle!K234))),"Descarte",IF(ISNUMBER(SEARCH("INATIVO",UPPER(controle!K234))),"Inativo",IF(OR(ISNUMBER(SEARCH("BOM",UPPER(controle!K234))),ISNUMBER(SEARCH("OK",UPPER(controle!K234)))),"Bom/OK","Outros")))) -> Descarte | D234: =IF(TRIM(controle!G234)="","Não informado",UPPER(TRIM(controle!G234))) -> LG
A235: =IF(TRIM(controle!A235)="","Não informado",IF(LEFT(UPPER(TRIM(controle!A235)),7)="MONITOR","Monitores",IF(OR(LEFT(UPPER(TRIM(controle!A235)),7)="DESKTOP",UPPER(TRIM(controle!A235))="MICRO",LEFT(UPPER(TRIM(controle!A235)),7)="MONTADO"),"Desktops/Micros",IF(LEFT(UPPER(TRIM(controle!A235)),8)="NOTEBOOK","Notebooks",IF(LEFT(UPPER(TRIM(controle!A235)),10)="IMPRESSORA","Impressoras",IF(LEFT(UPPER(TRIM(controle!A235)),8)="TELEFONE","Telefonia","Outros")))))) -> Monitores | B235: =IF(TRIM(controle!E235)="","Sem departamento",IF(OR(UPPER(TRIM(controle!E235))="TI",UPPER(TRIM(controle!E235))="T.I"),"T.I",IF(OR(UPPER(TRIM(controle!E235))="TECNICA",UPPER(TRIM(controle!E235))="TÉCNICA"),"TÉCNICA",SUBSTITUTE(UPPER(TRIM(controle!E235)),"SWICHER","SWITCHER")))) -> DEPÓSITO RH | C235: =IF(TRIM(controle!K235)="","Não informado",IF(ISNUMBER(SEARCH("DESCARTE",UPPER(controle!K235))),"Descarte",IF(ISNUMBER(SEARCH("INATIVO",UPPER(controle!K235))),"Inativo",IF(OR(ISNUMBER(SEARCH("BOM",UPPER(controle!K235))),ISNUMBER(SEARCH("OK",UPPER(controle!K235)))),"Bom/OK","Outros")))) -> Descarte | D235: =IF(TRIM(controle!G235)="","Não informado",UPPER(TRIM(controle!G235))) -> LG
... A439: =IF(TRIM(controle!A439)="","Não informado",IF(LEFT(UPPER(TRIM(controle!A439)),7)="MONITOR","Monitores",IF(OR(LEFT(UPPER(TRIM(controle!A439)),7)="DESKTOP",UPPER(TRIM(controle!A439))="MICRO",LEFT(UPPER(TRIM(controle!A439)),7)="MONTADO"),"Desktops/Micros",IF(LEFT(UPPER(TRIM(controle!A439)),8)="NOTEBOOK","Notebooks",IF(LEFT(UPPER(TRIM(controle!A439)),10)="IMPRESSORA","Impressoras",IF(LEFT(UPPER(TRIM(controle!A439)),8)="TELEFONE","Telefonia","Outros")))))) -> Desktops/Micros | B439: =IF(TRIM(controle!E439)="","Sem departamento",IF(OR(UPPER(TRIM(controle!E439))="TI",UPPER(TRIM(controle!E439))="T.I"),"T.I",IF(OR(UPPER(TRIM(controle!E439))="TECNICA",UPPER(TRIM(controle!E439))="TÉCNICA"),"TÉCNICA",SUBSTITUTE(UPPER(TRIM(controle!E439)),"SWICHER","SWITCHER")))) -> DEPÓSITO RH | C439: =IF(TRIM(controle!K439)="","Não informado",IF(ISNUMBER(SEARCH("DESCARTE",UPPER(controle!K439))),"Descarte",IF(ISNUMBER(SEARCH("INATIVO",UPPER(controle!K439))),"Inativo",IF(OR(ISNUMBER(SEARCH("BOM",UPPER(controle!K439))),ISNUMBER(SEARCH("OK",UPPER(controle!K439)))),"Bom/OK","Outros")))) -> Inativo | D439: =IF(TRIM(controle!G439)="","Não informado",UPPER(TRIM(controle!G439))) -> DELL
A440: =IF(TRIM(controle!A441)="","Não informado",IF(LEFT(UPPER(TRIM(controle!A441)),7)="MONITOR","Monitores",IF(OR(LEFT(UPPER(TRIM(controle!A441)),7)="DESKTOP",UPPER(TRIM(controle!A441))="MICRO",LEFT(UPPER(TRIM(controle!A441)),7)="MONTADO"),"Desktops/Micros",IF(LEFT(UPPER(TRIM(controle!A441)),8)="NOTEBOOK","Notebooks",IF(LEFT(UPPER(TRIM(controle!A441)),10)="IMPRESSORA","Impressoras",IF(LEFT(UPPER(TRIM(controle!A441)),8)="TELEFONE","Telefonia","Outros")))))) -> Notebooks | B440: =IF(TRIM(controle!E441)="","Sem departamento",IF(OR(UPPER(TRIM(controle!E441))="TI",UPPER(TRIM(controle!E441))="T.I"),"T.I",IF(OR(UPPER(TRIM(controle!E441))="TECNICA",UPPER(TRIM(controle!E441))="TÉCNICA"),"TÉCNICA",SUBSTITUTE(UPPER(TRIM(controle!E441)),"SWICHER","SWITCHER")))) -> COMERCIAL | C440: =IF(TRIM(controle!K441)="","Não informado",IF(ISNUMBER(SEARCH("DESCARTE",UPPER(controle!K441))),"Descarte",IF(ISNUMBER(SEARCH("INATIVO",UPPER(controle!K441))),"Inativo",IF(OR(ISNUMBER(SEARCH("BOM",UPPER(controle!K441))),ISNUMBER(SEARCH("OK",UPPER(controle!K441)))),"Bom/OK","Outros")))) -> Bom/OK | D440: =IF(TRIM(controle!G441)="","Não informado",UPPER(TRIM(controle!G441))) -> DELL
A441: =IF(TRIM(controle!A442)="","Não informado",IF(LEFT(UPPER(TRIM(controle!A442)),7)="MONITOR","Monitores",IF(OR(LEFT(UPPER(TRIM(controle!A442)),7)="DESKTOP",UPPER(TRIM(controle!A442))="MICRO",LEFT(UPPER(TRIM(controle!A442)),7)="MONTADO"),"Desktops/Micros",IF(LEFT(UPPER(TRIM(controle!A442)),8)="NOTEBOOK","Notebooks",IF(LEFT(UPPER(TRIM(controle!A442)),10)="IMPRESSORA","Impressoras",IF(LEFT(UPPER(TRIM(controle!A442)),8)="TELEFONE","Telefonia","Outros")))))) -> Notebooks | B441: =IF(TRIM(controle!E442)="","Sem departamento",IF(OR(UPPER(TRIM(controle!E442))="TI",UPPER(TRIM(controle!E442))="T.I"),"T.I",IF(OR(UPPER(TRIM(controle!E442))="TECNICA",UPPER(TRIM(controle!E442))="TÉCNICA"),"TÉCNICA",SUBSTITUTE(UPPER(TRIM(controle!E442)),"SWICHER","SWITCHER")))) -> COMERCIAL | C441: =IF(TRIM(controle!K442)="","Não informado",IF(ISNUMBER(SEARCH("DESCARTE",UPPER(controle!K442))),"Descarte",IF(ISNUMBER(SEARCH("INATIVO",UPPER(controle!K442))),"Inativo",IF(OR(ISNUMBER(SEARCH("BOM",UPPER(controle!K442))),ISNUMBER(SEARCH("OK",UPPER(controle!K442)))),"Bom/OK","Outros")))) -> Bom/OK | D441: =IF(TRIM(controle!G442)="","Não informado",UPPER(TRIM(controle!G442))) -> DELL
A442: =IF(TRIM(controle!A443)="","Não informado",IF(LEFT(UPPER(TRIM(controle!A443)),7)="MONITOR","Monitores",IF(OR(LEFT(UPPER(TRIM(controle!A443)),7)="DESKTOP",UPPER(TRIM(controle!A443))="MICRO",LEFT(UPPER(TRIM(controle!A443)),7)="MONTADO"),"Desktops/Micros",IF(LEFT(UPPER(TRIM(controle!A443)),8)="NOTEBOOK","Notebooks",IF(LEFT(UPPER(TRIM(controle!A443)),10)="IMPRESSORA","Impressoras",IF(LEFT(UPPER(TRIM(controle!A443)),8)="TELEFONE","Telefonia","Outros")))))) -> Notebooks | B442: =IF(TRIM(controle!E443)="","Sem departamento",IF(OR(UPPER(TRIM(controle!E443))="TI",UPPER(TRIM(controle!E443))="T.I"),"T.I",IF(OR(UPPER(TRIM(controle!E443))="TECNICA",UPPER(TRIM(controle!E443))="TÉCNICA"),"TÉCNICA",SUBSTITUTE(UPPER(TRIM(controle!E443)),"SWICHER","SWITCHER")))) -> COMERCIAL | C442: =IF(TRIM(controle!K443)="","Não informado",IF(ISNUMBER(SEARCH("DESCARTE",UPPER(controle!K443))),"Descarte",IF(ISNUMBER(SEARCH("INATIVO",UPPER(controle!K443))),"Inativo",IF(OR(ISNUMBER(SEARCH("BOM",UPPER(controle!K443))),ISNUMBER(SEARCH("OK",UPPER(controle!K443)))),"Bom/OK","Outros")))) -> Bom/OK | D442: =IF(TRIM(controle!G443)="","Não informado",UPPER(TRIM(controle!G443))) -> DELL
A443: =IF(TRIM(controle!A444)="","Não informado",IF(LEFT(UPPER(TRIM(controle!A444)),7)="MONITOR","Monitores",IF(OR(LEFT(UPPER(TRIM(controle!A444)),7)="DESKTOP",UPPER(TRIM(controle!A444))="MICRO",LEFT(UPPER(TRIM(controle!A444)),7)="MONTADO"),"Desktops/Micros",IF(LEFT(UPPER(TRIM(controle!A444)),8)="NOTEBOOK","Notebooks",IF(LEFT(UPPER(TRIM(controle!A444)),10)="IMPRESSORA","Impressoras",IF(LEFT(UPPER(TRIM(controle!A444)),8)="TELEFONE","Telefonia","Outros")))))) -> Notebooks | B443: =IF(TRIM(controle!E444)="","Sem departamento",IF(OR(UPPER(TRIM(controle!E444))="TI",UPPER(TRIM(controle!E444))="T.I"),"T.I",IF(OR(UPPER(TRIM(controle!E444))="TECNICA",UPPER(TRIM(controle!E444))="TÉCNICA"),"TÉCNICA",SUBSTITUTE(UPPER(TRIM(controle!E444)),"SWICHER","SWITCHER")))) -> DEPÓSITO RH | C443: =IF(TRIM(controle!K444)="","Não informado",IF(ISNUMBER(SEARCH("DESCARTE",UPPER(controle!K444))),"Descarte",IF(ISNUMBER(SEARCH("INATIVO",UPPER(controle!K444))),"Inativo",IF(OR(ISNUMBER(SEARCH("BOM",UPPER(controle!K444))),ISNUMBER(SEARCH("OK",UPPER(controle!K444)))),"Bom/OK","Outros")))) -> Bom/OK | D443: =IF(TRIM(controle!G444)="","Não informado",UPPER(TRIM(controle!G444))) -> DELL
A444: =IF(TRIM(controle!A445)="","Não informado",IF(LEFT(UPPER(TRIM(controle!A445)),7)="MONITOR","Monitores",IF(OR(LEFT(UPPER(TRIM(controle!A445)),7)="DESKTOP",UPPER(TRIM(controle!A445))="MICRO",LEFT(UPPER(TRIM(controle!A445)),7)="MONTADO"),"Desktops/Micros",IF(LEFT(UPPER(TRIM(controle!A445)),8)="NOTEBOOK","Notebooks",IF(LEFT(UPPER(TRIM(controle!A445)),10)="IMPRESSORA","Impressoras",IF(LEFT(UPPER(TRIM(controle!A445)),8)="TELEFONE","Telefonia","Outros")))))) -> Notebooks | B444: =IF(TRIM(controle!E445)="","Sem departamento",IF(OR(UPPER(TRIM(controle!E445))="TI",UPPER(TRIM(controle!E445))="T.I"),"T.I",IF(OR(UPPER(TRIM(controle!E445))="TECNICA",UPPER(TRIM(controle!E445))="TÉCNICA"),"TÉCNICA",SUBSTITUTE(UPPER(TRIM(controle!E445)),"SWICHER","SWITCHER")))) -> DEPÓSITO RH | C444: =IF(TRIM(controle!K445)="","Não informado",IF(ISNUMBER(SEARCH("DESCARTE",UPPER(controle!K445))),"Descarte",IF(ISNUMBER(SEARCH("INATIVO",UPPER(controle!K445))),"Inativo",IF(OR(ISNUMBER(SEARCH("BOM",UPPER(controle!K445))),ISNUMBER(SEARCH("OK",UPPER(controle!K445)))),"Bom/OK","Outros")))) -> Outros | D444: =IF(TRIM(controle!G445)="","Não informado",UPPER(TRIM(controle!G445))) -> DELL
A445: =IF(TRIM(controle!A446)="","Não informado",IF(LEFT(UPPER(TRIM(controle!A446)),7)="MONITOR","Monitores",IF(OR(LEFT(UPPER(TRIM(controle!A446)),7)="DESKTOP",UPPER(TRIM(controle!A446))="MICRO",LEFT(UPPER(TRIM(controle!A446)),7)="MONTADO"),"Desktops/Micros",IF(LEFT(UPPER(TRIM(controle!A446)),8)="NOTEBOOK","Notebooks",IF(LEFT(UPPER(TRIM(controle!A446)),10)="IMPRESSORA","Impressoras",IF(LEFT(UPPER(TRIM(controle!A446)),8)="TELEFONE","Telefonia","Outros")))))) -> Notebooks | B445: =IF(TRIM(controle!E446)="","Sem departamento",IF(OR(UPPER(TRIM(controle!E446))="TI",UPPER(TRIM(controle!E446))="T.I"),"T.I",IF(OR(UPPER(TRIM(controle!E446))="TECNICA",UPPER(TRIM(controle!E446))="TÉCNICA"),"TÉCNICA",SUBSTITUTE(UPPER(TRIM(controle!E446)),"SWICHER","SWITCHER")))) -> DEPÓSITO RH | C445: =IF(TRIM(controle!K446)="","Não informado",IF(ISNUMBER(SEARCH("DESCARTE",UPPER(controle!K446))),"Descarte",IF(ISNUMBER(SEARCH("INATIVO",UPPER(controle!K446))),"Inativo",IF(OR(ISNUMBER(SEARCH("BOM",UPPER(controle!K446))),ISNUMBER(SEARCH("OK",UPPER(controle!K446)))),"Bom/OK","Outros")))) -> Bom/OK | D445: =IF(TRIM(controle!G446)="","Não informado",UPPER(TRIM(controle!G446))) -> DELL
A446: =IF(TRIM(controle!A447)="","Não informado",IF(LEFT(UPPER(TRIM(controle!A447)),7)="MONITOR","Monitores",IF(OR(LEFT(UPPER(TRIM(controle!A447)),7)="DESKTOP",UPPER(TRIM(controle!A447))="MICRO",LEFT(UPPER(TRIM(controle!A447)),7)="MONTADO"),"Desktops/Micros",IF(LEFT(UPPER(TRIM(controle!A447)),8)="NOTEBOOK","Notebooks",IF(LEFT(UPPER(TRIM(controle!A447)),10)="IMPRESSORA","Impressoras",IF(LEFT(UPPER(TRIM(controle!A447)),8)="TELEFONE","Telefonia","Outros")))))) -> Notebooks | B446: =IF(TRIM(controle!E447)="","Sem departamento",IF(OR(UPPER(TRIM(controle!E447))="TI",UPPER(TRIM(controle!E447))="T.I"),"T.I",IF(OR(UPPER(TRIM(controle!E447))="TECNICA",UPPER(TRIM(controle!E447))="TÉCNICA"),"TÉCNICA",SUBSTITUTE(UPPER(TRIM(controle!E447)),"SWICHER","SWITCHER")))) -> DEPÓSITO RH | C446: =IF(TRIM(controle!K447)="","Não informado",IF(ISNUMBER(SEARCH("DESCARTE",UPPER(controle!K447))),"Descarte",IF(ISNUMBER(SEARCH("INATIVO",UPPER(controle!K447))),"Inativo",IF(OR(ISNUMBER(SEARCH("BOM",UPPER(controle!K447))),ISNUMBER(SEARCH("OK",UPPER(controle!K447)))),"Bom/OK","Outros")))) -> Outros | D446: =IF(TRIM(controle!G447)="","Não informado",UPPER(TRIM(controle!G447))) -> DELL
A447: =IF(TRIM(controle!A448)="","Não informado",IF(LEFT(UPPER(TRIM(controle!A448)),7)="MONITOR","Monitores",IF(OR(LEFT(UPPER(TRIM(controle!A448)),7)="DESKTOP",UPPER(TRIM(controle!A448))="MICRO",LEFT(UPPER(TRIM(controle!A448)),7)="MONTADO"),"Desktops/Micros",IF(LEFT(UPPER(TRIM(controle!A448)),8)="NOTEBOOK","Notebooks",IF(LEFT(UPPER(TRIM(controle!A448)),10)="IMPRESSORA","Impressoras",IF(LEFT(UPPER(TRIM(controle!A448)),8)="TELEFONE","Telefonia","Outros")))))) -> Notebooks | B447: =IF(TRIM(controle!E448)="","Sem departamento",IF(OR(UPPER(TRIM(controle!E448))="TI",UPPER(TRIM(controle!E448))="T.I"),"T.I",IF(OR(UPPER(TRIM(controle!E448))="TECNICA",UPPER(TRIM(controle!E448))="TÉCNICA"),"TÉCNICA",SUBSTITUTE(UPPER(TRIM(controle!E448)),"SWICHER","SWITCHER")))) -> DEPÓSITO RH | C447: =IF(TRIM(controle!K448)="","Não informado",IF(ISNUMBER(SEARCH("DESCARTE",UPPER(controle!K448))),"Descarte",IF(ISNUMBER(SEARCH("INATIVO",UPPER(controle!K448))),"Inativo",IF(OR(ISNUMBER(SEARCH("BOM",UPPER(controle!K448))),ISNUMBER(SEARCH("OK",UPPER(controle!K448)))),"Bom/OK","Outros")))) -> Bom/OK | D447: =IF(TRIM(controle!G448)="","Não informado",UPPER(TRIM(controle!G448))) -> DELL
A448: =IF(TRIM(controle!A449)="","Não informado",IF(LEFT(UPPER(TRIM(controle!A449)),7)="MONITOR","Monitores",IF(OR(LEFT(UPPER(TRIM(controle!A449)),7)="DESKTOP",UPPER(TRIM(controle!A449))="MICRO",LEFT(UPPER(TRIM(controle!A449)),7)="MONTADO"),"Desktops/Micros",IF(LEFT(UPPER(TRIM(controle!A449)),8)="NOTEBOOK","Notebooks",IF(LEFT(UPPER(TRIM(controle!A449)),10)="IMPRESSORA","Impressoras",IF(LEFT(UPPER(TRIM(controle!A449)),8)="TELEFONE","Telefonia","Outros")))))) -> Notebooks | B448: =IF(TRIM(controle!E449)="","Sem departamento",IF(OR(UPPER(TRIM(controle!E449))="TI",UPPER(TRIM(controle!E449))="T.I"),"T.I",IF(OR(UPPER(TRIM(controle!E449))="TECNICA",UPPER(TRIM(controle!E449))="TÉCNICA"),"TÉCNICA",SUBSTITUTE(UPPER(TRIM(controle!E449)),"SWICHER","SWITCHER")))) -> DEPÓSITO RH | C448: =IF(TRIM(controle!K449)="","Não informado",IF(ISNUMBER(SEARCH("DESCARTE",UPPER(controle!K449))),"Descarte",IF(ISNUMBER(SEARCH("INATIVO",UPPER(controle!K449))),"Inativo",IF(OR(ISNUMBER(SEARCH("BOM",UPPER(controle!K449))),ISNUMBER(SEARCH("OK",UPPER(controle!K449)))),"Bom/OK","Outros")))) -> Outros | D448: =IF(TRIM(controle!G449)="","Não informado",UPPER(TRIM(controle!G449))) -> DELL
A449: =IF(TRIM(controle!A450)="","Não informado",IF(LEFT(UPPER(TRIM(controle!A450)),7)="MONITOR","Monitores",IF(OR(LEFT(UPPER(TRIM(controle!A450)),7)="DESKTOP",UPPER(TRIM(controle!A450))="MICRO",LEFT(UPPER(TRIM(controle!A450)),7)="MONTADO"),"Desktops/Micros",IF(LEFT(UPPER(TRIM(controle!A450)),8)="NOTEBOOK","Notebooks",IF(LEFT(UPPER(TRIM(controle!A450)),10)="IMPRESSORA","Impressoras",IF(LEFT(UPPER(TRIM(controle!A450)),8)="TELEFONE","Telefonia","Outros")))))) -> Notebooks | B449: =IF(TRIM(controle!E450)="","Sem departamento",IF(OR(UPPER(TRIM(controle!E450))="TI",UPPER(TRIM(controle!E450))="T.I"),"T.I",IF(OR(UPPER(TRIM(controle!E450))="TECNICA",UPPER(TRIM(controle!E450))="TÉCNICA"),"TÉCNICA",SUBSTITUTE(UPPER(TRIM(controle!E450)),"SWICHER","SWITCHER")))) -> DEPÓSITO RH | C449: =IF(TRIM(controle!K450)="","Não informado",IF(ISNUMBER(SEARCH("DESCARTE",UPPER(controle!K450))),"Descarte",IF(ISNUMBER(SEARCH("INATIVO",UPPER(controle!K450))),"Inativo",IF(OR(ISNUMBER(SEARCH("BOM",UPPER(controle!K450))),ISNUMBER(SEARCH("OK",UPPER(controle!K450)))),"Bom/OK","Outros")))) -> Outros | D449: =IF(TRIM(controle!G450)="","Não informado",UPPER(TRIM(controle!G450))) -> DELL
A450: =IF(TRIM(controle!A451)="","Não informado",IF(LEFT(UPPER(TRIM(controle!A451)),7)="MONITOR","Monitores",IF(OR(LEFT(UPPER(TRIM(controle!A451)),7)="DESKTOP",UPPER(TRIM(controle!A451))="MICRO",LEFT(UPPER(TRIM(controle!A451)),7)="MONTADO"),"Desktops/Micros",IF(LEFT(UPPER(TRIM(controle!A451)),8)="NOTEBOOK","Notebooks",IF(LEFT(UPPER(TRIM(controle!A451)),10)="IMPRESSORA","Impressoras",IF(LEFT(UPPER(TRIM(controle!A451)),8)="TELEFONE","Telefonia","Outros")))))) -> Notebooks | B450: =IF(TRIM(controle!E451)="","Sem departamento",IF(OR(UPPER(TRIM(controle!E451))="TI",UPPER(TRIM(controle!E451))="T.I"),"T.I",IF(OR(UPPER(TRIM(controle!E451))="TECNICA",UPPER(TRIM(controle!E451))="TÉCNICA"),"TÉCNICA",SUBSTITUTE(UPPER(TRIM(controle!E451)),"SWICHER","SWITCHER")))) -> DEPÓSITO RH | C450: =IF(TRIM(controle!K451)="","Não informado",IF(ISNUMBER(SEARCH("DESCARTE",UPPER(controle!K451))),"Descarte",IF(ISNUMBER(SEARCH("INATIVO",UPPER(controle!K451))),"Inativo",IF(OR(ISNUMBER(SEARCH("BOM",UPPER(controle!K451))),ISNUMBER(SEARCH("OK",UPPER(controle!K451)))),"Bom/OK","Outros")))) -> Outros | D450: =IF(TRIM(controle!G451)="","Não informado",UPPER(TRIM(controle!G451))) -> DELL
A451: =IF(TRIM(controle!A452)="","Não informado",IF(LEFT(UPPER(TRIM(controle!A452)),7)="MONITOR","Monitores",IF(OR(LEFT(UPPER(TRIM(controle!A452)),7)="DESKTOP",UPPER(TRIM(controle!A452))="MICRO",LEFT(UPPER(TRIM(controle!A452)),7)="MONTADO"),"Desktops/Micros",IF(LEFT(UPPER(TRIM(controle!A452)),8)="NOTEBOOK","Notebooks",IF(LEFT(UPPER(TRIM(controle!A452)),10)="IMPRESSORA","Impressoras",IF(LEFT(UPPER(TRIM(controle!A452)),8)="TELEFONE","Telefonia","Outros")))))) -> Notebooks | B451: =IF(TRIM(controle!E452)="","Sem departamento",IF(OR(UPPER(TRIM(controle!E452))="TI",UPPER(TRIM(controle!E452))="T.I"),"T.I",IF(OR(UPPER(TRIM(controle!E452))="TECNICA",UPPER(TRIM(controle!E452))="TÉCNICA"),"TÉCNICA",SUBSTITUTE(UPPER(TRIM(controle!E452)),"SWICHER","SWITCHER")))) -> DEPÓSITO RH | C451: =IF(TRIM(controle!K452)="","Não informado",IF(ISNUMBER(SEARCH("DESCARTE",UPPER(controle!K452))),"Descarte",IF(ISNUMBER(SEARCH("INATIVO",UPPER(controle!K452))),"Inativo",IF(OR(ISNUMBER(SEARCH("BOM",UPPER(controle!K452))),ISNUMBER(SEARCH("OK",UPPER(controle!K452)))),"Bom/OK","Outros")))) -> Outros | D451: =IF(TRIM(controle!G452)="","Não informado",UPPER(TRIM(controle!G452))) -> DELL
... A458: =IF(TRIM(controle!A459)="","Não informado",IF(LEFT(UPPER(TRIM(controle!A459)),7)="MONITOR","Monitores",IF(OR(LEFT(UPPER(TRIM(controle!A459)),7)="DESKTOP",UPPER(TRIM(controle!A459))="MICRO",LEFT(UPPER(TRIM(controle!A459)),7)="MONTADO"),"Desktops/Micros",IF(LEFT(UPPER(TRIM(controle!A459)),8)="NOTEBOOK","Notebooks",IF(LEFT(UPPER(TRIM(controle!A459)),10)="IMPRESSORA","Impressoras",IF(LEFT(UPPER(TRIM(controle!A459)),8)="TELEFONE","Telefonia","Outros")))))) -> Notebooks | B458: =IF(TRIM(controle!E459)="","Sem departamento",IF(OR(UPPER(TRIM(controle!E459))="TI",UPPER(TRIM(controle!E459))="T.I"),"T.I",IF(OR(UPPER(TRIM(controle!E459))="TECNICA",UPPER(TRIM(controle!E459))="TÉCNICA"),"TÉCNICA",SUBSTITUTE(UPPER(TRIM(controle!E459)),"SWICHER","SWITCHER")))) -> Sem departamento | C458: =IF(TRIM(controle!K459)="","Não informado",IF(ISNUMBER(SEARCH("DESCARTE",UPPER(controle!K459))),"Descarte",IF(ISNUMBER(SEARCH("INATIVO",UPPER(controle!K459))),"Inativo",IF(OR(ISNUMBER(SEARCH("BOM",UPPER(controle!K459))),ISNUMBER(SEARCH("OK",UPPER(controle!K459)))),"Bom/OK","Outros")))) -> Outros | D458: =IF(TRIM(controle!G459)="","Não informado",UPPER(TRIM(controle!G459))) -> DELL
A459: =IF(TRIM(controle!A462)="","Não informado",IF(LEFT(UPPER(TRIM(controle!A462)),7)="MONITOR","Monitores",IF(OR(LEFT(UPPER(TRIM(controle!A462)),7)="DESKTOP",UPPER(TRIM(controle!A462))="MICRO",LEFT(UPPER(TRIM(controle!A462)),7)="MONTADO"),"Desktops/Micros",IF(LEFT(UPPER(TRIM(controle!A462)),8)="NOTEBOOK","Notebooks",IF(LEFT(UPPER(TRIM(controle!A462)),10)="IMPRESSORA","Impressoras",IF(LEFT(UPPER(TRIM(controle!A462)),8)="TELEFONE","Telefonia","Outros")))))) -> Telefonia | B459: =IF(TRIM(controle!E462)="","Sem departamento",IF(OR(UPPER(TRIM(controle!E462))="TI",UPPER(TRIM(controle!E462))="T.I"),"T.I",IF(OR(UPPER(TRIM(controle!E462))="TECNICA",UPPER(TRIM(controle!E462))="TÉCNICA"),"TÉCNICA",SUBSTITUTE(UPPER(TRIM(controle!E462)),"SWICHER","SWITCHER")))) -> ADMINISTRATIVO | C459: =IF(TRIM(controle!K462)="","Não informado",IF(ISNUMBER(SEARCH("DESCARTE",UPPER(controle!K462))),"Descarte",IF(ISNUMBER(SEARCH("INATIVO",UPPER(controle!K462))),"Inativo",IF(OR(ISNUMBER(SEARCH("BOM",UPPER(controle!K462))),ISNUMBER(SEARCH("OK",UPPER(controle!K462)))),"Bom/OK","Outros")))) -> Bom/OK | D459: =IF(TRIM(controle!G462)="","Não informado",UPPER(TRIM(controle!G462))) -> GRANDSTREAM
A460: =IF(TRIM(controle!A463)="","Não informado",IF(LEFT(UPPER(TRIM(controle!A463)),7)="MONITOR","Monitores",IF(OR(LEFT(UPPER(TRIM(controle!A463)),7)="DESKTOP",UPPER(TRIM(controle!A463))="MICRO",LEFT(UPPER(TRIM(controle!A463)),7)="MONTADO"),"Desktops/Micros",IF(LEFT(UPPER(TRIM(controle!A463)),8)="NOTEBOOK","Notebooks",IF(LEFT(UPPER(TRIM(controle!A463)),10)="IMPRESSORA","Impressoras",IF(LEFT(UPPER(TRIM(controle!A463)),8)="TELEFONE","Telefonia","Outros")))))) -> Telefonia | B460: =IF(TRIM(controle!E463)="","Sem departamento",IF(OR(UPPER(TRIM(controle!E463))="TI",UPPER(TRIM(controle!E463))="T.I"),"T.I",IF(OR(UPPER(TRIM(controle!E463))="TECNICA",UPPER(TRIM(controle!E463))="TÉCNICA"),"TÉCNICA",SUBSTITUTE(UPPER(TRIM(controle!E463)),"SWICHER","SWITCHER")))) -> ADMINISTRATIVO | C460: =IF(TRIM(controle!K463)="","Não informado",IF(ISNUMBER(SEARCH("DESCARTE",UPPER(controle!K463))),"Descarte",IF(ISNUMBER(SEARCH("INATIVO",UPPER(controle!K463))),"Inativo",IF(OR(ISNUMBER(SEARCH("BOM",UPPER(controle!K463))),ISNUMBER(SEARCH("OK",UPPER(controle!K463)))),"Bom/OK","Outros")))) -> Bom/OK | D460: =IF(TRIM(controle!G463)="","Não informado",UPPER(TRIM(controle!G463))) -> GRANDSTREAM
A461: =IF(TRIM(controle!A464)="","Não informado",IF(LEFT(UPPER(TRIM(controle!A464)),7)="MONITOR","Monitores",IF(OR(LEFT(UPPER(TRIM(controle!A464)),7)="DESKTOP",UPPER(TRIM(controle!A464))="MICRO",LEFT(UPPER(TRIM(controle!A464)),7)="MONTADO"),"Desktops/Micros",IF(LEFT(UPPER(TRIM(controle!A464)),8)="NOTEBOOK","Notebooks",IF(LEFT(UPPER(TRIM(controle!A464)),10)="IMPRESSORA","Impressoras",IF(LEFT(UPPER(TRIM(controle!A464)),8)="TELEFONE","Telefonia","Outros")))))) -> Telefonia | B461: =IF(TRIM(controle!E464)="","Sem departamento",IF(OR(UPPER(TRIM(controle!E464))="TI",UPPER(TRIM(controle!E464))="T.I"),"T.I",IF(OR(UPPER(TRIM(controle!E464))="TECNICA",UPPER(TRIM(controle!E464))="TÉCNICA"),"TÉCNICA",SUBSTITUTE(UPPER(TRIM(controle!E464)),"SWICHER","SWITCHER")))) -> ADMINISTRATIVO | C461: =IF(TRIM(controle!K464)="","Não informado",IF(ISNUMBER(SEARCH("DESCARTE",UPPER(controle!K464))),"Descarte",IF(ISNUMBER(SEARCH("INATIVO",UPPER(controle!K464))),"Inativo",IF(OR(ISNUMBER(SEARCH("BOM",UPPER(controle!K464))),ISNUMBER(SEARCH("OK",UPPER(controle!K464)))),"Bom/OK","Outros")))) -> Bom/OK | D461: =IF(TRIM(controle!G464)="","Não informado",UPPER(TRIM(controle!G464))) -> GRANDSTREAM
A462: =IF(TRIM(controle!A465)="","Não informado",IF(LEFT(UPPER(TRIM(controle!A465)),7)="MONITOR","Monitores",IF(OR(LEFT(UPPER(TRIM(controle!A465)),7)="DESKTOP",UPPER(TRIM(controle!A465))="MICRO",LEFT(UPPER(TRIM(controle!A465)),7)="MONTADO"),"Desktops/Micros",IF(LEFT(UPPER(TRIM(controle!A465)),8)="NOTEBOOK","Notebooks",IF(LEFT(UPPER(TRIM(controle!A465)),10)="IMPRESSORA","Impressoras",IF(LEFT(UPPER(TRIM(controle!A465)),8)="TELEFONE","Telefonia","Outros")))))) -> Telefonia | B462: =IF(TRIM(controle!E465)="","Sem departamento",IF(OR(UPPER(TRIM(controle!E465))="TI",UPPER(TRIM(controle!E465))="T.I"),"T.I",IF(OR(UPPER(TRIM(controle!E465))="TECNICA",UPPER(TRIM(controle!E465))="TÉCNICA"),"TÉCNICA",SUBSTITUTE(UPPER(TRIM(controle!E465)),"SWICHER","SWITCHER")))) -> ALMOXARIFADO | C462: =IF(TRIM(controle!K465)="","Não informado",IF(ISNUMBER(SEARCH("DESCARTE",UPPER(controle!K465))),"Descarte",IF(ISNUMBER(SEARCH("INATIVO",UPPER(controle!K465))),"Inativo",IF(OR(ISNUMBER(SEARCH("BOM",UPPER(controle!K465))),ISNUMBER(SEARCH("OK",UPPER(controle!K465)))),"Bom/OK","Outros")))) -> Bom/OK | D462: =IF(TRIM(controle!G465)="","Não informado",UPPER(TRIM(controle!G465))) -> GRANDSTREAM
A463: =IF(TRIM(controle!A466)="","Não informado",IF(LEFT(UPPER(TRIM(controle!A466)),7)="MONITOR","Monitores",IF(OR(LEFT(UPPER(TRIM(controle!A466)),7)="DESKTOP",UPPER(TRIM(controle!A466))="MICRO",LEFT(UPPER(TRIM(controle!A466)),7)="MONTADO"),"Desktops/Micros",IF(LEFT(UPPER(TRIM(controle!A466)),8)="NOTEBOOK","Notebooks",IF(LEFT(UPPER(TRIM(controle!A466)),10)="IMPRESSORA","Impressoras",IF(LEFT(UPPER(TRIM(controle!A466)),8)="TELEFONE","Telefonia","Outros")))))) -> Telefonia | B463: =IF(TRIM(controle!E466)="","Sem departamento",IF(OR(UPPER(TRIM(controle!E466))="TI",UPPER(TRIM(controle!E466))="T.I"),"T.I",IF(OR(UPPER(TRIM(controle!E466))="TECNICA",UPPER(TRIM(controle!E466))="TÉCNICA"),"TÉCNICA",SUBSTITUTE(UPPER(TRIM(controle!E466)),"SWICHER","SWITCHER")))) -> AUDIO HIBRIDA | C463: =IF(TRIM(controle!K466)="","Não informado",IF(ISNUMBER(SEARCH("DESCARTE",UPPER(controle!K466))),"Descarte",IF(ISNUMBER(SEARCH("INATIVO",UPPER(controle!K466))),"Inativo",IF(OR(ISNUMBER(SEARCH("BOM",UPPER(controle!K466))),ISNUMBER(SEARCH("OK",UPPER(controle!K466)))),"Bom/OK","Outros")))) -> Bom/OK | D463: =IF(TRIM(controle!G466)="","Não informado",UPPER(TRIM(controle!G466))) -> GRANDSTREAM
A464: =IF(TRIM(controle!A467)="","Não informado",IF(LEFT(UPPER(TRIM(controle!A467)),7)="MONITOR","Monitores",IF(OR(LEFT(UPPER(TRIM(controle!A467)),7)="DESKTOP",UPPER(TRIM(controle!A467))="MICRO",LEFT(UPPER(TRIM(controle!A467)),7)="MONTADO"),"Desktops/Micros",IF(LEFT(UPPER(TRIM(controle!A467)),8)="NOTEBOOK","Notebooks",IF(LEFT(UPPER(TRIM(controle!A467)),10)="IMPRESSORA","Impressoras",IF(LEFT(UPPER(TRIM(controle!A467)),8)="TELEFONE","Telefonia","Outros")))))) -> Telefonia | B464: =IF(TRIM(controle!E467)="","Sem departamento",IF(OR(UPPER(TRIM(controle!E467))="TI",UPPER(TRIM(controle!E467))="T.I"),"T.I",IF(OR(UPPER(TRIM(controle!E467))="TECNICA",UPPER(TRIM(controle!E467))="TÉCNICA"),"TÉCNICA",SUBSTITUTE(UPPER(TRIM(controle!E467)),"SWICHER","SWITCHER")))) -> CAMARIM | C464: =IF(TRIM(controle!K467)="","Não informado",IF(ISNUMBER(SEARCH("DESCARTE",UPPER(controle!K467))),"Descarte",IF(ISNUMBER(SEARCH("INATIVO",UPPER(controle!K467))),"Inativo",IF(OR(ISNUMBER(SEARCH("BOM",UPPER(controle!K467))),ISNUMBER(SEARCH("OK",UPPER(controle!K467)))),"Bom/OK","Outros")))) -> Bom/OK | D464: =IF(TRIM(controle!G467)="","Não informado",UPPER(TRIM(controle!G467))) -> GRANDSTREAM
A465: =IF(TRIM(controle!A468)="","Não informado",IF(LEFT(UPPER(TRIM(controle!A468)),7)="MONITOR","Monitores",IF(OR(LEFT(UPPER(TRIM(controle!A468)),7)="DESKTOP",UPPER(TRIM(controle!A468))="MICRO",LEFT(UPPER(TRIM(controle!A468)),7)="MONTADO"),"Desktops/Micros",IF(LEFT(UPPER(TRIM(controle!A468)),8)="NOTEBOOK","Notebooks",IF(LEFT(UPPER(TRIM(controle!A468)),10)="IMPRESSORA","Impressoras",IF(LEFT(UPPER(TRIM(controle!A468)),8)="TELEFONE","Telefonia","Outros")))))) -> Telefonia | B465: =IF(TRIM(controle!E468)="","Sem departamento",IF(OR(UPPER(TRIM(controle!E468))="TI",UPPER(TRIM(controle!E468))="T.I"),"T.I",IF(OR(UPPER(TRIM(controle!E468))="TECNICA",UPPER(TRIM(controle!E468))="TÉCNICA"),"TÉCNICA",SUBSTITUTE(UPPER(TRIM(controle!E468)),"SWICHER","SWITCHER")))) -> COMERCIAL | C465: =IF(TRIM(controle!K468)="","Não informado",IF(ISNUMBER(SEARCH("DESCARTE",UPPER(controle!K468))),"Descarte",IF(ISNUMBER(SEARCH("INATIVO",UPPER(controle!K468))),"Inativo",IF(OR(ISNUMBER(SEARCH("BOM",UPPER(controle!K468))),ISNUMBER(SEARCH("OK",UPPER(controle!K468)))),"Bom/OK","Outros")))) -> Bom/OK | D465: =IF(TRIM(controle!G468)="","Não informado",UPPER(TRIM(controle!G468))) -> GRANDSTREAM
A466: =IF(TRIM(controle!A469)="","Não informado",IF(LEFT(UPPER(TRIM(controle!A469)),7)="MONITOR","Monitores",IF(OR(LEFT(UPPER(TRIM(controle!A469)),7)="DESKTOP",UPPER(TRIM(controle!A469))="MICRO",LEFT(UPPER(TRIM(controle!A469)),7)="MONTADO"),"Desktops/Micros",IF(LEFT(UPPER(TRIM(controle!A469)),8)="NOTEBOOK","Notebooks",IF(LEFT(UPPER(TRIM(controle!A469)),10)="IMPRESSORA","Impressoras",IF(LEFT(UPPER(TRIM(controle!A469)),8)="TELEFONE","Telefonia","Outros")))))) -> Telefonia | B466: =IF(TRIM(controle!E469)="","Sem departamento",IF(OR(UPPER(TRIM(controle!E469))="TI",UPPER(TRIM(controle!E469))="T.I"),"T.I",IF(OR(UPPER(TRIM(controle!E469))="TECNICA",UPPER(TRIM(controle!E469))="TÉCNICA"),"TÉCNICA",SUBSTITUTE(UPPER(TRIM(controle!E469)),"SWICHER","SWITCHER")))) -> COMERCIAL | C466: =IF(TRIM(controle!K469)="","Não informado",IF(ISNUMBER(SEARCH("DESCARTE",UPPER(controle!K469))),"Descarte",IF(ISNUMBER(SEARCH("INATIVO",UPPER(controle!K469))),"Inativo",IF(OR(ISNUMBER(SEARCH("BOM",UPPER(controle!K469))),ISNUMBER(SEARCH("OK",UPPER(controle!K469)))),"Bom/OK","Outros")))) -> Bom/OK | D466: =IF(TRIM(controle!G469)="","Não informado",UPPER(TRIM(controle!G469))) -> GRANDSTREAM
A467: =IF(TRIM(controle!A470)="","Não informado",IF(LEFT(UPPER(TRIM(controle!A470)),7)="MONITOR","Monitores",IF(OR(LEFT(UPPER(TRIM(controle!A470)),7)="DESKTOP",UPPER(TRIM(controle!A470))="MICRO",LEFT(UPPER(TRIM(controle!A470)),7)="MONTADO"),"Desktops/Micros",IF(LEFT(UPPER(TRIM(controle!A470)),8)="NOTEBOOK","Notebooks",IF(LEFT(UPPER(TRIM(controle!A470)),10)="IMPRESSORA","Impressoras",IF(LEFT(UPPER(TRIM(controle!A470)),8)="TELEFONE","Telefonia","Outros")))))) -> Telefonia | B467: =IF(TRIM(controle!E470)="","Sem departamento",IF(OR(UPPER(TRIM(controle!E470))="TI",UPPER(TRIM(controle!E470))="T.I"),"T.I",IF(OR(UPPER(TRIM(controle!E470))="TECNICA",UPPER(TRIM(controle!E470))="TÉCNICA"),"TÉCNICA",SUBSTITUTE(UPPER(TRIM(controle!E470)),"SWICHER","SWITCHER")))) -> CONTABILIDADE | C467: =IF(TRIM(controle!K470)="","Não informado",IF(ISNUMBER(SEARCH("DESCARTE",UPPER(controle!K470))),"Descarte",IF(ISNUMBER(SEARCH("INATIVO",UPPER(controle!K470))),"Inativo",IF(OR(ISNUMBER(SEARCH("BOM",UPPER(controle!K470))),ISNUMBER(SEARCH("OK",UPPER(controle!K470)))),"Bom/OK","Outros")))) -> Bom/OK | D467: =IF(TRIM(controle!G470)="","Não informado",UPPER(TRIM(controle!G470))) -> GRANDSTREAM
A468: =IF(TRIM(controle!A471)="","Não informado",IF(LEFT(UPPER(TRIM(controle!A471)),7)="MONITOR","Monitores",IF(OR(LEFT(UPPER(TRIM(controle!A471)),7)="DESKTOP",UPPER(TRIM(controle!A471))="MICRO",LEFT(UPPER(TRIM(controle!A471)),7)="MONTADO"),"Desktops/Micros",IF(LEFT(UPPER(TRIM(controle!A471)),8)="NOTEBOOK","Notebooks",IF(LEFT(UPPER(TRIM(controle!A471)),10)="IMPRESSORA","Impressoras",IF(LEFT(UPPER(TRIM(controle!A471)),8)="TELEFONE","Telefonia","Outros")))))) -> Telefonia | B468: =IF(TRIM(controle!E471)="","Sem departamento",IF(OR(UPPER(TRIM(controle!E471))="TI",UPPER(TRIM(controle!E471))="T.I"),"T.I",IF(OR(UPPER(TRIM(controle!E471))="TECNICA",UPPER(TRIM(controle!E471))="TÉCNICA"),"TÉCNICA",SUBSTITUTE(UPPER(TRIM(controle!E471)),"SWICHER","SWITCHER")))) -> CONTABILIDADE | C468: =IF(TRIM(controle!K471)="","Não informado",IF(ISNUMBER(SEARCH("DESCARTE",UPPER(controle!K471))),"Descarte",IF(ISNUMBER(SEARCH("INATIVO",UPPER(controle!K471))),"Inativo",IF(OR(ISNUMBER(SEARCH("BOM",UPPER(controle!K471))),ISNUMBER(SEARCH("OK",UPPER(controle!K471)))),"Bom/OK","Outros")))) -> Bom/OK | D468: =IF(TRIM(controle!G471)="","Não informado",UPPER(TRIM(controle!G471))) -> GRANDSTREAM
A469: =IF(TRIM(controle!A472)="","Não informado",IF(LEFT(UPPER(TRIM(controle!A472)),7)="MONITOR","Monitores",IF(OR(LEFT(UPPER(TRIM(controle!A472)),7)="DESKTOP",UPPER(TRIM(controle!A472))="MICRO",LEFT(UPPER(TRIM(controle!A472)),7)="MONTADO"),"Desktops/Micros",IF(LEFT(UPPER(TRIM(controle!A472)),8)="NOTEBOOK","Notebooks",IF(LEFT(UPPER(TRIM(controle!A472)),10)="IMPRESSORA","Impressoras",IF(LEFT(UPPER(TRIM(controle!A472)),8)="TELEFONE","Telefonia","Outros")))))) -> Telefonia | B469: =IF(TRIM(controle!E472)="","Sem departamento",IF(OR(UPPER(TRIM(controle!E472))="TI",UPPER(TRIM(controle!E472))="T.I"),"T.I",IF(OR(UPPER(TRIM(controle!E472))="TECNICA",UPPER(TRIM(controle!E472))="TÉCNICA"),"TÉCNICA",SUBSTITUTE(UPPER(TRIM(controle!E472)),"SWICHER","SWITCHER")))) -> CONTROLADORIA | C469: =IF(TRIM(controle!K472)="","Não informado",IF(ISNUMBER(SEARCH("DESCARTE",UPPER(controle!K472))),"Descarte",IF(ISNUMBER(SEARCH("INATIVO",UPPER(controle!K472))),"Inativo",IF(OR(ISNUMBER(SEARCH("BOM",UPPER(controle!K472))),ISNUMBER(SEARCH("OK",UPPER(controle!K472)))),"Bom/OK","Outros")))) -> Bom/OK | D469: =IF(TRIM(controle!G472)="","Não informado",UPPER(TRIM(controle!G472))) -> GRANDSTREAM
A470: =IF(TRIM(controle!A473)="","Não informado",IF(LEFT(UPPER(TRIM(controle!A473)),7)="MONITOR","Monitores",IF(OR(LEFT(UPPER(TRIM(controle!A473)),7)="DESKTOP",UPPER(TRIM(controle!A473))="MICRO",LEFT(UPPER(TRIM(controle!A473)),7)="MONTADO"),"Desktops/Micros",IF(LEFT(UPPER(TRIM(controle!A473)),8)="NOTEBOOK","Notebooks",IF(LEFT(UPPER(TRIM(controle!A473)),10)="IMPRESSORA","Impressoras",IF(LEFT(UPPER(TRIM(controle!A473)),8)="TELEFONE","Telefonia","Outros")))))) -> Telefonia | B470: =IF(TRIM(controle!E473)="","Sem departamento",IF(OR(UPPER(TRIM(controle!E473))="TI",UPPER(TRIM(controle!E473))="T.I"),"T.I",IF(OR(UPPER(TRIM(controle!E473))="TECNICA",UPPER(TRIM(controle!E473))="TÉCNICA"),"TÉCNICA",SUBSTITUTE(UPPER(TRIM(controle!E473)),"SWICHER","SWITCHER")))) -> COPA | C470: =IF(TRIM(controle!K473)="","Não informado",IF(ISNUMBER(SEARCH("DESCARTE",UPPER(controle!K473))),"Descarte",IF(ISNUMBER(SEARCH("INATIVO",UPPER(controle!K473))),"Inativo",IF(OR(ISNUMBER(SEARCH("BOM",UPPER(controle!K473))),ISNUMBER(SEARCH("OK",UPPER(controle!K473)))),"Bom/OK","Outros")))) -> Bom/OK | D470: =IF(TRIM(controle!G473)="","Não informado",UPPER(TRIM(controle!G473))) -> GRANDSTREAM
... A511: =IF(TRIM(controle!A514)="","Não informado",IF(LEFT(UPPER(TRIM(controle!A514)),7)="MONITOR","Monitores",IF(OR(LEFT(UPPER(TRIM(controle!A514)),7)="DESKTOP",UPPER(TRIM(controle!A514))="MICRO",LEFT(UPPER(TRIM(controle!A514)),7)="MONTADO"),"Desktops/Micros",IF(LEFT(UPPER(TRIM(controle!A514)),8)="NOTEBOOK","Notebooks",IF(LEFT(UPPER(TRIM(controle!A514)),10)="IMPRESSORA","Impressoras",IF(LEFT(UPPER(TRIM(controle!A514)),8)="TELEFONE","Telefonia","Outros")))))) -> Telefonia | B511: =IF(TRIM(controle!E514)="","Sem departamento",IF(OR(UPPER(TRIM(controle!E514))="TI",UPPER(TRIM(controle!E514))="T.I"),"T.I",IF(OR(UPPER(TRIM(controle!E514))="TECNICA",UPPER(TRIM(controle!E514))="TÉCNICA"),"TÉCNICA",SUBSTITUTE(UPPER(TRIM(controle!E514)),"SWICHER","SWITCHER")))) -> T.I | C511: =IF(TRIM(controle!K514)="","Não informado",IF(ISNUMBER(SEARCH("DESCARTE",UPPER(controle!K514))),"Descarte",IF(ISNUMBER(SEARCH("INATIVO",UPPER(controle!K514))),"Inativo",IF(OR(ISNUMBER(SEARCH("BOM",UPPER(controle!K514))),ISNUMBER(SEARCH("OK",UPPER(controle!K514)))),"Bom/OK","Outros")))) -> Bom/OK | D511: =IF(TRIM(controle!G514)="","Não informado",UPPER(TRIM(controle!G514))) -> GRANDSTREAM

Sheet Índice Pesquisa
A1: Aba | B1: Célula | C1: Campo | D1: Conteúdo | F1: Todas
A2: CENTRAL | B2: A1 | C2: Coluna A | D2: INVENTARIO DO T.I | F2: CENTRAL
A3: CENTRAL | B3: A4 | C3: Coluna A | D3: TOTAL DE ATIVOS | F3: Listas
A4: CENTRAL | B4: D4 | C4: Coluna D | D4: DEPARTAMENTOS | F4: Responsável
A5: CENTRAL | B5: G4 | C5: Coluna G | D5: COM RESPONSÁVEL | F5: Monitores
A6: CENTRAL | B6: J4 | C6: Coluna J | D6: COM HOSTNAME | F6: celular
A7: CENTRAL | B7: A5 | C7: Coluna A | D7: 510 | F7: conectores
A8: CENTRAL | B8: D5 | C8: Coluna D | D8: 58 | F8: A+
A9: CENTRAL | B9: G5 | C9: Coluna G | D9: 438 | F9: Dados Gráfico
A10: CENTRAL | B10: J5 | C10: Coluna J | D10: 340 | F10: Dados Dashboard
A11: Listas | B11: A1 | C11: Categoria | D11: Categoria | F11: TESTE
A12: Listas | B12: B1 | C12: Modelo | D12: Modelo
A13: Listas | B13: C1 | C13: Hostname | D13: Hostname
A14: Listas | B14: D1 | C14: Patrimônio | D14: Patrimônio
A15: Listas | B15: E1 | C15: Departamento | D15: Departamento
A16: Listas | B16: F1 | C16: Responsável | D16: Responsável
A17: Listas | B17: G1 | C17: Marca | D17: Marca
A18: Listas | B18: H1 | C18: Serial | D18: Serial
A19: Listas | B19: I1 | C19: Ramal | D19: Ramal
A20: Listas | B20: J1 | C20: IP | D20: IP
A21: Listas | B21: K1 | C21: Observação | D21: Observação
A22: Listas | B22: L1 | C22: CPU | D22: CPU
A23: Listas | B23: M1 | C23: Disco | D23: Disco
... A32: Listas | B32: C2 | C32: Hostname | D32: 4TH31H4
A33: Listas | B33: D2 | C33: Patrimônio | D33: 889
A34: Listas | B34: E2 | C34: Departamento | D34: Administração
A35: Listas | B35: F2 | C35: Responsável | D35: SABRINA CARVALHO DA SILVA
A36: Listas | B36: G2 | C36: Marca | D36: Dell
A37: Listas | B37: K2 | C37: Observação | D37: Status: Bom
A38: Listas | B38: L2 | C38: CPU | D38: Intel Core i5-14500T
A39: Listas | B39: M2 | C39: Disco | D39: 512GB SSD NVME
A40: Listas | B40: N2 | C40: RAM | D40: 16GB DDR5
A41: Listas | B41: P2 | C41: Status | D41: OK
A42: Listas | B42: Q2 | C42: Chave de auditoria | D42: #REF!
A43: Listas | B43: R2 | C43: VERIFICAÇÃO | D43: 46266
A44: Listas | B44: A3 | C44: Categoria | D44: Micro
A45: Listas | B45: B3 | C45: Modelo | D45: DELL PRO MICRO QCM1250
A46: Listas | B46: C3 | C46: Hostname | D46: GZJ31H4
A47: Listas | B47: D3 | C47: Patrimônio | D47: 838
A48: Listas | B48: E3 | C48: Departamento | D48: Administração
A49: Listas | B49: F3 | C49: Responsável | D49: DAISY DA SILVA RUSSO
A50: Listas | B50: G3 | C50: Marca | D50: Dell
A51: Listas | B51: K3 | C51: Observação | D51: Status: Bom
A52: Listas | B52: L3 | C52: CPU | D52: Intel Core i5-14500T
A53: Listas | B53: M3 | C53: Disco | D53: 512GB SSD NVME
A54: Listas | B54: N3 | C54: RAM | D54: 16GB DDR5
A55: Listas | B55: P3 | C55: Status | D55: OK
A56: Listas | B56: Q3 | C56: Chave de auditoria | D56: #REF!
A57: Listas | B57: R3 | C57: VERIFICAÇÃO | D57: 46266
A58: Listas | B58: A4 | C58: Categoria | D58: Micro
A59: Listas | B59: B4 | C59: Modelo | D59: DELL PRO MICRO QCM1250
A60: Listas | B60: C4 | C60: Hostname | D60: JTH31H4
A61: Listas | B61: D4 | C61: Patrimônio | D61: 830
A62: Listas | B62: E4 | C62: Departamento | D62: Administração
A63: Listas | B63: F4 | C63: Responsável | D63: AMANDA GOMES PACHECO SEVERO
A64: Listas | B64: G4 | C64: Marca | D64: Dell
A65: Listas | B65: K4 | C65: Observação | D65: Status: Bom
A66: Listas | B66: L4 | C66: CPU | D66: Intel Core i5-14500T
A67: Listas | B67: M4 | C67: Disco | D67: 512GB SSD NVME
A68: Listas | B68: N4 | C68: RAM | D68: 16GB DDR5
A69: Listas | B69: P4 | C69: Status | D69: OK
A70: Listas | B70: Q4 | C70: Chave de auditoria | D70: #REF!
A71: Listas | B71: R4 | C71: VERIFICAÇÃO | D71: 46266
A72: Listas | B72: A5 | C72: Categoria | D72: Impressora
A73: Listas | B73: B5 | C73: Modelo | D73: WorkCentre 3345
A74: Listas | B74: D5 | C74: Patrimônio | D74: 8234
A75: Listas | B75: E5 | C75: Departamento | D75: Administrativo
A76: Listas | B76: G5 | C76: Marca | D76: XEROX
A77: Listas | B77: H5 | C77: Serial | D77: 3BT806127
A78: Listas | B78: J5 | C78: IP | D78: 10.28.70.21
A79: Listas | B79: K5 | C79: Observação | D79: Status: Bom
A80: Listas | B80: P5 | C80: Status | D80: OK
A81: Listas | B81: Q5 | C81: Chave de auditoria | D81: #REF!
A82: Listas | B82: R5 | C82: VERIFICAÇÃO | D82: 46266
A83: Listas | B83: A6 | C83: Categoria | D83: Micro
A84: Listas | B84: B6 | C84: Modelo | D84: DELL PRO MICRO QCM1250
A85: Listas | B85: C6 | C85: Hostname | D85: F2K31H4
A86: Listas | B86: D6 | C86: Patrimônio | D86: 807
A87: Listas | B87: E6 | C87: Departamento | D87: Administrativo
A88: Listas | B88: F6 | C88: Responsável | D88: ADRIANO BARBOSA RESTA
A89: Listas | B89: G6 | C89: Marca | D89: Dell
A90: Listas | B90: K6 | C90: Observação | D90: Status: Bom
A91: Listas | B91: L6 | C91: CPU | D91: Intel Core i5-14500T
A92: Listas | B92: M6 | C92: Disco | D92: 512GB SSD NVME
A93: Listas | B93: N6 | C93: RAM | D93: 16GB DDR5
A94: Listas | B94: P6 | C94: Status | D94: OK
A95: Listas | B95: Q6 | C95: Chave de auditoria | D95: #REF!
A96: Listas | B96: R6 | C96: VERIFICAÇÃO | D96: 46266
A97: Listas | B97: A7 | C97: Categoria | D97: Monitor 18.5”, HD , 60Hz
A98: Listas | B98: B7 | C98: Modelo | D98: 9P1E
A99: Listas | B99: C7 | C99: Hostname | D99: 3
A100: Listas | B100: D7 | C100: Patrimônio | D100: 668
A101: Listas | B101: E7 | C101: Departamento | D101: Administrativo
A102: Listas | B102: F7 | C102: Responsável | D102: AMANDA PACHECO
A103: Listas | B103: G7 | C103: Marca | D103: Dell
A104: Listas | B104: K7 | C104: Observação | D104: Status: Bom
A105: Listas | B105: P7 | C105: Status | D105: OK
A106: Listas | B106: Q7 | C106: Chave de auditoria | D106: #REF!
A107: Listas | B107: R7 | C107: VERIFICAÇÃO | D107: 46266
A108: Listas | B108: A8 | C108: Categoria | D108: Monitor 18.5”, HD , 60Hz
...

Sheet Índice Equipamentos
A1: Equipamento | B1: Responsável cadastrado | C1: Responsável relacionado | D1: Departamento | E1: Classificação | F1: Modelo | G1: Marca | H1: Patrimônio | I1: Hostname / Número | J1: Status | K1: Condição | L1: CPU / Processador | M1: Disco / Armazenamento | N1: RAM | O1: IP / Ramal | P1: Observação / Avaria | Q1: Detalhes técnicos | R1: Origem | S1: Localização | T1: Termos de pesquisa
A2: Desktop | B2: SABRINA CARVALHO DA SILVA | C2: SABRINA CARVALHO DA SILVA | D2: Administração | E2: Micro | F2: DELL PRO MICRO QCM1250 | G2: Dell | H2: 889 | I2: 4TH31H4 | J2: OK | K2: Status: Bom | L2: Intel Core i5-14500T | M2: 512GB SSD NVME | N2: 16GB DDR5 | P2: Status: Bom | R2: Listas | S2: Listas!A2:R2 | T2: Desktop | SABRINA CARVALHO DA SILVA | SABRINA CARVALHO DA SILVA | Administração | Micro | DELL PRO MICRO QCM1250 | Dell | 889 | 4TH31H4 | OK | Status: Bom | Intel Core i5-14500T | 512GB SSD NVME | 16GB DDR5 | | Status: Bom | | Listas | Listas!A2:R2
A3: Desktop | B3: DAISY DA SILVA RUSSO | C3: DAISY DA SILVA RUSSO | D3: Administração | E3: Micro | F3: DELL PRO MICRO QCM1250 | G3: Dell | H3: 838 | I3: GZJ31H4 | J3: OK | K3: Status: Bom | L3: Intel Core i5-14500T | M3: 512GB SSD NVME | N3: 16GB DDR5 | P3: Status: Bom | R3: Listas | S3: Listas!A3:R3 | T3: Desktop | DAISY DA SILVA RUSSO | DAISY DA SILVA RUSSO | Administração | Micro | DELL PRO MICRO QCM1250 | Dell | 838 | GZJ31H4 | OK | Status: Bom | Intel Core i5-14500T | 512GB SSD NVME | 16GB DDR5 | | Status: Bom | | Listas | Listas!A3:R3
A4: Desktop | B4: AMANDA GOMES PACHECO SEVERO | C4: AMANDA GOMES PACHECO SEVERO | D4: Administração | E4: Micro | F4: DELL PRO MICRO QCM1250 | G4: Dell | H4: 830 | I4: JTH31H4 | J4: OK | K4: Status: Bom | L4: Intel Core i5-14500T | M4: 512GB SSD NVME | N4: 16GB DDR5 | P4: Status: Bom | R4: Listas | S4: Listas!A4:R4 | T4: Desktop | AMANDA GOMES PACHECO SEVERO | AMANDA GOMES PACHECO SEVERO | Administração | Micro | DELL PRO MICRO QCM1250 | Dell | 830 | JTH31H4 | OK | Status: Bom | Intel Core i5-14500T | 512GB SSD NVME | 16GB DDR5 | | Status: Bom | | Listas | Listas!A4:R4
A5: Impressora | C5: Sem responsável | D5: Administrativo | E5: Impressora | F5: WorkCentre 3345 | G5: XEROX | H5: 8234 | I5: 3BT806127 | J5: OK | K5: Status: Bom | O5: IP: 10.28.70.21 | P5: Status: Bom | R5: Listas | S5: Listas!A5:R5 | T5: Impressora | | Sem responsável | Administrativo | Impressora | WorkCentre 3345 | XEROX | 8234 | 3BT806127 | OK | Status: Bom | | | | IP: 10.28.70.21 | Status: Bom | | Listas | Listas!A5:R5
A6: Desktop | B6: ADRIANO BARBOSA RESTA | C6: ADRIANO BARBOSA RESTA | D6: Administrativo | E6: Micro | F6: DELL PRO MICRO QCM1250 | G6: Dell | H6: 807 | I6: F2K31H4 | J6: OK | K6: Status: Bom | L6: Intel Core i5-14500T | M6: 512GB SSD NVME | N6: 16GB DDR5 | P6: Status: Bom | R6: Listas | S6: Listas!A6:R6 | T6: Desktop | ADRIANO BARBOSA RESTA | ADRIANO BARBOSA RESTA | Administrativo | Micro | DELL PRO MICRO QCM1250 | Dell | 807 | F2K31H4 | OK | Status: Bom | Intel Core i5-14500T | 512GB SSD NVME | 16GB DDR5 | | Status: Bom | | Listas | Listas!A6:R6
A7: Monitor | B7: AMANDA PACHECO | C7: AMANDA GOMES PACHECO SEVERO | D7: Administrativo | E7: Monitor 18.5”, HD , 60Hz | F7: 9P1E | G7: Dell | H7: 668 | I7: 3 | J7: OK | K7: Status: Bom | P7: Status: Bom | R7: Listas | S7: Listas!A7:R7 | T7: Monitor | AMANDA PACHECO | AMANDA GOMES PACHECO SEVERO | Administrativo | Monitor 18.5”, HD , 60Hz | 9P1E | Dell | 668 | 3 | OK | Status: Bom | | | | | Status: Bom | | Listas | Listas!A7:R7
A8: Monitor | B8: AMANDA PACHECO | C8: AMANDA GOMES PACHECO SEVERO | D8: Administrativo | E8: Monitor 18.5”, HD , 60Hz | F8: 9P1E | G8: Dell | H8: 677 | I8: 4 | J8: OK | K8: Status: Bom | P8: Status: Bom | R8: Listas | S8: Listas!A8:R8 | T8: Monitor | AMANDA PACHECO | AMANDA GOMES PACHECO SEVERO | Administrativo | Monitor 18.5”, HD , 60Hz | 9P1E | Dell | 677 | 4 | OK | Status: Bom | | | | | Status: Bom | | Listas | Listas!A8:R8
A9: Monitor | B9: SABRINA | C9: SABRINA CARVALHO DA SILVA | D9: Administrativo | E9: Monitor 18.5”, HD , 60Hz | F9: 9P1E | G9: Dell | H9: 663 | I9: 5 | J9: OK | K9: Status: Bom | P9: Status: Bom | R9: Listas | S9: Listas!A9:R9 | T9: Monitor | SABRINA | SABRINA CARVALHO DA SILVA | Administrativo | Monitor 18.5”, HD , 60Hz | 9P1E | Dell | 663 | 5 | OK | Status: Bom | | | | | Status: Bom | | Listas | Listas!A9:R9
A10: Monitor | B10: SABRINA | C10: SABRINA CARVALHO DA SILVA | D10: Administrativo | E10: Monitor 18.5”, HD , 60Hz | F10: 9P1E | G10: Dell | H10: 664 | I10: 6 | J10: OK | K10: Status: Bom | P10: Status: Bom | R10: Listas | S10: Listas!A10:R10 | T10: Monitor | SABRINA | SABRINA CARVALHO DA SILVA | Administrativo | Monitor 18.5”, HD , 60Hz | 9P1E | Dell | 664 | 6 | OK | Status: Bom | | | | | Status: Bom | | Listas | Listas!A10:R10
A11: Monitor | B11: DAISY | C11: DAISY DA SILVA RUSSO | D11: Administrativo | E11: Monitor 18.5”, HD , 60Hz | F11: 9P1E | G11: Dell | H11: 683 | I11: 7 | J11: OK | K11: Status: Bom | P11: Status: Bom | R11: Listas | S11: Listas!A11:R11 | T11: Monitor | DAISY | DAISY DA SILVA RUSSO | Administrativo | Monitor 18.5”, HD , 60Hz | 9P1E | Dell | 683 | 7 | OK | Status: Bom | | | | | Status: Bom | | Listas | Listas!A11:R11
A12: Monitor | B12: DAISY | C12: DAISY DA SILVA RUSSO | D12: Administrativo | E12: Monitor 18.5”, HD , 60Hz | F12: 9P1E | G12: Dell | H12: 681 | I12: 8 | J12: OK | K12: Status: Bom | P12: Status: Bom | R12: Listas | S12: Listas!A12:R12 | T12: Monitor | DAISY | DAISY DA SILVA RUSSO | Administrativo | Monitor 18.5”, HD , 60Hz | 9P1E | Dell | 681 | 8 | OK | Status: Bom | | | | | Status: Bom | | Listas | Listas!A12:R12
A13: Monitor | B13: ADRIANO RESTA | C13: ADRIANO BARBOSA RESTA | D13: Administrativo | E13: Monitor 18.5”, HD , 60Hz | F13: 9P1E | G13: Dell | H13: 667 | I13: 9 | J13: OK | K13: Status: Bom | P13: Status: Bom | R13: Listas | S13: Listas!A13:R13 | T13: Monitor | ADRIANO RESTA | ADRIANO BARBOSA RESTA | Administrativo | Monitor 18.5”, HD , 60Hz | 9P1E | Dell | 667 | 9 | OK | Status: Bom | | | | | Status: Bom | | Listas | Listas!A13:R13
A14: Monitor | B14: ADRIANO RESTA | C14: ADRIANO BARBOSA RESTA | D14: Administrativo | E14: Monitor 18.5”, HD , 60Hz | F14: 9P1E | G14: Dell | H14: 676 | I14: 10 | J14: OK | K14: Status: Bom | P14: Status: Bom | R14: Listas | S14: Listas!A14:R14 | T14: Monitor | ADRIANO RESTA | ADRIANO BARBOSA RESTA | Administrativo | Monitor 18.5”, HD , 60Hz | 9P1E | Dell | 676 | 10 | OK | Status: Bom | | | | | Status: Bom | | Listas | Listas!A14:R14
